Workbook
Name BtuTable: SEDS_CONS_API!$A$1:$BK$307
Name BuildingList: 'Chart Controls'!$D$3:$D$6
Name DivisionList: 'Chart Controls'!$B$3:$B$12
Name EndUseList: 'Chart Controls'!$E$3:$E$22
Name ExpTable: SEDS_EXP_API!$A$1:$BK$307
Name FirstNEMSYrPlot: 'Year Selections'!$C$17
Name FuelList: 'Chart Controls'!$C$3:$C$10
Name LastHHStockYr: 'Year Selections'!$C$20
Name LastSEDSyr: 'Year Selections'!$C$11
Name NEMS_Internal_PriceYr: 'Year Selections'!$C$5
Name PivotData: SEDSDataPivots!$C$3:$G$54
Name Price_Base_yr: 'Year Selections'!$C$8
Name RECSYr: 'Year Selections'!$C$14
Name SelectedBuilding: 'Chart Controls'!$D$25
Name SelectedDivision: 'Chart Controls'!$B$25
Name SelectedEndUse: 'Chart Controls'!$E$25
Name SelectedFuel: 'Chart Controls'!$C$25
Name SourceDir: Menu!$D$4

Sheet Menu
B2: NEMS Residential Database
B4: Source for Files | D4: \\Nemsfs\k\output\aeo2026\cb2026\d021826b\p1
B5: RunDescription | D5: AEO2026 Reference Case
B6: RunID | D6: =IF(RIGHT(SourceDir,3)<>"\p1",MID(SourceDir,(FIND("|",SUBSTITUTE(SourceDir,"\","|",LEN(SourceDir)-LEN(SUBSTITUTE(SourceDir,"\",""))-1)))+1,((FIND("\",SourceDir,(FIND("|",SUBSTITUTE(SourceDir,"\","|",LEN(SourceDir)-LEN(SUBSTITUTE(SourceDir,"\",""))-1)))+1))-(FIND("|",SUBSTITUTE(SourceDir,"\","|",LEN(SourceDir)-LEN(SUBSTITUTE(SourceDir,"\",""))-1))))-1)&"."&RIGHT(SourceDir,8),MID(SourceDir,(FIND("|",SUBSTITUTE(SourceDir,"\","|",LEN(SourceDir)-LEN(SUBSTITUTE(SourceDir,"\",""))-2)))+1,((FIND("\",SourceDir,(FIND("|",SUBSTITUTE(SourceDir,"\","|",LEN(SourceDir)-LEN(SUBSTITUTE(SourceDir,"\",""))-2)))+1))-(FIND("|",SUBSTITUTE(SourceDir,"\","|",LEN(SourceDir)-LEN(SUBSTITUTE(SourceDir,"\",""))-2))))-1)&"."&MID(SourceDir,(FIND("|",SUBSTITUTE(SourceDir,"\","|",LEN(SourceDir)-LEN(SUBSTITUTE(SourceDir,"\",""))-1)))+1,((FIND("\",SourceDir,(FIND("|",SUBSTITUTE(SourceDir,"\","|",LEN(SourceDir)-LEN(SUBSTITUTE(SourceDir,"\",""))-1)))+1))-(FIND("|",SUBSTITUTE(SourceDir,"\","|",LEN(SourceDir)-LEN(SUBSTITUTE(SourceDir,"\",""))-1))))-1)) -> cb2026.d021826b
B7: Last Change | D7: Remove deprecated kerosene consumption; rename LPG fuel price as Propane

Sheet Summary Charts
B1: Summary Historical Data with NEMS Projections
B2: =Menu!D5 -> AEO2026 Reference Case
F3: Chart Selections: | I3: Census Division: | K3: ='Chart Data Staging'!C3 -> (All)
I4: Fuel: | K4: ='Chart Data Staging'!C4 -> Electricity
I5: Building: | K5: ='Chart Data Staging'!C5 -> (All)
I6: End Use: | K6: ='Chart Data Staging'!C6 -> (All)
B8: Selections are possible for which some of the chart variables are not defined. Rather than generating an error, the affected charts will display blank or zero data.

Sheet Chart Data Staging
B2: Selections:
B3: Division | C3: =[0]!SelectedDivision -> (All) | E3: =IF(C3="(all)",0,1) -> 0
B4: Fuel | C4: =[0]!SelectedFuel -> Electricity | E4: =IF(C4="(all)",0,1) -> 1
B5: Building | C5: =[0]!SelectedBuilding -> (All) | E5: =IF(C5="(all)",0,1) -> 0
B6: End Use | C6: =[0]!SelectedEndUse -> (All) | E6: =IF(C6="(all)",0,1) -> 0
B8: Deflator Base Year | D8: =Price_Base_yr -> 2023
B9: Price Conversion Factor | D9: =HLOOKUP(D8,Deflators!$D$2:$BG$5,3,0) -> 2.3034306
B11: Availability
B12: Division | C12: 1 | G12: 1
B13: Fuel | C13: 1 | G13: 1
B14: Building | C14: 0 | G14: 0
B15: EndUse | C15: 0 | G15: 0
B16: Plot? | C16: 1 | G16: =SUMPRODUCT(G12:G15,$E$3:$E$6)-SUM($E$3:$E$6)+1 -> 1
G19: Historical | H19: Projected | J19: Historical | K19: Projected | M19: Historical | N19: Projected | P19: Historical | Q19: Projected | S19: Historical | T19: Projected | V19: Historical | W19: Projected
C20: Historical | E20: Projected | G20: Consumption | H20: Consumption | J20: Stocks | K20: Housing Stock | M20: Floorspace | N20: Floorspace | P20: Intensity | Q20: Intensity | S20: Intensity | T20: Intensity | V20: Avg | W20: Avg
C21: Prices | E21: Prices | G21: Quad | H21: Quad | J21: mill units | K21: mill units | M21: bill sqft | N21: bill sqft | P21: MMBtu/HH | Q21: MMBtu/HH | S21: MMBtu/1000sqft | T21: MMBtu/1000sqft | V21: Sqft | W21: Sqft
B22: =SEDSDataPivots!B8 -> 1970 | C22: =IF($D22>LastSEDSyr,#N/A,SEDSDataPivots!I8) -> #N/A | D22: =B23-1 -> 1970 | G22: =IF(G$16<1,#N/A,IF($D22>LastSEDSyr,#N/A,SEDSDataPivots!D8))/10^6 -> 0
B23: =B22+1 -> 1971 | C23: =IF($D23>LastSEDSyr,#N/A,SEDSDataPivots!I9) -> #VALUE! | D23: =D22+1 -> 1971 | G23: =IF(G$16<1,#N/A,IF($D23>LastSEDSyr,#N/A,SEDSDataPivots!D9))/10^6 -> 0.001798
B24: =B23+1 -> 1972 | C24: =IF($D24>LastSEDSyr,#N/A,SEDSDataPivots!I10) -> #VALUE! | D24: =D23+1 -> 1972 | G24: =IF(G$16<1,#N/A,IF($D24>LastSEDSyr,#N/A,SEDSDataPivots!D10))/10^6 -> 0.00415
B25: =B24+1 -> 1973 | C25: =IF($D25>LastSEDSyr,#N/A,SEDSDataPivots!I11) -> #VALUE! | D25: =D24+1 -> 1973 | G25: =IF(G$16<1,#N/A,IF($D25>LastSEDSyr,#N/A,SEDSDataPivots!D11))/10^6 -> 0.002832
B26: =B25+1 -> 1974 | C26: =IF($D26>LastSEDSyr,#N/A,SEDSDataPivots!I12) -> #VALUE! | D26: =D25+1 -> 1974 | G26: =IF(G$16<1,#N/A,IF($D26>LastSEDSyr,#N/A,SEDSDataPivots!D12))/10^6 -> 0.004384
B27: =B26+1 -> 1975 | C27: =IF($D27>LastSEDSyr,#N/A,SEDSDataPivots!I13) -> #VALUE! | D27: =D26+1 -> 1975 | G27: =IF(G$16<1,#N/A,IF($D27>LastSEDSyr,#N/A,SEDSDataPivots!D13))/10^6 -> 0.002059
B28: =B27+1 -> 1976 | C28: =IF($D28>LastSEDSyr,#N/A,SEDSDataPivots!I14) -> #VALUE! | D28: =D27+1 -> 1976 | G28: =IF(G$16<1,#N/A,IF($D28>LastSEDSyr,#N/A,SEDSDataPivots!D14))/10^6 -> 0.004742
B29: =B28+1 -> 1977 | C29: =IF($D29>LastSEDSyr,#N/A,SEDSDataPivots!I15) -> #VALUE! | D29: =D28+1 -> 1977 | G29: =IF(G$16<1,#N/A,IF($D29>LastSEDSyr,#N/A,SEDSDataPivots!D15))/10^6 -> 0.005037
B30: =B29+1 -> 1978 | C30: =IF($D30>LastSEDSyr,#N/A,SEDSDataPivots!I16) -> #VALUE! | D30: =D29+1 -> 1978 | G30: =IF(G$16<1,#N/A,IF($D30>LastSEDSyr,#N/A,SEDSDataPivots!D16))/10^6 -> 0.005878
B31: =B30+1 -> 1979 | C31: =IF($D31>LastSEDSyr,#N/A,SEDSDataPivots!I17) -> #VALUE! | D31: =D30+1 -> 1979 | G31: =IF(G$16<1,#N/A,IF($D31>LastSEDSyr,#N/A,SEDSDataPivots!D17))/10^6 -> 0.003988
B32: =B31+1 -> 1980 | C32: =IF($D32>LastSEDSyr,#N/A,SEDSDataPivots!I18) -> #VALUE! | D32: =D31+1 -> 1980 | G32: =IF(G$16<1,#N/A,IF($D32>LastSEDSyr,#N/A,SEDSDataPivots!D18))/10^6 -> 0.004775
B33: =B32+1 -> 1981 | C33: =IF($D33>LastSEDSyr,#N/A,SEDSDataPivots!I19) -> #VALUE! | D33: =D32+1 -> 1981 | G33: =IF(G$16<1,#N/A,IF($D33>LastSEDSyr,#N/A,SEDSDataPivots!D19))/10^6 -> 0.005411
B34: =B33+1 -> 1982 | C34: =IF($D34>LastSEDSyr,#N/A,SEDSDataPivots!I20) -> #VALUE! | D34: =D33+1 -> 1982 | G34: =IF(G$16<1,#N/A,IF($D34>LastSEDSyr,#N/A,SEDSDataPivots!D20))/10^6 -> 0.005234
... B41: =B40+1 -> 1989 | C41: =IF($D41>LastSEDSyr,#N/A,SEDSDataPivots!I27) -> #VALUE! | D41: =D40+1 -> 1989 | G41: =IF(G$16<1,#N/A,IF($D41>LastSEDSyr,#N/A,SEDSDataPivots!D27))/10^6 -> 0.006788
B42: =B41+1 -> 1990 | C42: =IF($D42>LastSEDSyr,#N/A,SEDSDataPivots!I28) -> #VALUE! | D42: =D41+1 -> 1990 | E42: =IF($E$4=0,#N/A,IF(B42>=FirstNEMSYrPlot,GETPIVOTDATA("EQSTOCK",NEMSPriceFcast!$A$7,"YEAR",B42)*$D$9,#N/A)) -> #N/A | G42: =IF(G$16<1,#N/A,IF($D42>LastSEDSyr,#N/A,SEDSDataPivots!D28))/10^6 -> 0.018247 | H42: =IF(B42>=FirstNEMSYrPlot,GETPIVOTDATA("CONSUMPTION",NEMSConsFcast!$A$9,"YEAR",B42)/10^9,#N/A) -> #N/A | J42: =IFERROR(IF(GETPIVOTDATA("Sum of "&D42,'RECS Data'!$B$99)=0,#N/A,GETPIVOTDATA("Sum of "&D42,'RECS Data'!$B$99)),#N/A) -> 93.990964 | K42: =IF($B42>RECSYr,GETPIVOTDATA("HOUSEHOLDS",HousingStockTable!$A$12,"YEAR",B42)/10^6,#N/A) -> #N/A | M42: =IFERROR(IF(AND(B42<=RECSYr,GETPIVOTDATA("Sum of "&B42,'RECS Data'!$B$179)>0),GETPIVOTDATA("Sum of "&B42,'RECS Data'!$B$179),#N/A)/1000,#N/A) -> 147.49028 | N42: =IF($B42>RECSYr,GETPIVOTDATA("HOUSEHOLDS",SqftTable!$A$7,"YEAR",B42),#N/A)/1000 -> #N/A | P42: =IF(ISERROR(G42/J42*1000),#N/A,G42/J42*1000) -> 0.19413568 | Q42: =H42/K42*1000 -> #N/A | S42: =IFERROR(G42/M42*10^3,#N/A) -> 0.12371663 | T42: =H42/N42*1000 -> #N/A | V42: =IFERROR(M42*1000/J42,#N/A) -> 1569.1964 | W42: =N42*1000/K42 -> #N/A
B43: =B42+1 -> 1991 | C43: =IF($D43>LastSEDSyr,#N/A,SEDSDataPivots!I29) -> #VALUE! | D43: =D42+1 -> 1991 | E43: =IF($E$4=0,#N/A,IF(B43>=FirstNEMSYrPlot,GETPIVOTDATA("EQSTOCK",NEMSPriceFcast!$A$7,"YEAR",B43)*$D$9,#N/A)) -> #N/A | G43: =IF(G$16<1,#N/A,IF($D43>LastSEDSyr,#N/A,SEDSDataPivots!D29))/10^6 -> 0.022109 | H43: =IF(B43>=FirstNEMSYrPlot,GETPIVOTDATA("CONSUMPTION",NEMSConsFcast!$A$9,"YEAR",B43)/10^9,#N/A) -> #N/A | J43: =IFERROR(IF(GETPIVOTDATA("Sum of "&D43,'RECS Data'!$B$99)=0,#N/A,GETPIVOTDATA("Sum of "&D43,'RECS Data'!$B$99)),#N/A) -> #N/A | K43: =IF($B43>RECSYr,GETPIVOTDATA("HOUSEHOLDS",HousingStockTable!$A$12,"YEAR",B43)/10^6,#N/A) -> #N/A | M43: =IFERROR(IF(AND(B43<=RECSYr,GETPIVOTDATA("Sum of "&B43,'RECS Data'!$B$179)>0),GETPIVOTDATA("Sum of "&B43,'RECS Data'!$B$179),#N/A)/1000,#N/A) -> #N/A | N43: =IF($B43>RECSYr,GETPIVOTDATA("HOUSEHOLDS",SqftTable!$A$7,"YEAR",B43),#N/A)/1000 -> #N/A | P43: =IF(ISERROR(G43/J43*1000),#N/A,G43/J43*1000) -> #N/A | Q43: =H43/K43*1000 -> #N/A | S43: =IFERROR(G43/M43*10^3,#N/A) -> #N/A | T43: =H43/N43*1000 -> #N/A | V43: =IFERROR(M43*1000/J43,#N/A) -> #N/A | W43: =N43*1000/K43 -> #N/A
B44: =B43+1 -> 1992 | C44: =IF($D44>LastSEDSyr,#N/A,SEDSDataPivots!I30) -> #VALUE! | D44: =D43+1 -> 1992 | E44: =IF($E$4=0,#N/A,IF(B44>=FirstNEMSYrPlot,GETPIVOTDATA("EQSTOCK",NEMSPriceFcast!$A$7,"YEAR",B44)*$D$9,#N/A)) -> #N/A | G44: =IF(G$16<1,#N/A,IF($D44>LastSEDSyr,#N/A,SEDSDataPivots!D30))/10^6 -> 0.014745 | H44: =IF(B44>=FirstNEMSYrPlot,GETPIVOTDATA("CONSUMPTION",NEMSConsFcast!$A$9,"YEAR",B44)/10^9,#N/A) -> #N/A | J44: =IFERROR(IF(GETPIVOTDATA("Sum of "&D44,'RECS Data'!$B$99)=0,#N/A,GETPIVOTDATA("Sum of "&D44,'RECS Data'!$B$99)),#N/A) -> #N/A | K44: =IF($B44>RECSYr,GETPIVOTDATA("HOUSEHOLDS",HousingStockTable!$A$12,"YEAR",B44)/10^6,#N/A) -> #N/A | M44: =IFERROR(IF(AND(B44<=RECSYr,GETPIVOTDATA("Sum of "&B44,'RECS Data'!$B$179)>0),GETPIVOTDATA("Sum of "&B44,'RECS Data'!$B$179),#N/A)/1000,#N/A) -> #N/A | N44: =IF($B44>RECSYr,GETPIVOTDATA("HOUSEHOLDS",SqftTable!$A$7,"YEAR",B44),#N/A)/1000 -> #N/A | P44: =IF(ISERROR(G44/J44*1000),#N/A,G44/J44*1000) -> #N/A | Q44: =H44/K44*1000 -> #N/A | S44: =IFERROR(G44/M44*10^3,#N/A) -> #N/A | T44: =H44/N44*1000 -> #N/A | V44: =IFERROR(M44*1000/J44,#N/A) -> #N/A | W44: =N44*1000/K44 -> #N/A
B45: =B44+1 -> 1993 | C45: =IF($D45>LastSEDSyr,#N/A,SEDSDataPivots!I31) -> #VALUE! | D45: =D44+1 -> 1993 | E45: =IF($E$4=0,#N/A,IF(B45>=FirstNEMSYrPlot,GETPIVOTDATA("EQSTOCK",NEMSPriceFcast!$A$7,"YEAR",B45)*$D$9,#N/A)) -> #N/A | G45: =IF(G$16<1,#N/A,IF($D45>LastSEDSyr,#N/A,SEDSDataPivots!D31))/10^6 -> 0.023475 | H45: =IF(B45>=FirstNEMSYrPlot,GETPIVOTDATA("CONSUMPTION",NEMSConsFcast!$A$9,"YEAR",B45)/10^9,#N/A) -> #N/A | J45: =IFERROR(IF(GETPIVOTDATA("Sum of "&D45,'RECS Data'!$B$99)=0,#N/A,GETPIVOTDATA("Sum of "&D45,'RECS Data'!$B$99)),#N/A) -> 96.631492 | K45: =IF($B45>RECSYr,GETPIVOTDATA("HOUSEHOLDS",HousingStockTable!$A$12,"YEAR",B45)/10^6,#N/A) -> #N/A | M45: =IFERROR(IF(AND(B45<=RECSYr,GETPIVOTDATA("Sum of "&B45,'RECS Data'!$B$179)>0),GETPIVOTDATA("Sum of "&B45,'RECS Data'!$B$179),#N/A)/1000,#N/A) -> 157.53553 | N45: =IF($B45>RECSYr,GETPIVOTDATA("HOUSEHOLDS",SqftTable!$A$7,"YEAR",B45),#N/A)/1000 -> #N/A | P45: =IF(ISERROR(G45/J45*1000),#N/A,G45/J45*1000) -> 0.24293323 | Q45: =H45/K45*1000 -> #N/A | S45: =IFERROR(G45/M45*10^3,#N/A) -> 0.14901401 | T45: =H45/N45*1000 -> #N/A | V45: =IFERROR(M45*1000/J45,#N/A) -> 1630.2711 | W45: =N45*1000/K45 -> #N/A
B46: =B45+1 -> 1994 | C46: =IF($D46>LastSEDSyr,#N/A,SEDSDataPivots!I32) -> #VALUE! | D46: =D45+1 -> 1994 | E46: =IF($E$4=0,#N/A,IF(B46>=FirstNEMSYrPlot,GETPIVOTDATA("EQSTOCK",NEMSPriceFcast!$A$7,"YEAR",B46)*$D$9,#N/A)) -> #N/A | G46: =IF(G$16<1,#N/A,IF($D46>LastSEDSyr,#N/A,SEDSDataPivots!D32))/10^6 -> 0.03185 | H46: =IF(B46>=FirstNEMSYrPlot,GETPIVOTDATA("CONSUMPTION",NEMSConsFcast!$A$9,"YEAR",B46)/10^9,#N/A) -> #N/A | J46: =IFERROR(IF(GETPIVOTDATA("Sum of "&D46,'RECS Data'!$B$99)=0,#N/A,GETPIVOTDATA("Sum of "&D46,'RECS Data'!$B$99)),#N/A) -> #N/A | K46: =IF($B46>RECSYr,GETPIVOTDATA("HOUSEHOLDS",HousingStockTable!$A$12,"YEAR",B46)/10^6,#N/A) -> #N/A | M46: =IFERROR(IF(AND(B46<=RECSYr,GETPIVOTDATA("Sum of "&B46,'RECS Data'!$B$179)>0),GETPIVOTDATA("Sum of "&B46,'RECS Data'!$B$179),#N/A)/1000,#N/A) -> #N/A | N46: =IF($B46>RECSYr,GETPIVOTDATA("HOUSEHOLDS",SqftTable!$A$7,"YEAR",B46),#N/A)/1000 -> #N/A | P46: =IF(ISERROR(G46/J46*1000),#N/A,G46/J46*1000) -> #N/A | Q46: =H46/K46*1000 -> #N/A | S46: =IFERROR(G46/M46*10^3,#N/A) -> #N/A | T46: =H46/N46*1000 -> #N/A | V46: =IFERROR(M46*1000/J46,#N/A) -> #N/A | W46: =N46*1000/K46 -> #N/A
B47: =B46+1 -> 1995 | C47: =IF($D47>LastSEDSyr,#N/A,SEDSDataPivots!I33) -> #VALUE! | D47: =D46+1 -> 1995 | E47: =IF($E$4=0,#N/A,IF(B47>=FirstNEMSYrPlot,GETPIVOTDATA("EQSTOCK",NEMSPriceFcast!$A$7,"YEAR",B47)*$D$9,#N/A)) -> #N/A | G47: =IF(G$16<1,#N/A,IF($D47>LastSEDSyr,#N/A,SEDSDataPivots!D33))/10^6 -> 0.013167 | H47: =IF(B47>=FirstNEMSYrPlot,GETPIVOTDATA("CONSUMPTION",NEMSConsFcast!$A$9,"YEAR",B47)/10^9,#N/A) -> #N/A | J47: =IFERROR(IF(GETPIVOTDATA("Sum of "&D47,'RECS Data'!$B$99)=0,#N/A,GETPIVOTDATA("Sum of "&D47,'RECS Data'!$B$99)),#N/A) -> #N/A | K47: =IF($B47>RECSYr,GETPIVOTDATA("HOUSEHOLDS",HousingStockTable!$A$12,"YEAR",B47)/10^6,#N/A) -> #N/A | M47: =IFERROR(IF(AND(B47<=RECSYr,GETPIVOTDATA("Sum of "&B47,'RECS Data'!$B$179)>0),GETPIVOTDATA("Sum of "&B47,'RECS Data'!$B$179),#N/A)/1000,#N/A) -> #N/A | N47: =IF($B47>RECSYr,GETPIVOTDATA("HOUSEHOLDS",SqftTable!$A$7,"YEAR",B47),#N/A)/1000 -> #N/A | P47: =IF(ISERROR(G47/J47*1000),#N/A,G47/J47*1000) -> #N/A | Q47: =H47/K47*1000 -> #N/A | S47: =IFERROR(G47/M47*10^3,#N/A) -> #N/A | T47: =H47/N47*1000 -> #N/A | V47: =IFERROR(M47*1000/J47,#N/A) -> #N/A | W47: =N47*1000/K47 -> #N/A
B48: =B47+1 -> 1996 | C48: =IF($D48>LastSEDSyr,#N/A,SEDSDataPivots!I34) -> #VALUE! | D48: =D47+1 -> 1996 | E48: =IF($E$4=0,#N/A,IF(B48>=FirstNEMSYrPlot,GETPIVOTDATA("EQSTOCK",NEMSPriceFcast!$A$7,"YEAR",B48)*$D$9,#N/A)) -> #N/A | G48: =IF(G$16<1,#N/A,IF($D48>LastSEDSyr,#N/A,SEDSDataPivots!D34))/10^6 -> 0.03361 | H48: =IF(B48>=FirstNEMSYrPlot,GETPIVOTDATA("CONSUMPTION",NEMSConsFcast!$A$9,"YEAR",B48)/10^9,#N/A) -> #N/A | J48: =IFERROR(IF(GETPIVOTDATA("Sum of "&D48,'RECS Data'!$B$99)=0,#N/A,GETPIVOTDATA("Sum of "&D48,'RECS Data'!$B$99)),#N/A) -> #N/A | K48: =IF($B48>RECSYr,GETPIVOTDATA("HOUSEHOLDS",HousingStockTable!$A$12,"YEAR",B48)/10^6,#N/A) -> #N/A | M48: =IFERROR(IF(AND(B48<=RECSYr,GETPIVOTDATA("Sum of "&B48,'RECS Data'!$B$179)>0),GETPIVOTDATA("Sum of "&B48,'RECS Data'!$B$179),#N/A)/1000,#N/A) -> #N/A | N48: =IF($B48>RECSYr,GETPIVOTDATA("HOUSEHOLDS",SqftTable!$A$7,"YEAR",B48),#N/A)/1000 -> #N/A | P48: =IF(ISERROR(G48/J48*1000),#N/A,G48/J48*1000) -> #N/A | Q48: =H48/K48*1000 -> #N/A | S48: =IFERROR(G48/M48*10^3,#N/A) -> #N/A | T48: =H48/N48*1000 -> #N/A | V48: =IFERROR(M48*1000/J48,#N/A) -> #N/A | W48: =N48*1000/K48 -> #N/A
B49: =B48+1 -> 1997 | C49: =IF($D49>LastSEDSyr,#N/A,SEDSDataPivots!I35) -> #VALUE! | D49: =D48+1 -> 1997 | E49: =IF($E$4=0,#N/A,IF(B49>=FirstNEMSYrPlot,GETPIVOTDATA("EQSTOCK",NEMSPriceFcast!$A$7,"YEAR",B49)*$D$9,#N/A)) -> #N/A | G49: =IF(G$16<1,#N/A,IF($D49>LastSEDSyr,#N/A,SEDSDataPivots!D35))/10^6 -> 0.033524 | H49: =IF(B49>=FirstNEMSYrPlot,GETPIVOTDATA("CONSUMPTION",NEMSConsFcast!$A$9,"YEAR",B49)/10^9,#N/A) -> #N/A | J49: =IFERROR(IF(GETPIVOTDATA("Sum of "&D49,'RECS Data'!$B$99)=0,#N/A,GETPIVOTDATA("Sum of "&D49,'RECS Data'!$B$99)),#N/A) -> 101.48117 | K49: =IF($B49>RECSYr,GETPIVOTDATA("HOUSEHOLDS",HousingStockTable!$A$12,"YEAR",B49)/10^6,#N/A) -> #N/A | M49: =IFERROR(IF(AND(B49<=RECSYr,GETPIVOTDATA("Sum of "&B49,'RECS Data'!$B$179)>0),GETPIVOTDATA("Sum of "&B49,'RECS Data'!$B$179),#N/A)/1000,#N/A) -> 168.80894 | N49: =IF($B49>RECSYr,GETPIVOTDATA("HOUSEHOLDS",SqftTable!$A$7,"YEAR",B49),#N/A)/1000 -> #N/A | P49: =IF(ISERROR(G49/J49*1000),#N/A,G49/J49*1000) -> 0.330347 | Q49: =H49/K49*1000 -> #N/A | S49: =IFERROR(G49/M49*10^3,#N/A) -> 0.19859138 | T49: =H49/N49*1000 -> #N/A | V49: =IFERROR(M49*1000/J49,#N/A) -> 1663.4508 | W49: =N49*1000/K49 -> #N/A
B50: =B49+1 -> 1998 | C50: =IF($D50>LastSEDSyr,#N/A,SEDSDataPivots!I36) -> #VALUE! | D50: =D49+1 -> 1998 | E50: =IF($E$4=0,#N/A,IF(B50>=FirstNEMSYrPlot,GETPIVOTDATA("EQSTOCK",NEMSPriceFcast!$A$7,"YEAR",B50)*$D$9,#N/A)) -> #N/A | G50: =IF(G$16<1,#N/A,IF($D50>LastSEDSyr,#N/A,SEDSDataPivots!D36))/10^6 -> 0.030814 | H50: =IF(B50>=FirstNEMSYrPlot,GETPIVOTDATA("CONSUMPTION",NEMSConsFcast!$A$9,"YEAR",B50)/10^9,#N/A) -> #N/A | J50: =IFERROR(IF(GETPIVOTDATA("Sum of "&D50,'RECS Data'!$B$99)=0,#N/A,GETPIVOTDATA("Sum of "&D50,'RECS Data'!$B$99)),#N/A) -> #N/A | K50: =IF($B50>RECSYr,GETPIVOTDATA("HOUSEHOLDS",HousingStockTable!$A$12,"YEAR",B50)/10^6,#N/A) -> #N/A | M50: =IFERROR(IF(AND(B50<=RECSYr,GETPIVOTDATA("Sum of "&B50,'RECS Data'!$B$179)>0),GETPIVOTDATA("Sum of "&B50,'RECS Data'!$B$179),#N/A)/1000,#N/A) -> #N/A | N50: =IF($B50>RECSYr,GETPIVOTDATA("HOUSEHOLDS",SqftTable!$A$7,"YEAR",B50),#N/A)/1000 -> #N/A | P50: =IF(ISERROR(G50/J50*1000),#N/A,G50/J50*1000) -> #N/A | Q50: =H50/K50*1000 -> #N/A | S50: =IFERROR(G50/M50*10^3,#N/A) -> #N/A | T50: =H50/N50*1000 -> #N/A | V50: =IFERROR(M50*1000/J50,#N/A) -> #N/A | W50: =N50*1000/K50 -> #N/A
B51: =B50+1 -> 1999 | C51: =IF($D51>LastSEDSyr,#N/A,SEDSDataPivots!I37) -> #VALUE! | D51: =D50+1 -> 1999 | E51: =IF($E$4=0,#N/A,IF(B51>=FirstNEMSYrPlot,GETPIVOTDATA("EQSTOCK",NEMSPriceFcast!$A$7,"YEAR",B51)*$D$9,#N/A)) -> #N/A | G51: =IF(G$16<1,#N/A,IF($D51>LastSEDSyr,#N/A,SEDSDataPivots!D37))/10^6 -> 0.024884 | H51: =IF(B51>=FirstNEMSYrPlot,GETPIVOTDATA("CONSUMPTION",NEMSConsFcast!$A$9,"YEAR",B51)/10^9,#N/A) -> #N/A | J51: =IFERROR(IF(GETPIVOTDATA("Sum of "&D51,'RECS Data'!$B$99)=0,#N/A,GETPIVOTDATA("Sum of "&D51,'RECS Data'!$B$99)),#N/A) -> #N/A | K51: =IF($B51>RECSYr,GETPIVOTDATA("HOUSEHOLDS",HousingStockTable!$A$12,"YEAR",B51)/10^6,#N/A) -> #N/A | M51: =IFERROR(IF(AND(B51<=RECSYr,GETPIVOTDATA("Sum of "&B51,'RECS Data'!$B$179)>0),GETPIVOTDATA("Sum of "&B51,'RECS Data'!$B$179),#N/A)/1000,#N/A) -> #N/A | N51: =IF($B51>RECSYr,GETPIVOTDATA("HOUSEHOLDS",SqftTable!$A$7,"YEAR",B51),#N/A)/1000 -> #N/A | P51: =IF(ISERROR(G51/J51*1000),#N/A,G51/J51*1000) -> #N/A | Q51: =H51/K51*1000 -> #N/A | S51: =IFERROR(G51/M51*10^3,#N/A) -> #N/A | T51: =H51/N51*1000 -> #N/A | V51: =IFERROR(M51*1000/J51,#N/A) -> #N/A | W51: =N51*1000/K51 -> #N/A
B52: =B51+1 -> 2000 | C52: =IF($D52>LastSEDSyr,#N/A,SEDSDataPivots!I38) -> #VALUE! | D52: =D51+1 -> 2000 | E52: =IF($E$4=0,#N/A,IF(B52>=FirstNEMSYrPlot,GETPIVOTDATA("EQSTOCK",NEMSPriceFcast!$A$7,"YEAR",B52)*$D$9,#N/A)) -> #N/A | G52: =IF(G$16<1,#N/A,IF($D52>LastSEDSyr,#N/A,SEDSDataPivots!D38))/10^6 -> 0.02384 | H52: =IF(B52>=FirstNEMSYrPlot,GETPIVOTDATA("CONSUMPTION",NEMSConsFcast!$A$9,"YEAR",B52)/10^9,#N/A) -> #N/A | J52: =IFERROR(IF(GETPIVOTDATA("Sum of "&D52,'RECS Data'!$B$99)=0,#N/A,GETPIVOTDATA("Sum of "&D52,'RECS Data'!$B$99)),#N/A) -> #N/A | K52: =IF($B52>RECSYr,GETPIVOTDATA("HOUSEHOLDS",HousingStockTable!$A$12,"YEAR",B52)/10^6,#N/A) -> #N/A | M52: =IFERROR(IF(AND(B52<=RECSYr,GETPIVOTDATA("Sum of "&B52,'RECS Data'!$B$179)>0),GETPIVOTDATA("Sum of "&B52,'RECS Data'!$B$179),#N/A)/1000,#N/A) -> #N/A | N52: =IF($B52>RECSYr,GETPIVOTDATA("HOUSEHOLDS",SqftTable!$A$7,"YEAR",B52),#N/A)/1000 -> #N/A | P52: =IF(ISERROR(G52/J52*1000),#N/A,G52/J52*1000) -> #N/A | Q52: =H52/K52*1000 -> #N/A | S52: =IFERROR(G52/M52*10^3,#N/A) -> #N/A | T52: =H52/N52*1000 -> #N/A | V52: =IFERROR(M52*1000/J52,#N/A) -> #N/A | W52: =N52*1000/K52 -> #N/A
B53: =B52+1 -> 2001 | C53: =IF($D53>LastSEDSyr,#N/A,SEDSDataPivots!I39) -> #VALUE! | D53: =D52+1 -> 2001 | E53: =IF($E$4=0,#N/A,IF(B53>=FirstNEMSYrPlot,GETPIVOTDATA("EQSTOCK",NEMSPriceFcast!$A$7,"YEAR",B53)*$D$9,#N/A)) -> #N/A | G53: =IF(G$16<1,#N/A,IF($D53>LastSEDSyr,#N/A,SEDSDataPivots!D39))/10^6 -> 0.026237 | H53: =IF(B53>=FirstNEMSYrPlot,GETPIVOTDATA("CONSUMPTION",NEMSConsFcast!$A$9,"YEAR",B53)/10^9,#N/A) -> #N/A | J53: =IFERROR(IF(GETPIVOTDATA("Sum of "&D53,'RECS Data'!$B$99)=0,#N/A,GETPIVOTDATA("Sum of "&D53,'RECS Data'!$B$99)),#N/A) -> 106.98927 | K53: =IF($B53>RECSYr,GETPIVOTDATA("HOUSEHOLDS",HousingStockTable!$A$12,"YEAR",B53)/10^6,#N/A) -> #N/A | M53: =IFERROR(IF(AND(B53<=RECSYr,GETPIVOTDATA("Sum of "&B53,'RECS Data'!$B$179)>0),GETPIVOTDATA("Sum of "&B53,'RECS Data'!$B$179),#N/A)/1000,#N/A) -> 181.01774 | N53: =IF($B53>RECSYr,GETPIVOTDATA("HOUSEHOLDS",SqftTable!$A$7,"YEAR",B53),#N/A)/1000 -> #N/A | P53: =IF(ISERROR(G53/J53*1000),#N/A,G53/J53*1000) -> 0.24523019 | Q53: =H53/K53*1000 -> #N/A | S53: =IFERROR(G53/M53*10^3,#N/A) -> 0.1449416 | T53: =H53/N53*1000 -> #N/A | V53: =IFERROR(M53*1000/J53,#N/A) -> 1691.9242 | W53: =N53*1000/K53 -> #N/A
... B60: =B59+1 -> 2008 | C60: =IF($D60>LastSEDSyr,#N/A,SEDSDataPivots!I46) -> #VALUE! | D60: =D59+1 -> 2008 | E60: =IF($E$4=0,#N/A,IF(B60>=FirstNEMSYrPlot,GETPIVOTDATA("EQSTOCK",NEMSPriceFcast!$A$7,"YEAR",B60)*$D$9,#N/A)) -> #N/A | G60: =IF(G$16<1,#N/A,IF($D60>LastSEDSyr,#N/A,SEDSDataPivots!D46))/10^6 -> 0.033 | H60: =IF(B60>=FirstNEMSYrPlot,GETPIVOTDATA("CONSUMPTION",NEMSConsFcast!$A$9,"YEAR",B60)/10^9,#N/A) -> #N/A | J60: =IFERROR(IF(GETPIVOTDATA("Sum of "&D60,'RECS Data'!$B$99)=0,#N/A,GETPIVOTDATA("Sum of "&D60,'RECS Data'!$B$99)),#N/A) -> #N/A | K60: =IF($B60>RECSYr,GETPIVOTDATA("HOUSEHOLDS",HousingStockTable!$A$12,"YEAR",B60)/10^6,#N/A) -> #N/A | M60: =IFERROR(IF(AND(B60<=RECSYr,GETPIVOTDATA("Sum of "&B60,'RECS Data'!$B$179)>0),GETPIVOTDATA("Sum of "&B60,'RECS Data'!$B$179),#N/A)/1000,#N/A) -> #N/A | N60: =IF($B60>RECSYr,GETPIVOTDATA("HOUSEHOLDS",SqftTable!$A$7,"YEAR",B60),#N/A)/1000 -> #N/A | P60: =IF(ISERROR(G60/J60*1000),#N/A,G60/J60*1000) -> #N/A | Q60: =H60/K60*1000 -> #N/A | S60: =IFERROR(G60/M60*10^3,#N/A) -> #N/A | T60: =H60/N60*1000 -> #N/A | V60: =IFERROR(M60*1000/J60,#N/A) -> #N/A | W60: =N60*1000/K60 -> #N/A
B61: 2009 | C61: =IF($D61>LastSEDSyr,#N/A,SEDSDataPivots!I47) -> #VALUE! | D61: =D60+1 -> 2009 | E61: =IF($E$4=0,#N/A,IF(B61>=FirstNEMSYrPlot,GETPIVOTDATA("EQSTOCK",NEMSPriceFcast!$A$7,"YEAR",B61)*$D$9,#N/A)) -> #N/A | G61: =IF(G$16<1,#N/A,IF($D61>LastSEDSyr,#N/A,SEDSDataPivots!D47))/10^6 -> 0.05239 | H61: =IF(B61>=FirstNEMSYrPlot,GETPIVOTDATA("CONSUMPTION",NEMSConsFcast!$A$9,"YEAR",B61)/10^9,#N/A) -> #N/A | J61: =IFERROR(IF(GETPIVOTDATA("Sum of "&D61,'RECS Data'!$B$99)=0,#N/A,GETPIVOTDATA("Sum of "&D61,'RECS Data'!$B$99)),#N/A) -> 113.61623 | K61: =IF($B61>RECSYr,GETPIVOTDATA("HOUSEHOLDS",HousingStockTable!$A$12,"YEAR",B61)/10^6,#N/A) -> #N/A | M61: =IFERROR(IF(AND(B61<=RECSYr,GETPIVOTDATA("Sum of "&B61,'RECS Data'!$B$179)>0),GETPIVOTDATA("Sum of "&B61,'RECS Data'!$B$179),#N/A)/1000,#N/A) -> 186.78902 | N61: =IF($B61>RECSYr,GETPIVOTDATA("HOUSEHOLDS",SqftTable!$A$7,"YEAR",B61),#N/A)/1000 -> #N/A | P61: =IF(ISERROR(G61/J61*1000),#N/A,G61/J61*1000) -> 0.4611137 | Q61: =H61/K61*1000 -> #N/A | S61: =IFERROR(G61/M61*10^3,#N/A) -> 0.28047687 | T61: =H61/N61*1000 -> #N/A | V61: =IFERROR(M61*1000/J61,#N/A) -> 1644.0347 | W61: =N61*1000/K61 -> #N/A
B62: 2010 | C62: =IF($D62>LastSEDSyr,#N/A,SEDSDataPivots!I48) -> #VALUE! | D62: =D61+1 -> 2010 | E62: =IF($E$4=0,#N/A,IF(B62>=FirstNEMSYrPlot,GETPIVOTDATA("EQSTOCK",NEMSPriceFcast!$A$7,"YEAR",B62)*$D$9,#N/A)) -> #N/A | G62: =IF(G$16<1,#N/A,IF($D62>LastSEDSyr,#N/A,SEDSDataPivots!D48))/10^6 -> 0.014765 | H62: =IF(B62>=FirstNEMSYrPlot,GETPIVOTDATA("CONSUMPTION",NEMSConsFcast!$A$9,"YEAR",B62)/10^9,#N/A) -> #N/A | J62: =IFERROR(IF(GETPIVOTDATA("Sum of "&D62,'RECS Data'!$B$99)=0,#N/A,GETPIVOTDATA("Sum of "&D62,'RECS Data'!$B$99)),#N/A) -> #N/A | K62: =IF($B62>RECSYr,GETPIVOTDATA("HOUSEHOLDS",HousingStockTable!$A$12,"YEAR",B62)/10^6,#N/A) -> #N/A | M62: =IFERROR(IF(AND(B62<=RECSYr,GETPIVOTDATA("Sum of "&B62,'RECS Data'!$B$179)>0),GETPIVOTDATA("Sum of "&B62,'RECS Data'!$B$179),#N/A)/1000,#N/A) -> #N/A | N62: =IF($B62>RECSYr,GETPIVOTDATA("HOUSEHOLDS",SqftTable!$A$7,"YEAR",B62),#N/A)/1000 -> #N/A | P62: =IF(ISERROR(G62/J62*1000),#N/A,G62/J62*1000) -> #N/A | Q62: =H62/K62*1000 -> #N/A | S62: =IFERROR(G62/M62*10^3,#N/A) -> #N/A | T62: =H62/N62*1000 -> #N/A | V62: =IFERROR(M62*1000/J62,#N/A) -> #N/A | W62: =N62*1000/K62 -> #N/A
B63: 2011 | C63: =IF($D63>LastSEDSyr,#N/A,SEDSDataPivots!I49) -> #VALUE! | D63: =D62+1 -> 2011 | E63: =IF($E$4=0,#N/A,IF(B63>=FirstNEMSYrPlot,GETPIVOTDATA("EQSTOCK",NEMSPriceFcast!$A$7,"YEAR",B63)*$D$9,#N/A)) -> #N/A | G63: =IF(G$16<1,#N/A,IF($D63>LastSEDSyr,#N/A,SEDSDataPivots!D49))/10^6 -> 0.061217 | H63: =IF(B63>=FirstNEMSYrPlot,GETPIVOTDATA("CONSUMPTION",NEMSConsFcast!$A$9,"YEAR",B63)/10^9,#N/A) -> #N/A | J63: =IFERROR(IF(GETPIVOTDATA("Sum of "&D63,'RECS Data'!$B$99)=0,#N/A,GETPIVOTDATA("Sum of "&D63,'RECS Data'!$B$99)),#N/A) -> #N/A | K63: =IF($B63>RECSYr,GETPIVOTDATA("HOUSEHOLDS",HousingStockTable!$A$12,"YEAR",B63)/10^6,#N/A) -> #N/A | M63: =IFERROR(IF(AND(B63<=RECSYr,GETPIVOTDATA("Sum of "&B63,'RECS Data'!$B$179)>0),GETPIVOTDATA("Sum of "&B63,'RECS Data'!$B$179),#N/A)/1000,#N/A) -> #N/A | N63: =IF($B63>RECSYr,GETPIVOTDATA("HOUSEHOLDS",SqftTable!$A$7,"YEAR",B63),#N/A)/1000 -> #N/A | P63: =IF(ISERROR(G63/J63*1000),#N/A,G63/J63*1000) -> #N/A | Q63: =H63/K63*1000 -> #N/A | S63: =IFERROR(G63/M63*10^3,#N/A) -> #N/A | T63: =H63/N63*1000 -> #N/A | V63: =IFERROR(M63*1000/J63,#N/A) -> #N/A | W63: =N63*1000/K63 -> #N/A
B64: 2012 | C64: =IF($D64>LastSEDSyr,#N/A,SEDSDataPivots!I50) -> #VALUE! | D64: =D63+1 -> 2012 | E64: =IF($E$4=0,#N/A,IF(B64>=FirstNEMSYrPlot,GETPIVOTDATA("EQSTOCK",NEMSPriceFcast!$A$7,"YEAR",B64)*$D$9,#N/A)) -> #N/A | G64: =IF(G$16<1,#N/A,IF($D64>LastSEDSyr,#N/A,SEDSDataPivots!D50))/10^6 -> 0.039394 | H64: =IF(B64>=FirstNEMSYrPlot,GETPIVOTDATA("CONSUMPTION",NEMSConsFcast!$A$9,"YEAR",B64)/10^9,#N/A) -> #N/A | J64: =IFERROR(IF(GETPIVOTDATA("Sum of "&D64,'RECS Data'!$B$99)=0,#N/A,GETPIVOTDATA("Sum of "&D64,'RECS Data'!$B$99)),#N/A) -> #N/A | K64: =IF($B64>RECSYr,GETPIVOTDATA("HOUSEHOLDS",HousingStockTable!$A$12,"YEAR",B64)/10^6,#N/A) -> #N/A | M64: =IFERROR(IF(AND(B64<=RECSYr,GETPIVOTDATA("Sum of "&B64,'RECS Data'!$B$179)>0),GETPIVOTDATA("Sum of "&B64,'RECS Data'!$B$179),#N/A)/1000,#N/A) -> #N/A | N64: =IF($B64>RECSYr,GETPIVOTDATA("HOUSEHOLDS",SqftTable!$A$7,"YEAR",B64),#N/A)/1000 -> #N/A | P64: =IF(ISERROR(G64/J64*1000),#N/A,G64/J64*1000) -> #N/A | Q64: =H64/K64*1000 -> #N/A | S64: =IFERROR(G64/M64*10^3,#N/A) -> #N/A | T64: =H64/N64*1000 -> #N/A | V64: =IFERROR(M64*1000/J64,#N/A) -> #N/A | W64: =N64*1000/K64 -> #N/A
B65: 2013 | C65: =IF($D65>LastSEDSyr,#N/A,SEDSDataPivots!I51) -> #VALUE! | D65: =D64+1 -> 2013 | E65: =IF($E$4=0,#N/A,IF(B65>=FirstNEMSYrPlot,GETPIVOTDATA("EQSTOCK",NEMSPriceFcast!$A$7,"YEAR",B65)*$D$9,#N/A)) -> #N/A | G65: =IF(G$16<1,#N/A,IF($D65>LastSEDSyr,#N/A,SEDSDataPivots!D51))/10^6 -> 0.076882 | H65: =IF(B65>=FirstNEMSYrPlot,GETPIVOTDATA("CONSUMPTION",NEMSConsFcast!$A$9,"YEAR",B65)/10^9,#N/A) -> #N/A | J65: =IFERROR(IF(GETPIVOTDATA("Sum of "&D65,'RECS Data'!$B$99)=0,#N/A,GETPIVOTDATA("Sum of "&D65,'RECS Data'!$B$99)),#N/A) -> #N/A | K65: =IF($B65>RECSYr,GETPIVOTDATA("HOUSEHOLDS",HousingStockTable!$A$12,"YEAR",B65)/10^6,#N/A) -> #N/A | M65: =IFERROR(IF(AND(B65<=RECSYr,GETPIVOTDATA("Sum of "&B65,'RECS Data'!$B$179)>0),GETPIVOTDATA("Sum of "&B65,'RECS Data'!$B$179),#N/A)/1000,#N/A) -> #N/A | N65: =IF($B65>RECSYr,GETPIVOTDATA("HOUSEHOLDS",SqftTable!$A$7,"YEAR",B65),#N/A)/1000 -> #N/A | P65: =IF(ISERROR(G65/J65*1000),#N/A,G65/J65*1000) -> #N/A | Q65: =H65/K65*1000 -> #N/A | S65: =IFERROR(G65/M65*10^3,#N/A) -> #N/A | T65: =H65/N65*1000 -> #N/A | V65: =IFERROR(M65*1000/J65,#N/A) -> #N/A | W65: =N65*1000/K65 -> #N/A
B66: 2014 | C66: =IF($D66>LastSEDSyr,#N/A,SEDSDataPivots!I52) -> #VALUE! | D66: =D65+1 -> 2014 | E66: =IF($E$4=0,#N/A,IF(B66>=FirstNEMSYrPlot,GETPIVOTDATA("EQSTOCK",NEMSPriceFcast!$A$7,"YEAR",B66)*$D$9,#N/A)) -> #N/A | G66: =IF(G$16<1,#N/A,IF($D66>LastSEDSyr,#N/A,SEDSDataPivots!D52))/10^6 -> 0.075971 | H66: =IF(B66>=FirstNEMSYrPlot,GETPIVOTDATA("CONSUMPTION",NEMSConsFcast!$A$9,"YEAR",B66)/10^9,#N/A) -> #N/A | J66: =IFERROR(IF(GETPIVOTDATA("Sum of "&D66,'RECS Data'!$B$99)=0,#N/A,GETPIVOTDATA("Sum of "&D66,'RECS Data'!$B$99)),#N/A) -> #N/A | K66: =IF($B66>RECSYr,GETPIVOTDATA("HOUSEHOLDS",HousingStockTable!$A$12,"YEAR",B66)/10^6,#N/A) -> #N/A | M66: =IFERROR(IF(AND(B66<=RECSYr,GETPIVOTDATA("Sum of "&B66,'RECS Data'!$B$179)>0),GETPIVOTDATA("Sum of "&B66,'RECS Data'!$B$179),#N/A)/1000,#N/A) -> #N/A | N66: =IF($B66>RECSYr,GETPIVOTDATA("HOUSEHOLDS",SqftTable!$A$7,"YEAR",B66),#N/A)/1000 -> #N/A | P66: =IF(ISERROR(G66/J66*1000),#N/A,G66/J66*1000) -> #N/A | Q66: =H66/K66*1000 -> #N/A | S66: =IFERROR(G66/M66*10^3,#N/A) -> #N/A | T66: =H66/N66*1000 -> #N/A | V66: =IFERROR(M66*1000/J66,#N/A) -> #N/A | W66: =N66*1000/K66 -> #N/A
B67: 2015 | C67: =IF($D67>LastSEDSyr,#N/A,SEDSDataPivots!I53) -> #VALUE! | D67: =D66+1 -> 2015 | E67: =IF($E$4=0,#N/A,IF(B67>=FirstNEMSYrPlot,GETPIVOTDATA("EQSTOCK",NEMSPriceFcast!$A$7,"YEAR",B67)*$D$9,#N/A)) -> #N/A | G67: =IF(G$16<1,#N/A,IF($D67>LastSEDSyr,#N/A,SEDSDataPivots!D53))/10^6 -> 0.08698 | H67: =IF(B67>=FirstNEMSYrPlot,GETPIVOTDATA("CONSUMPTION",NEMSConsFcast!$A$9,"YEAR",B67)/10^9,#N/A) -> #N/A | J67: =IFERROR(IF(GETPIVOTDATA("Sum of "&D67,'RECS Data'!$B$99)=0,#N/A,GETPIVOTDATA("Sum of "&D67,'RECS Data'!$B$99)),#N/A) -> 118.20825 | K67: =IF($B67>RECSYr,GETPIVOTDATA("HOUSEHOLDS",HousingStockTable!$A$12,"YEAR",B67)/10^6,#N/A) -> #N/A | M67: =IFERROR(IF(AND(B67<=RECSYr,GETPIVOTDATA("Sum of "&B67,'RECS Data'!$B$179)>0),GETPIVOTDATA("Sum of "&B67,'RECS Data'!$B$179),#N/A)/1000,#N/A) -> 207.70879 | N67: =IF($B67>RECSYr,GETPIVOTDATA("HOUSEHOLDS",SqftTable!$A$7,"YEAR",B67),#N/A)/1000 -> #N/A | P67: =IF(ISERROR(G67/J67*1000),#N/A,G67/J67*1000) -> 0.73582005 | Q67: =H67/K67*1000 -> #N/A | S67: =IFERROR(G67/M67*10^3,#N/A) -> 0.41875937 | T67: =H67/N67*1000 -> #N/A | V67: =IFERROR(M67*1000/J67,#N/A) -> 1757.1429 | W67: =N67*1000/K67 -> #N/A
B68: 2016 | C68: =IF($D68>LastSEDSyr,#N/A,SEDSDataPivots!I54) -> #VALUE! | D68: =D67+1 -> 2016 | E68: =IF($E$4=0,#N/A,IF(B68>=FirstNEMSYrPlot,GETPIVOTDATA("EQSTOCK",NEMSPriceFcast!$A$7,"YEAR",B68)*$D$9,#N/A)) -> #N/A | G68: =IF(G$16<1,#N/A,IF($D68>LastSEDSyr,#N/A,SEDSDataPivots!D54))/10^6 -> 0.0785 | H68: =IF(B68>=FirstNEMSYrPlot,GETPIVOTDATA("CONSUMPTION",NEMSConsFcast!$A$9,"YEAR",B68)/10^9,#N/A) -> #N/A | J68: =IFERROR(IF(GETPIVOTDATA("Sum of "&D68,'RECS Data'!$B$99)=0,#N/A,GETPIVOTDATA("Sum of "&D68,'RECS Data'!$B$99)),#N/A) -> #N/A | K68: =IF($B68>RECSYr,GETPIVOTDATA("HOUSEHOLDS",HousingStockTable!$A$12,"YEAR",B68)/10^6,#N/A) -> #N/A | M68: =IFERROR(IF(AND(B68<=RECSYr,GETPIVOTDATA("Sum of "&B68,'RECS Data'!$B$179)>0),GETPIVOTDATA("Sum of "&B68,'RECS Data'!$B$179),#N/A)/1000,#N/A) -> #N/A | N68: =IF($B68>RECSYr,GETPIVOTDATA("HOUSEHOLDS",SqftTable!$A$7,"YEAR",B68),#N/A)/1000 -> #N/A | P68: =IF(ISERROR(G68/J68*1000),#N/A,G68/J68*1000) -> #N/A | Q68: =H68/K68*1000 -> #N/A | S68: =IFERROR(G68/M68*10^3,#N/A) -> #N/A | T68: =H68/N68*1000 -> #N/A | V68: =IFERROR(M68*1000/J68,#N/A) -> #N/A | W68: =N68*1000/K68 -> #N/A
B69: 2017 | C69: =IF($D69>LastSEDSyr,#N/A,SEDSDataPivots!I55) -> #VALUE! | D69: =D68+1 -> 2017 | E69: =IF($E$4=0,#N/A,IF(B69>=FirstNEMSYrPlot,GETPIVOTDATA("EQSTOCK",NEMSPriceFcast!$A$7,"YEAR",B69)*$D$9,#N/A)) -> #N/A | G69: =IF(G$16<1,#N/A,IF($D69>LastSEDSyr,#N/A,SEDSDataPivots!D55))/10^6 -> 0.042562 | H69: =IF(B69>=FirstNEMSYrPlot,GETPIVOTDATA("CONSUMPTION",NEMSConsFcast!$A$9,"YEAR",B69)/10^9,#N/A) -> #N/A | J69: =IFERROR(IF(GETPIVOTDATA("Sum of "&D69,'RECS Data'!$B$99)=0,#N/A,GETPIVOTDATA("Sum of "&D69,'RECS Data'!$B$99)),#N/A) -> #N/A | K69: =IF($B69>RECSYr,GETPIVOTDATA("HOUSEHOLDS",HousingStockTable!$A$12,"YEAR",B69)/10^6,#N/A) -> #N/A | M69: =IFERROR(IF(AND(B69<=RECSYr,GETPIVOTDATA("Sum of "&B69,'RECS Data'!$B$179)>0),GETPIVOTDATA("Sum of "&B69,'RECS Data'!$B$179),#N/A)/1000,#N/A) -> #N/A | N69: =IF($B69>RECSYr,GETPIVOTDATA("HOUSEHOLDS",SqftTable!$A$7,"YEAR",B69),#N/A)/1000 -> #N/A | P69: =IF(ISERROR(G69/J69*1000),#N/A,G69/J69*1000) -> #N/A | Q69: =H69/K69*1000 -> #N/A | S69: =IFERROR(G69/M69*10^3,#N/A) -> #N/A | T69: =H69/N69*1000 -> #N/A | V69: =IFERROR(M69*1000/J69,#N/A) -> #N/A | W69: =N69*1000/K69 -> #N/A
B70: 2018 | C70: =IF($D70>LastSEDSyr,#N/A,SEDSDataPivots!I56) -> #VALUE! | D70: =D69+1 -> 2018 | E70: =IF($E$4=0,#N/A,IF(B70>=FirstNEMSYrPlot,GETPIVOTDATA("EQSTOCK",NEMSPriceFcast!$A$7,"YEAR",B70)*$D$9,#N/A)) -> #N/A | G70: =IF(G$16<1,#N/A,IF($D70>LastSEDSyr,#N/A,SEDSDataPivots!D56))/10^6 -> 0.050021 | H70: =IF(B70>=FirstNEMSYrPlot,GETPIVOTDATA("CONSUMPTION",NEMSConsFcast!$A$9,"YEAR",B70)/10^9,#N/A) -> #N/A | J70: =IFERROR(IF(GETPIVOTDATA("Sum of "&D70,'RECS Data'!$B$99)=0,#N/A,GETPIVOTDATA("Sum of "&D70,'RECS Data'!$B$99)),#N/A) -> #N/A | K70: =IF($B70>RECSYr,GETPIVOTDATA("HOUSEHOLDS",HousingStockTable!$A$12,"YEAR",B70)/10^6,#N/A) -> #N/A | M70: =IFERROR(IF(AND(B70<=RECSYr,GETPIVOTDATA("Sum of "&B70,'RECS Data'!$B$179)>0),GETPIVOTDATA("Sum of "&B70,'RECS Data'!$B$179),#N/A)/1000,#N/A) -> #N/A | N70: =IF($B70>RECSYr,GETPIVOTDATA("HOUSEHOLDS",SqftTable!$A$7,"YEAR",B70),#N/A)/1000 -> #N/A | P70: =IF(ISERROR(G70/J70*1000),#N/A,G70/J70*1000) -> #N/A | Q70: =H70/K70*1000 -> #N/A | S70: =IFERROR(G70/M70*10^3,#N/A) -> #N/A | T70: =H70/N70*1000 -> #N/A | V70: =IFERROR(M70*1000/J70,#N/A) -> #N/A | W70: =N70*1000/K70 -> #N/A
B71: 2019 | C71: =IF($D71>LastSEDSyr,#N/A,SEDSDataPivots!I57) -> #VALUE! | D71: =D70+1 -> 2019 | E71: =IF($E$4=0,#N/A,IF(B71>=FirstNEMSYrPlot,GETPIVOTDATA("EQSTOCK",NEMSPriceFcast!$A$7,"YEAR",B71)*$D$9,#N/A)) -> #N/A | G71: =IF(G$16<1,#N/A,IF($D71>LastSEDSyr,#N/A,SEDSDataPivots!D57))/10^6 -> 0.122071 | H71: =IF(B71>=FirstNEMSYrPlot,GETPIVOTDATA("CONSUMPTION",NEMSConsFcast!$A$9,"YEAR",B71)/10^9,#N/A) -> #N/A | J71: =IFERROR(IF(GETPIVOTDATA("Sum of "&D71,'RECS Data'!$B$99)=0,#N/A,GETPIVOTDATA("Sum of "&D71,'RECS Data'!$B$99)),#N/A) -> #N/A | K71: =IF($B71>RECSYr,GETPIVOTDATA("HOUSEHOLDS",HousingStockTable!$A$12,"YEAR",B71)/10^6,#N/A) -> #N/A | M71: =IFERROR(IF(AND(B71<=RECSYr,GETPIVOTDATA("Sum of "&B71,'RECS Data'!$B$179)>0),GETPIVOTDATA("Sum of "&B71,'RECS Data'!$B$179),#N/A)/1000,#N/A) -> #N/A | N71: =IF($B71>RECSYr,GETPIVOTDATA("HOUSEHOLDS",SqftTable!$A$7,"YEAR",B71),#N/A)/1000 -> #N/A | P71: =IF(ISERROR(G71/J71*1000),#N/A,G71/J71*1000) -> #N/A | Q71: =H71/K71*1000 -> #N/A | S71: =IFERROR(G71/M71*10^3,#N/A) -> #N/A | T71: =H71/N71*1000 -> #N/A | V71: =IFERROR(M71*1000/J71,#N/A) -> #N/A | W71: =N71*1000/K71 -> #N/A
B72: 2020 | C72: =IF($D72>LastSEDSyr,#N/A,SEDSDataPivots!I58) -> #VALUE! | D72: =D71+1 -> 2020 | E72: =IF($E$4=0,#N/A,IF(B72>=FirstNEMSYrPlot,GETPIVOTDATA("EQSTOCK",NEMSPriceFcast!$A$7,"YEAR",B72)*$D$9,#N/A)) -> #N/A | G72: =IF(G$16<1,#N/A,IF($D72>LastSEDSyr,#N/A,SEDSDataPivots!D58))/10^6 -> 0.083969 | H72: =IF(B72>=FirstNEMSYrPlot,GETPIVOTDATA("CONSUMPTION",NEMSConsFcast!$A$9,"YEAR",B72)/10^9,#N/A) -> #N/A | J72: =IFERROR(IF(GETPIVOTDATA("Sum of "&D72,'RECS Data'!$B$99)=0,#N/A,GETPIVOTDATA("Sum of "&D72,'RECS Data'!$B$99)),#N/A) -> 123.52903 | K72: =IF($B72>RECSYr,GETPIVOTDATA("HOUSEHOLDS",HousingStockTable!$A$12,"YEAR",B72)/10^6,#N/A) -> #N/A | M72: =IFERROR(IF(AND(B72<=RECSYr,GETPIVOTDATA("Sum of "&B72,'RECS Data'!$B$179)>0),GETPIVOTDATA("Sum of "&B72,'RECS Data'!$B$179),#N/A)/1000,#N/A) -> 199.88873 | N72: =IF($B72>RECSYr,GETPIVOTDATA("HOUSEHOLDS",SqftTable!$A$7,"YEAR",B72),#N/A)/1000 -> #N/A | P72: =IF(ISERROR(G72/J72*1000),#N/A,G72/J72*1000) -> 0.67975118 | Q72: =H72/K72*1000 -> #N/A | S72: =IFERROR(G72/M72*10^3,#N/A) -> 0.4200787 | T72: =H72/N72*1000 -> #N/A | V72: =IFERROR(M72*1000/J72,#N/A) -> 1618.152 | W72: =N72*1000/K72 -> #N/A
... B90: 2038 | C90: =IF($D90>LastSEDSyr,#N/A,SEDSDataPivots!I76) -> #N/A | D90: =D89+1 -> 2038 | E90: =IF($E$4=0,#N/A,IF(B90>=FirstNEMSYrPlot,GETPIVOTDATA("EQSTOCK",NEMSPriceFcast!$A$7,"YEAR",B90)*$D$9,#N/A)) -> 1230.6999 | G90: =IF(G$16<1,#N/A,IF($D90>LastSEDSyr,#N/A,SEDSDataPivots!D76))/10^6 -> #N/A | H90: =IF(B90>=FirstNEMSYrPlot,GETPIVOTDATA("CONSUMPTION",NEMSConsFcast!$A$9,"YEAR",B90)/10^9,#N/A) -> 11.131201 | J90: =IFERROR(IF(GETPIVOTDATA("Sum of "&D90,'RECS Data'!$B$99)=0,#N/A,GETPIVOTDATA("Sum of "&D90,'RECS Data'!$B$99)),#N/A) -> #N/A | K90: =IF($B90>RECSYr,GETPIVOTDATA("HOUSEHOLDS",HousingStockTable!$A$12,"YEAR",B90)/10^6,#N/A) -> 147.90639 | M90: =IFERROR(IF(AND(B90<=RECSYr,GETPIVOTDATA("Sum of "&B90,'RECS Data'!$B$179)>0),GETPIVOTDATA("Sum of "&B90,'RECS Data'!$B$179),#N/A)/1000,#N/A) -> #N/A | N90: =IF($B90>RECSYr,GETPIVOTDATA("HOUSEHOLDS",SqftTable!$A$7,"YEAR",B90),#N/A)/1000 -> 252.414 | P90: =IF(ISERROR(G90/J90*1000),#N/A,G90/J90*1000) -> #N/A | Q90: =H90/K90*1000 -> 75.25842 | S90: =IFERROR(G90/M90*10^3,#N/A) -> #N/A | T90: =H90/N90*1000 -> 44.098985 | V90: =IFERROR(M90*1000/J90,#N/A) -> #N/A | W90: =N90*1000/K90 -> 1706.5794
B91: 2039 | C91: =IF($D91>LastSEDSyr,#N/A,SEDSDataPivots!I77) -> #N/A | D91: 2039 | E91: =IF($E$4=0,#N/A,IF(B91>=FirstNEMSYrPlot,GETPIVOTDATA("EQSTOCK",NEMSPriceFcast!$A$7,"YEAR",B91)*$D$9,#N/A)) -> 1235.9978 | G91: =IF(G$16<1,#N/A,IF($D91>LastSEDSyr,#N/A,SEDSDataPivots!D77))/10^6 -> #N/A | H91: =IF(B91>=FirstNEMSYrPlot,GETPIVOTDATA("CONSUMPTION",NEMSConsFcast!$A$9,"YEAR",B91)/10^9,#N/A) -> 11.123768 | J91: =IFERROR(IF(GETPIVOTDATA("Sum of "&D91,'RECS Data'!$B$99)=0,#N/A,GETPIVOTDATA("Sum of "&D91,'RECS Data'!$B$99)),#N/A) -> #N/A | K91: =IF($B91>RECSYr,GETPIVOTDATA("HOUSEHOLDS",HousingStockTable!$A$12,"YEAR",B91)/10^6,#N/A) -> 148.98797 | M91: =IFERROR(IF(AND(B91<=RECSYr,GETPIVOTDATA("Sum of "&B91,'RECS Data'!$B$179)>0),GETPIVOTDATA("Sum of "&B91,'RECS Data'!$B$179),#N/A)/1000,#N/A) -> #N/A | N91: =IF($B91>RECSYr,GETPIVOTDATA("HOUSEHOLDS",SqftTable!$A$7,"YEAR",B91),#N/A)/1000 -> 254.919 | P91: =IF(ISERROR(G91/J91*1000),#N/A,G91/J91*1000) -> #N/A | Q91: =H91/K91*1000 -> 74.662187 | S91: =IFERROR(G91/M91*10^3,#N/A) -> #N/A | T91: =H91/N91*1000 -> 43.63648 | V91: =IFERROR(M91*1000/J91,#N/A) -> #N/A | W91: =N91*1000/K91 -> 1711.0039
B92: 2040 | C92: =IF($D92>LastSEDSyr,#N/A,SEDSDataPivots!I78) -> #N/A | D92: 2040 | E92: =IF($E$4=0,#N/A,IF(B92>=FirstNEMSYrPlot,GETPIVOTDATA("EQSTOCK",NEMSPriceFcast!$A$7,"YEAR",B92)*$D$9,#N/A)) -> 1244.175 | G92: =IF(G$16<1,#N/A,IF($D92>LastSEDSyr,#N/A,SEDSDataPivots!D78))/10^6 -> #N/A | H92: =IF(B92>=FirstNEMSYrPlot,GETPIVOTDATA("CONSUMPTION",NEMSConsFcast!$A$9,"YEAR",B92)/10^9,#N/A) -> 11.111928 | J92: =IFERROR(IF(GETPIVOTDATA("Sum of "&D92,'RECS Data'!$B$99)=0,#N/A,GETPIVOTDATA("Sum of "&D92,'RECS Data'!$B$99)),#N/A) -> #N/A | K92: =IF($B92>RECSYr,GETPIVOTDATA("HOUSEHOLDS",HousingStockTable!$A$12,"YEAR",B92)/10^6,#N/A) -> 150.02422 | M92: =IFERROR(IF(AND(B92<=RECSYr,GETPIVOTDATA("Sum of "&B92,'RECS Data'!$B$179)>0),GETPIVOTDATA("Sum of "&B92,'RECS Data'!$B$179),#N/A)/1000,#N/A) -> #N/A | N92: =IF($B92>RECSYr,GETPIVOTDATA("HOUSEHOLDS",SqftTable!$A$7,"YEAR",B92),#N/A)/1000 -> 257.357 | P92: =IF(ISERROR(G92/J92*1000),#N/A,G92/J92*1000) -> #N/A | Q92: =H92/K92*1000 -> 74.067561 | S92: =IFERROR(G92/M92*10^3,#N/A) -> #N/A | T92: =H92/N92*1000 -> 43.177098 | V92: =IFERROR(M92*1000/J92,#N/A) -> #N/A | W92: =N92*1000/K92 -> 1715.4363
B93: 2041 | C93: =IF($D93>LastSEDSyr,#N/A,SEDSDataPivots!I79) -> #N/A | D93: 2041 | E93: =IF($E$4=0,#N/A,IF(B93>=FirstNEMSYrPlot,GETPIVOTDATA("EQSTOCK",NEMSPriceFcast!$A$7,"YEAR",B93)*$D$9,#N/A)) -> 1249.9566 | G93: =IF(G$16<1,#N/A,IF($D93>LastSEDSyr,#N/A,SEDSDataPivots!D79))/10^6 -> #N/A | H93: =IF(B93>=FirstNEMSYrPlot,GETPIVOTDATA("CONSUMPTION",NEMSConsFcast!$A$9,"YEAR",B93)/10^9,#N/A) -> 11.108267 | J93: =IFERROR(IF(GETPIVOTDATA("Sum of "&D93,'RECS Data'!$B$99)=0,#N/A,GETPIVOTDATA("Sum of "&D93,'RECS Data'!$B$99)),#N/A) -> #N/A | K93: =IF($B93>RECSYr,GETPIVOTDATA("HOUSEHOLDS",HousingStockTable!$A$12,"YEAR",B93)/10^6,#N/A) -> 151.00626 | M93: =IFERROR(IF(AND(B93<=RECSYr,GETPIVOTDATA("Sum of "&B93,'RECS Data'!$B$179)>0),GETPIVOTDATA("Sum of "&B93,'RECS Data'!$B$179),#N/A)/1000,#N/A) -> #N/A | N93: =IF($B93>RECSYr,GETPIVOTDATA("HOUSEHOLDS",SqftTable!$A$7,"YEAR",B93),#N/A)/1000 -> 259.723 | P93: =IF(ISERROR(G93/J93*1000),#N/A,G93/J93*1000) -> #N/A | Q93: =H93/K93*1000 -> 73.561628 | S93: =IFERROR(G93/M93*10^3,#N/A) -> #N/A | T93: =H93/N93*1000 -> 42.769669 | V93: =IFERROR(M93*1000/J93,#N/A) -> #N/A | W93: =N93*1000/K93 -> 1719.9485
B94: 2042 | C94: =IF($D94>LastSEDSyr,#N/A,SEDSDataPivots!I80) -> #N/A | D94: 2042 | E94: =IF($E$4=0,#N/A,IF(B94>=FirstNEMSYrPlot,GETPIVOTDATA("EQSTOCK",NEMSPriceFcast!$A$7,"YEAR",B94)*$D$9,#N/A)) -> 1255.6691 | G94: =IF(G$16<1,#N/A,IF($D94>LastSEDSyr,#N/A,SEDSDataPivots!D80))/10^6 -> #N/A | H94: =IF(B94>=FirstNEMSYrPlot,GETPIVOTDATA("CONSUMPTION",NEMSConsFcast!$A$9,"YEAR",B94)/10^9,#N/A) -> 11.109854 | J94: =IFERROR(IF(GETPIVOTDATA("Sum of "&D94,'RECS Data'!$B$99)=0,#N/A,GETPIVOTDATA("Sum of "&D94,'RECS Data'!$B$99)),#N/A) -> #N/A | K94: =IF($B94>RECSYr,GETPIVOTDATA("HOUSEHOLDS",HousingStockTable!$A$12,"YEAR",B94)/10^6,#N/A) -> 151.9517 | M94: =IFERROR(IF(AND(B94<=RECSYr,GETPIVOTDATA("Sum of "&B94,'RECS Data'!$B$179)>0),GETPIVOTDATA("Sum of "&B94,'RECS Data'!$B$179),#N/A)/1000,#N/A) -> #N/A | N94: =IF($B94>RECSYr,GETPIVOTDATA("HOUSEHOLDS",SqftTable!$A$7,"YEAR",B94),#N/A)/1000 -> 262.036 | P94: =IF(ISERROR(G94/J94*1000),#N/A,G94/J94*1000) -> #N/A | Q94: =H94/K94*1000 -> 73.114376 | S94: =IFERROR(G94/M94*10^3,#N/A) -> #N/A | T94: =H94/N94*1000 -> 42.398196 | V94: =IFERROR(M94*1000/J94,#N/A) -> #N/A | W94: =N94*1000/K94 -> 1724.469
B95: 2043 | C95: =IF($D95>LastSEDSyr,#N/A,SEDSDataPivots!I81) -> #N/A | D95: 2043 | E95: =IF($E$4=0,#N/A,IF(B95>=FirstNEMSYrPlot,GETPIVOTDATA("EQSTOCK",NEMSPriceFcast!$A$7,"YEAR",B95)*$D$9,#N/A)) -> 1259.2164 | G95: =IF(G$16<1,#N/A,IF($D95>LastSEDSyr,#N/A,SEDSDataPivots!D81))/10^6 -> #N/A | H95: =IF(B95>=FirstNEMSYrPlot,GETPIVOTDATA("CONSUMPTION",NEMSConsFcast!$A$9,"YEAR",B95)/10^9,#N/A) -> 11.115803 | J95: =IFERROR(IF(GETPIVOTDATA("Sum of "&D95,'RECS Data'!$B$99)=0,#N/A,GETPIVOTDATA("Sum of "&D95,'RECS Data'!$B$99)),#N/A) -> #N/A | K95: =IF($B95>RECSYr,GETPIVOTDATA("HOUSEHOLDS",HousingStockTable!$A$12,"YEAR",B95)/10^6,#N/A) -> 152.8614 | M95: =IFERROR(IF(AND(B95<=RECSYr,GETPIVOTDATA("Sum of "&B95,'RECS Data'!$B$179)>0),GETPIVOTDATA("Sum of "&B95,'RECS Data'!$B$179),#N/A)/1000,#N/A) -> #N/A | N95: =IF($B95>RECSYr,GETPIVOTDATA("HOUSEHOLDS",SqftTable!$A$7,"YEAR",B95),#N/A)/1000 -> 264.287 | P95: =IF(ISERROR(G95/J95*1000),#N/A,G95/J95*1000) -> #N/A | Q95: =H95/K95*1000 -> 72.718178 | S95: =IFERROR(G95/M95*10^3,#N/A) -> #N/A | T95: =H95/N95*1000 -> 42.05959 | V95: =IFERROR(M95*1000/J95,#N/A) -> #N/A | W95: =N95*1000/K95 -> 1728.9322
B96: 2044 | C96: =IF($D96>LastSEDSyr,#N/A,SEDSDataPivots!I82) -> #N/A | D96: 2044 | E96: =IF($E$4=0,#N/A,IF(B96>=FirstNEMSYrPlot,GETPIVOTDATA("EQSTOCK",NEMSPriceFcast!$A$7,"YEAR",B96)*$D$9,#N/A)) -> 1263.0632 | G96: =IF(G$16<1,#N/A,IF($D96>LastSEDSyr,#N/A,SEDSDataPivots!D82))/10^6 -> #N/A | H96: =IF(B96>=FirstNEMSYrPlot,GETPIVOTDATA("CONSUMPTION",NEMSConsFcast!$A$9,"YEAR",B96)/10^9,#N/A) -> 11.12406 | J96: =IFERROR(IF(GETPIVOTDATA("Sum of "&D96,'RECS Data'!$B$99)=0,#N/A,GETPIVOTDATA("Sum of "&D96,'RECS Data'!$B$99)),#N/A) -> #N/A | K96: =IF($B96>RECSYr,GETPIVOTDATA("HOUSEHOLDS",HousingStockTable!$A$12,"YEAR",B96)/10^6,#N/A) -> 153.74846 | M96: =IFERROR(IF(AND(B96<=RECSYr,GETPIVOTDATA("Sum of "&B96,'RECS Data'!$B$179)>0),GETPIVOTDATA("Sum of "&B96,'RECS Data'!$B$179),#N/A)/1000,#N/A) -> #N/A | N96: =IF($B96>RECSYr,GETPIVOTDATA("HOUSEHOLDS",SqftTable!$A$7,"YEAR",B96),#N/A)/1000 -> 266.503 | P96: =IF(ISERROR(G96/J96*1000),#N/A,G96/J96*1000) -> #N/A | Q96: =H96/K96*1000 -> 72.352337 | S96: =IFERROR(G96/M96*10^3,#N/A) -> #N/A | T96: =H96/N96*1000 -> 41.740845 | V96: =IFERROR(M96*1000/J96,#N/A) -> #N/A | W96: =N96*1000/K96 -> 1733.3702
B97: 2045 | C97: =IF($D97>LastSEDSyr,#N/A,SEDSDataPivots!I83) -> #N/A | D97: 2045 | E97: =IF($E$4=0,#N/A,IF(B97>=FirstNEMSYrPlot,GETPIVOTDATA("EQSTOCK",NEMSPriceFcast!$A$7,"YEAR",B97)*$D$9,#N/A)) -> 1269.3285 | G97: =IF(G$16<1,#N/A,IF($D97>LastSEDSyr,#N/A,SEDSDataPivots!D83))/10^6 -> #N/A | H97: =IF(B97>=FirstNEMSYrPlot,GETPIVOTDATA("CONSUMPTION",NEMSConsFcast!$A$9,"YEAR",B97)/10^9,#N/A) -> 11.134093 | J97: =IFERROR(IF(GETPIVOTDATA("Sum of "&D97,'RECS Data'!$B$99)=0,#N/A,GETPIVOTDATA("Sum of "&D97,'RECS Data'!$B$99)),#N/A) -> #N/A | K97: =IF($B97>RECSYr,GETPIVOTDATA("HOUSEHOLDS",HousingStockTable!$A$12,"YEAR",B97)/10^6,#N/A) -> 154.63762 | M97: =IFERROR(IF(AND(B97<=RECSYr,GETPIVOTDATA("Sum of "&B97,'RECS Data'!$B$179)>0),GETPIVOTDATA("Sum of "&B97,'RECS Data'!$B$179),#N/A)/1000,#N/A) -> #N/A | N97: =IF($B97>RECSYr,GETPIVOTDATA("HOUSEHOLDS",SqftTable!$A$7,"YEAR",B97),#N/A)/1000 -> 268.715 | P97: =IF(ISERROR(G97/J97*1000),#N/A,G97/J97*1000) -> #N/A | Q97: =H97/K97*1000 -> 72.001195 | S97: =IFERROR(G97/M97*10^3,#N/A) -> #N/A | T97: =H97/N97*1000 -> 41.43458 | V97: =IFERROR(M97*1000/J97,#N/A) -> #N/A | W97: =N97*1000/K97 -> 1737.7078
B98: 2046 | C98: =IF($D98>LastSEDSyr,#N/A,SEDSDataPivots!I84) -> #N/A | D98: 2046 | E98: =IF($E$4=0,#N/A,IF(B98>=FirstNEMSYrPlot,GETPIVOTDATA("EQSTOCK",NEMSPriceFcast!$A$7,"YEAR",B98)*$D$9,#N/A)) -> 1275.709 | G98: =IF(G$16<1,#N/A,IF($D98>LastSEDSyr,#N/A,SEDSDataPivots!D84))/10^6 -> #N/A | H98: =IF(B98>=FirstNEMSYrPlot,GETPIVOTDATA("CONSUMPTION",NEMSConsFcast!$A$9,"YEAR",B98)/10^9,#N/A) -> 11.149922 | J98: =IFERROR(IF(GETPIVOTDATA("Sum of "&D98,'RECS Data'!$B$99)=0,#N/A,GETPIVOTDATA("Sum of "&D98,'RECS Data'!$B$99)),#N/A) -> #N/A | K98: =IF($B98>RECSYr,GETPIVOTDATA("HOUSEHOLDS",HousingStockTable!$A$12,"YEAR",B98)/10^6,#N/A) -> 155.53193 | M98: =IFERROR(IF(AND(B98<=RECSYr,GETPIVOTDATA("Sum of "&B98,'RECS Data'!$B$179)>0),GETPIVOTDATA("Sum of "&B98,'RECS Data'!$B$179),#N/A)/1000,#N/A) -> #N/A | N98: =IF($B98>RECSYr,GETPIVOTDATA("HOUSEHOLDS",SqftTable!$A$7,"YEAR",B98),#N/A)/1000 -> 270.931 | P98: =IF(ISERROR(G98/J98*1000),#N/A,G98/J98*1000) -> #N/A | Q98: =H98/K98*1000 -> 71.688958 | S98: =IFERROR(G98/M98*10^3,#N/A) -> #N/A | T98: =H98/N98*1000 -> 41.154102 | V98: =IFERROR(M98*1000/J98,#N/A) -> #N/A | W98: =N98*1000/K98 -> 1741.9639
B99: 2047 | C99: =IF($D99>LastSEDSyr,#N/A,SEDSDataPivots!I85) -> #N/A | D99: 2047 | E99: =IF($E$4=0,#N/A,IF(B99>=FirstNEMSYrPlot,GETPIVOTDATA("EQSTOCK",NEMSPriceFcast!$A$7,"YEAR",B99)*$D$9,#N/A)) -> 1281.2833 | G99: =IF(G$16<1,#N/A,IF($D99>LastSEDSyr,#N/A,SEDSDataPivots!D85))/10^6 -> #N/A | H99: =IF(B99>=FirstNEMSYrPlot,GETPIVOTDATA("CONSUMPTION",NEMSConsFcast!$A$9,"YEAR",B99)/10^9,#N/A) -> 11.165703 | J99: =IFERROR(IF(GETPIVOTDATA("Sum of "&D99,'RECS Data'!$B$99)=0,#N/A,GETPIVOTDATA("Sum of "&D99,'RECS Data'!$B$99)),#N/A) -> #N/A | K99: =IF($B99>RECSYr,GETPIVOTDATA("HOUSEHOLDS",HousingStockTable!$A$12,"YEAR",B99)/10^6,#N/A) -> 156.42377 | M99: =IFERROR(IF(AND(B99<=RECSYr,GETPIVOTDATA("Sum of "&B99,'RECS Data'!$B$179)>0),GETPIVOTDATA("Sum of "&B99,'RECS Data'!$B$179),#N/A)/1000,#N/A) -> #N/A | N99: =IF($B99>RECSYr,GETPIVOTDATA("HOUSEHOLDS",SqftTable!$A$7,"YEAR",B99),#N/A)/1000 -> 273.144 | P99: =IF(ISERROR(G99/J99*1000),#N/A,G99/J99*1000) -> #N/A | Q99: =H99/K99*1000 -> 71.381115 | S99: =IFERROR(G99/M99*10^3,#N/A) -> #N/A | T99: =H99/N99*1000 -> 40.878448 | V99: =IFERROR(M99*1000/J99,#N/A) -> #N/A | W99: =N99*1000/K99 -> 1746.1797
B100: 2048 | C100: =IF($D100>LastSEDSyr,#N/A,SEDSDataPivots!I86) -> #N/A | D100: 2048 | E100: =IF($E$4=0,#N/A,IF(B100>=FirstNEMSYrPlot,GETPIVOTDATA("EQSTOCK",NEMSPriceFcast!$A$7,"YEAR",B100)*$D$9,#N/A)) -> 1286.1666 | G100: =IF(G$16<1,#N/A,IF($D100>LastSEDSyr,#N/A,SEDSDataPivots!D86))/10^6 -> #N/A | H100: =IF(B100>=FirstNEMSYrPlot,GETPIVOTDATA("CONSUMPTION",NEMSConsFcast!$A$9,"YEAR",B100)/10^9,#N/A) -> 11.184945 | J100: =IFERROR(IF(GETPIVOTDATA("Sum of "&D100,'RECS Data'!$B$99)=0,#N/A,GETPIVOTDATA("Sum of "&D100,'RECS Data'!$B$99)),#N/A) -> #N/A | K100: =IF($B100>RECSYr,GETPIVOTDATA("HOUSEHOLDS",HousingStockTable!$A$12,"YEAR",B100)/10^6,#N/A) -> 157.31463 | M100: =IFERROR(IF(AND(B100<=RECSYr,GETPIVOTDATA("Sum of "&B100,'RECS Data'!$B$179)>0),GETPIVOTDATA("Sum of "&B100,'RECS Data'!$B$179),#N/A)/1000,#N/A) -> #N/A | N100: =IF($B100>RECSYr,GETPIVOTDATA("HOUSEHOLDS",SqftTable!$A$7,"YEAR",B100),#N/A)/1000 -> 275.352 | P100: =IF(ISERROR(G100/J100*1000),#N/A,G100/J100*1000) -> #N/A | Q100: =H100/K100*1000 -> 71.099206 | S100: =IFERROR(G100/M100*10^3,#N/A) -> #N/A | T100: =H100/N100*1000 -> 40.620535 | V100: =IFERROR(M100*1000/J100,#N/A) -> #N/A | W100: =N100*1000/K100 -> 1750.3267
B101: 2049 | C101: =IF($D101>LastSEDSyr,#N/A,SEDSDataPivots!I87) -> #N/A | D101: 2049 | E101: =IF($E$4=0,#N/A,IF(B101>=FirstNEMSYrPlot,GETPIVOTDATA("EQSTOCK",NEMSPriceFcast!$A$7,"YEAR",B101)*$D$9,#N/A)) -> 1291.188 | G101: =IF(G$16<1,#N/A,IF($D101>LastSEDSyr,#N/A,SEDSDataPivots!D87))/10^6 -> #N/A | H101: =IF(B101>=FirstNEMSYrPlot,GETPIVOTDATA("CONSUMPTION",NEMSConsFcast!$A$9,"YEAR",B101)/10^9,#N/A) -> 11.205852 | J101: =IFERROR(IF(GETPIVOTDATA("Sum of "&D101,'RECS Data'!$B$99)=0,#N/A,GETPIVOTDATA("Sum of "&D101,'RECS Data'!$B$99)),#N/A) -> #N/A | K101: =IF($B101>RECSYr,GETPIVOTDATA("HOUSEHOLDS",HousingStockTable!$A$12,"YEAR",B101)/10^6,#N/A) -> 158.20627 | M101: =IFERROR(IF(AND(B101<=RECSYr,GETPIVOTDATA("Sum of "&B101,'RECS Data'!$B$179)>0),GETPIVOTDATA("Sum of "&B101,'RECS Data'!$B$179),#N/A)/1000,#N/A) -> #N/A | N101: =IF($B101>RECSYr,GETPIVOTDATA("HOUSEHOLDS",SqftTable!$A$7,"YEAR",B101),#N/A)/1000 -> 277.561 | P101: =IF(ISERROR(G101/J101*1000),#N/A,G101/J101*1000) -> #N/A | Q101: =H101/K101*1000 -> 70.830645 | S101: =IFERROR(G101/M101*10^3,#N/A) -> #N/A | T101: =H101/N101*1000 -> 40.372573 | V101: =IFERROR(M101*1000/J101,#N/A) -> #N/A | W101: =N101*1000/K101 -> 1754.4248
B102: 2050 | C102: =IF($D102>LastSEDSyr,#N/A,SEDSDataPivots!I88) -> #N/A | D102: 2050 | E102: =IF($E$4=0,#N/A,IF(B102>=FirstNEMSYrPlot,GETPIVOTDATA("EQSTOCK",NEMSPriceFcast!$A$7,"YEAR",B102)*$D$9,#N/A)) -> 1296.7623 | G102: =IF(G$16<1,#N/A,IF($D102>LastSEDSyr,#N/A,SEDSDataPivots!D88))/10^6 -> #N/A | H102: =IF(B102>=FirstNEMSYrPlot,GETPIVOTDATA("CONSUMPTION",NEMSConsFcast!$A$9,"YEAR",B102)/10^9,#N/A) -> 11.23017 | J102: =IFERROR(IF(GETPIVOTDATA("Sum of "&D102,'RECS Data'!$B$99)=0,#N/A,GETPIVOTDATA("Sum of "&D102,'RECS Data'!$B$99)),#N/A) -> #N/A | K102: =IF($B102>RECSYr,GETPIVOTDATA("HOUSEHOLDS",HousingStockTable!$A$12,"YEAR",B102)/10^6,#N/A) -> 159.10183 | M102: =IFERROR(IF(AND(B102<=RECSYr,GETPIVOTDATA("Sum of "&B102,'RECS Data'!$B$179)>0),GETPIVOTDATA("Sum of "&B102,'RECS Data'!$B$179),#N/A)/1000,#N/A) -> #N/A | N102: =IF($B102>RECSYr,GETPIVOTDATA("HOUSEHOLDS",SqftTable!$A$7,"YEAR",B102),#N/A)/1000 -> 279.776 | P102: =IF(ISERROR(G102/J102*1000),#N/A,G102/J102*1000) -> #N/A | Q102: =H102/K102*1000 -> 70.584795 | S102: =IFERROR(G102/M102*10^3,#N/A) -> #N/A | T102: =H102/N102*1000 -> 40.139862 | V102: =IFERROR(M102*1000/J102,#N/A) -> #N/A | W102: =N102*1000/K102 -> 1758.4713

Sheet Units
B2: End-Use Equipment | C2: EQPCLASS (EquipStockTable) | D2: ENDUSE (EquipStockTable) | E2: Efficiency Metric | F2: RDM_DBOUT End Use
A3: Space Heating | F3: HT
B4: Air-Source Heat Pump | C4: ELEC_HP | D4: Heating | E4: Heating Seasonal Performance Factor (HSPF)
B5: Electric Furnace | C5: ELEC_RAD | D5: Heating | E5: Coefficient of Performance (COP)
B6: Distillate Fuel Oil/ Kerosene Boiler | C6: DIST_RAD | D6: Heating | E6: Annual Fuel Utilization Efficiency (AFUE)
B7: Distillate Fuel Oil/ Kerosene Furnace | C7: DIST_FA | D7: Heating | E7: AFUE
B8: Ground-Source Heat Pump | C8: GEO_HP | D8: Heating | E8: COP
B9: Propane Furnace | C9: LPG_FA | D9: Heating | E9: AFUE
B10: Natural Gas Boiler | C10: NG_RAD | D10: Heating | E10: AFUE
B11: Natural Gas Furnace | C11: NG_FA | D11: Heating | E11: AFUE
B12: Natural Gas Heat Pump | C12: NG_HP | D12: Heating | E12: COP
B13: Wood Stove | C13: WOOD_HT | D13: Heating | E13: COP
A14: Space Cooling | F14: CL
B15: Air-Source Heat Pump | C15: ELEC_HP | D15: Cooling | E15: Seasonal Energy Efficiency Ratio (SEER)
B16: Central Air Conditioner | C16: CENT_AIR | D16: Cooling | E16: SEER
B17: Ground-Source Heat Pump | C17: GEO_HP | D17: Cooling | E17: Energy Efficiency Ratio (EER)
B18: Natural Gas Heat Pump | C18: NG_HP | D18: Cooling | E18: COP
B19: Room Air Conditioner | C19: ROOM_AIR | D19: Cooling | E19: EER
A20: Water Heating | F20: HW
B21: Electricity Water Heater | C21: ELEC_WH | D21: HotWater | E21: Uniform Energy Factor (UEF)
B22: Distillate Fuel Oil/ Kerosene Water Heater | C22: DIST_WH | D22: HotWater | E22: UEF
B23: Propane Water Heater | C23: LPG_WH | D23: HotWater | E23: UEF
B24: Natural Gas Water Heater | C24: NG_WH | D24: HotWater | E24: UEF
B25: Solar Water Heater | C25: SOLAR_WH | D25: HotWater | E25: UEF
A26: Cooking | F26: CK
B27: Electric Cooking Range | C27: ELEC_STV | D27: Cooking | E27: kilowatthours per year (kWh/yr)
B28: Propane Cooking Range | C28: LPG_STV | D28: Cooking | E28: Thermal Efficiency (Btu Out / Btu In)
B29: Natural Gas Cooking Range | C29: NG_STV | D29: Cooking | E29: Thermal Efficiency (Btu Out / Btu In)
A30: Clothes Drying | F30: DR
B31: Electric Clothes Dryer | C31: ELEC_DRY | D31: Dryer | E31: Combined Energy Factor (CEF)
B32: Natural Gas Clothes Dryer | C32: NG_DRY | D32: Dryer | E32: CEF
A33: Clothes Washing | F33: CW
B34: Top-loading Clothes Washer | C34: CL_WASH | D34: ClothesWash | E34: kWh / cycle (motor), Modified Energy Factor (MEF), Water Factor (WF)
B35: Front-loading Clothes Washer | C35: CL_WASH | D35: ClothesWash | E35: kWh / cycle (motor), Modified Energy Factor (MEF), Water Factor (WF)
A36: Dishwashing | F36: DW
B37: Dishwasher | C37: DS_WASH | D37: DishWash | E37: cycles / kWh, kWh / year, gallons / cycle
A38: Refrigeration | F38: RF
B39: Refrigerator with top freezer (19 cubic foot capacity) | C39: REFR | D39: Refrigerator | E39: kWh / yr
B40: Refrigerator with side freezer (26 cubic foot capacity) | C40: REFR | D40: Refrigerator | E40: kWh / yr
B41: Refrigerator with bottom freezer (19 cubic foot capacity) | C41: REFR | D41: Refrigerator | E41: kWh / yr
A42: Freezing | F42: FZ
B43: Chest Freezer (16 cubic foot capacity) | C43: FREZ | D43: Freezer | E43: kWh / yr
B44: Upright Freezer (automatic defrost, 17 cubic foot capacity) | C44: FREZ | D44: Freezer | E44: kWh / yr
A45: Lighting | F45: LT
B46: General Service – Incandescent and Halogen | C46: GSL-INC | D46: Lighting | E46: watts
B47: General Service – Compact Fluorescent Lamp (CFL) | C47: GSL-CFL | D47: Lighting | E47: watts
B48: General Service – Light-Emitting Diode (LED) | C48: GSL-LED | D48: Lighting | E48: watts
B49: Reflector (Incandescent) | C49: REF-INC | D49: Lighting | E49: watts
B50: Reflector (Halogen) | C50: REF-HAL | D50: Lighting | E50: watts
B51: Reflector (CFL) | C51: REF-CFL | D51: Lighting | E51: watts
B52: Reflector (LED) | C52: REF-LED | D52: Lighting | E52: watts
B53: Linear Fluorescent (T12) | C53: LFL-T12 | D53: Lighting | E53: watts
B54: Linear Fluorescent (T8) | C54: LFL-T8 | D54: Lighting | E54: watts
B55: Linear Fluorescent (LED) | C55: LFL-LED | D55: Lighting | E55: watts
B56: Exterior (Incandescent and Halogen) | C56: EXT-INC | D56: Lighting | E56: watts
B57: Exterior (CFL) | C57: EXT-CFL | D57: Lighting | E57: watts
... B59: Exterior (LED) | C59: EXT-LED | D59: Lighting | E59: watts
A60: Televisions and Set-Top Boxes
B61: Televisions | C61: TV&R | D61: TV | E61: kWh / yr | F61: TVS
B62: Set-top Boxes | C62: TV&R | D62: SetTopBox | E62: kWh / yr | F62: STB
B63: Video Game Consoles | C63: TV&R | D63: VideoGameConsole | E63: kWh / yr | F63: VGC
B64: Home Theater Systems | C64: TV&R | D64: HomeTheaterSystem | E64: kWh / yr | F64: HTS
B65: Over-the-Top (OTT) Streaming Devices | C65: TV&R | D65: OTTstreaming | E65: kWh / yr | F65: OTT
A66: PCs and Related Equipment
B67: Desktops | C67: PC&R | D67: Desktop | E67: kWh / yr | F67: DPC
B68: Laptops | C68: PC&R | D68: Laptop | E68: kWh / yr | F68: LPC
B69: Monitors | C69: PC&R | D69: Monitor | E69: kWh / yr | F69: MON
B70: Networking Equipment (modems and routers) | C70: PC&R | D70: NetworkEquipment | E70: kWh / yr | F70: NET
A71: Secondary Heating1
B72: Natural Gas | C72: GS | D72: SecHeating | E72: mmBtu / yr | F72: SH
B73: Electric | C73: EL | D73: SecHeating | E73: mmBtu / yr | F73: SH
B74: Distillate Fuel Oil/ Kerosene | C74: DS | D74: SecHeating | E74: mmBtu / yr | F74: SH
B75: Propane | C75: LG | D75: SecHeating | E75: mmBtu / yr | F75: SH
B76: Wood | C76: WD | D76: SecHeating | E76: mmBtu / yr | F76: SH
A77: Furnace Fans and Boiler Circulation Pumps | F77: FF
B78: Furnace Fans and Boiler Circulation Pumps | C78: FurnaceFans | D78: FurnaceFans | E78: kWh / yr
A79: Electric Other Uses
B80: Ceiling Fans | C80: MEL | D80: CeilingFan | E80: kWh / yr | F80: CFN
B81: Coffee Makers | C81: MEL | D81: CoffeeMaker | E81: kWh / yr | F81: COF
B82: Dehumidifiers | C82: MEL | D82: Dehumidifier | E82: kWh / yr | F82: DEH
B83: Microwaves | C83: MEL | D83: Microwave | E83: kWh / yr | F83: MCO
B84: Pool Pumps | C84: MEL | D84: PoolPump | E84: kWh / yr | F84: PLP
B85: Pool Heaters | C85: MEL | D85: PoolHeater | E85: kWh / yr | F85: PLH
B86: Portable Electric Spas | C86: MEL | D86: Spa | E86: kWh / yr | F86: SPA
B87: Non-PC Rechargeable Electronics | C87: MEL | D87: Rechargeable | E87: kWh / yr | F87: BAT
B88: Tablets | C88: MEL | D88: Tablet | E88: kWh / yr | F88: TAB
B89: Smartphones | C89: MEL | D89: Smartphone | E89: kWh / yr | F89: PHN
B90: Smart Speakers | C90: MEL | D90: SmartSpeaker | E90: kWh / yr | F90: SPK
B91: Security System | C91: MEL | D91: SecuritySys | E91: kWh / yr | F91: SEC
... B97: Unspecified: Distillate Fuel Oil/ Kerosene | C97: DS | D97: OtherAppl | E97: mmBtu / yr | F97: OA
A98: Distributed Generation
B99: Solar Photovoltaic (PV) | C99: (separate database) | D99: (separate database) | E99: Electrical Efficiency | F99: -
B100: Fuel Cell | C100: (separate database) | D100: (separate database) | E100: Electrical Efficiency, Thermal Output | F100: -
B101: Small Wind Turbine | C101: (separate database) | D101: (separate database) | E101: Electrical Efficiency | F101: -
B103: 1 Secondary heating consumption is aggregated with space heating consumption by fuel
B105: For electricity consumption, translate mmBtu into million kWh by dividing mmBtu values by 3412.
A107: Other Variables
B108: Households | C108: - | D108: - | E108: Number of Housing Units | F108: HS
B109: Square Feet (average house size) | C109: - | D109: - | E109: Square Feet | F109: SQ
B110: Switch To | C110: - | D110: - | E110: Number of Units | F110: ST
...

Sheet NEMSPriceFcast
A1: 1987 $/mmBtu
A3: FUEL | B3: (All)
A4: CDIV | B4: (All)
A5: ENDUSE | B5: FP
A7: Sum of EQSTOCK
A8: YEAR | B8: Total
A9: 1990 | B9: 398.18
A10: 1991 | B10: 392.53
A11: 1992 | B11: 382.42
A12: 1993 | B12: 381.62
A13: 1994 | B13: 383.9
A14: 1995 | B14: 409.26
A15: 1996 | B15: 420.44
A16: 1997 | B16: 420.42
A17: 1998 | B17: 392.89
A18: 1999 | B18: 386.02
A19: 2000 | B19: 438.15
A20: 2001 | B20: 457.49
... A69: 2050 | B69: 562.97

Sheet NEMSConsFcast
A1: Delivered energy, mmBtu
A3: EQPCLASS | B3: (All)
A4: ENDUSE | B4: (Multiple Items)
A5: BLDG | B5: (All)
A6: FUEL | B6: (All)
A7: CDIV | B7: (All)
A9: Sum of CONSUMPTION
A10: YEAR | B10: Total
A11: 2020 | B11: 11222287378
A12: 2021 | B12: 11370043235
A13: 2022 | B13: 11906822378
A14: 2023 | B14: 11173912962
A15: 2024 | B15: 11123851170
A16: 2025 | B16: 11692794047
A17: 2026 | B17: 11495598106
A18: 2027 | B18: 11500735580
A19: 2028 | B19: 11527485697
A20: 2029 | B20: 11497263474
A21: 2030 | B21: 11431461455
A22: 2031 | B22: 11344948671
... A41: 2050 | B41: 11230169950

Sheet EquipStockTable
A1: Number of units (total stock)
A3: BLDG | B3: (All)
A4: CDIV | B4: (All)
A5: ENDUSE | B5: (All)
A6: FUEL | B6: (All)
A7: EQPCLASS | B7: (All)
A9: Sum of EQSTOCK
A10: YEAR | B10: Total
A11: 2020 | B11: 10280866567
A12: 2021 | B12: 10453704782
A13: 2022 | B13: 10651352454
A14: 2023 | B14: 10832271423
A15: 2024 | B15: 11006905883
A16: 2025 | B16: 11172515121
A17: 2026 | B17: 11336327071
A18: 2027 | B18: 11498094711
A19: 2028 | B19: 11654039352
A20: 2029 | B20: 11806276777
A21: 2030 | B21: 11954220390
A22: 2031 | B22: 12099210990
... A41: 2050 | B41: 14439403189

Sheet DetailedEquipTable
A1: Number of units (purchases)
A5: EQPTYPE | B5: (All)
A6: EQPCLASS | B6: (All)
A7: FUEL | B7: (All)
A8: ENDUSE | B8: (All)
A9: BLDG | B9: (All)
A10: CDIV | B10: (All)
B12: Data
A13: YEAR | B13: Sum of REPPURCHASE | C13: Sum of NEWPURCHASE | D13: Sum of TOTPURCHASE
A14: 2021 | B14: 848588696 | C14: 118918902 | D14: 967507598
A15: 2022 | B15: 670964105 | C15: 113644902 | D15: 784609007
A16: 2023 | B16: 658016637 | C16: 105749609 | D16: 763766246
A17: 2024 | B17: 585028294 | C17: 104081353 | D17: 689109647
A18: 2025 | B18: 545500900 | C18: 100594627 | D18: 646095527
A19: 2026 | B19: 530233403 | C19: 102127425 | D19: 632360828
A20: 2027 | B20: 501863035 | C20: 103200919 | D20: 605063954
A21: 2028 | B21: 502170839 | C21: 101913023 | D21: 604083862
A22: 2029 | B22: 516542600 | C22: 101878809 | D22: 618421409
A23: 2030 | B23: 520028945 | C23: 101142084 | D23: 621171029
A24: 2031 | B24: 540201913 | C24: 100582368 | D24: 640784281
A25: 2032 | B25: 549020071 | C25: 100329596 | D25: 649349667
... A43: 2050 | B43: 681351375 | C43: 74730064 | D43: 756081439

Sheet HousingStockTable
A1: Number of Households
A5: ENDUSE | B5: HT
A6: BLDG | B6: (All)
A7: CDIV | B7: (All)
A9: Sum of HOUSEHOLDS
A10: YEAR | B10: Total
A11: 2020 | B11: 123529024
A12: 2021 | B12: 125116611
A13: 2022 | B13: 126659565
A14: 2023 | B14: 128048589
A15: 2024 | B15: 129401591
A16: 2025 | B16: 130729203
A17: 2026 | B17: 132095186
A18: 2027 | B18: 133495360
A19: 2028 | B19: 134873478
A20: 2029 | B20: 136251925
A21: 2030 | B21: 137615488
A22: 2031 | B22: 138988196
... A41: 2050 | B41: 159101828

Sheet SqftTable
A1: Million Square Feet
A3: ENDUSE | B3: Squarefootage
A4: BLDG | B4: (All)
A5: CDIV | B5: (All)
A7: Sum of HOUSEHOLDS
A8: YEAR | B8: Total
A9: 2020 | B9: 199877
A10: 2021 | B10: 203298
A11: 2022 | B11: 206572
A12: 2023 | B12: 209614
A13: 2024 | B13: 212609
A14: 2025 | B14: 215504
A15: 2026 | B15: 218445
A16: 2027 | B16: 221422
A17: 2028 | B17: 224365
A18: 2029 | B18: 227308
A19: 2030 | B19: 230224
A20: 2031 | B20: 233120
... A39: 2050 | B39: 279776

Sheet HousingStartsTable
A1: Number of Starts
A6: BLDG | B6: (All)
A7: CDIV | B7: (All)
A9: Sum of EQSTOCK | B9: ENDUSE
A10: YEAR | B10: HousingStarts
A11: 2021 | B11: 1709000
A12: 2022 | B12: 1664084
A13: 2023 | B13: 1509999
A14: 2024 | B14: 1473418
A15: 2025 | B15: 1447719
A16: 2026 | B16: 1485832
A17: 2027 | B17: 1520279
A18: 2028 | B18: 1499065
A19: 2029 | B19: 1500317
A20: 2030 | B20: 1486238
A21: 2031 | B21: 1495565
A22: 2032 | B22: 1494399
... A40: 2050 | B40: 1018914

Sheet FuelSwitchingTable
A1: Number of units
A2: Model does not track specifically what fuels equipment are switched from and too (only THAT they are switching)
A6: BLDG | B6: (All)
A7: CDIV | B7: (All)
A9: Sum of EQSTOCK | B9: ENDUSE | C9: FUEL | D9: EQPCLASS
B10: SF | Q10: SF Total | R10: ST | AG10: ST Total
B11: Distillate | D11: Distillate Total | E11: EL | H11: EL Total | I11: Natural Gas | L11: Natural Gas Total | M11: Propane | N11: Propane Total | O11: Wood | P11: Wood Total | R11: Distillate | T11: Distillate Total | U11: EL | X11: EL Total | Y11: Natural Gas | AB11: Natural Gas Total | AC11: Propane | AD11: Propane Total | AE11: Wood | AF11: Wood Total
A12: YEAR | B12: DIST_FA | C12: DIST_RAD | E12: ELEC_HP | F12: ELEC_RAD | G12: GEO_HP | I12: NG_FA | J12: NG_HP | K12: NG_RAD | M12: LPG_FA | O12: WOOD_HT | R12: DIST_FA | S12: DIST_RAD | U12: ELEC_HP | V12: ELEC_RAD | W12: GEO_HP | Y12: NG_FA | Z12: NG_HP | AA12: NG_RAD | AC12: LPG_FA | AE12: WOOD_HT
A13: 2021 | B13: 19501 | C13: 1970 | D13: 21471 | E13: 11391 | F13: 3479 | G13: 0 | H13: 14870 | I13: 0 | J13: 0 | K13: 0 | L13: 0 | M13: 20970 | N13: 20970 | O13: 4838 | P13: 4838 | Q13: 62149 | R13: 271 | S13: 0 | T13: 271 | U13: 24208 | V13: 33849 | W13: 7 | X13: 58064 | Y13: 3774 | Z13: 0 | AA13: 9 | AB13: 3783 | AC13: 27 | AD13: 27 | AE13: 4 | AF13: 4 | AG13: 62149
A14: 2022 | B14: 32437 | C14: 7733 | D14: 40170 | E14: 10562 | F14: 4958 | G14: 0 | H14: 15520 | I14: 0 | J14: 0 | K14: 0 | L14: 0 | M14: 36521 | N14: 36521 | O14: 9081 | P14: 9081 | Q14: 101292 | R14: 1301 | S14: 0 | T14: 1301 | U14: 52631 | V14: 42218 | W14: 158 | X14: 95007 | Y14: 4962 | Z14: 0 | AA14: 12 | AB14: 4974 | AC14: 5 | AD14: 5 | AE14: 4 | AF14: 4 | AG14: 101291
A15: 2023 | B15: 32215 | C15: 3775 | D15: 35990 | E15: 11260 | F15: 4961 | G15: 0 | H15: 16221 | I15: 0 | J15: 0 | K15: 0 | L15: 0 | M15: 30831 | N15: 30831 | O15: 7733 | P15: 7733 | Q15: 90775 | R15: 182 | S15: 0 | T15: 182 | U15: 48366 | V15: 39196 | W15: 45 | X15: 87607 | Y15: 2932 | Z15: 0 | AA15: 10 | AB15: 2942 | AC15: 41 | AD15: 41 | AE15: 3 | AF15: 3 | AG15: 90775
A16: 2024 | B16: 31340 | C16: 2564 | D16: 33904 | E16: 11902 | F16: 4715 | G16: 0 | H16: 16617 | I16: 0 | J16: 0 | K16: 0 | L16: 0 | M16: 25066 | N16: 25066 | O16: 5606 | P16: 5606 | Q16: 81193 | R16: 120 | S16: 0 | T16: 120 | U16: 42153 | V16: 35537 | W16: 46 | X16: 77736 | Y16: 3249 | Z16: 0 | AA16: 14 | AB16: 3263 | AC16: 73 | AD16: 73 | AE16: 3 | AF16: 3 | AG16: 81195
A17: 2025 | B17: 31496 | C17: 3399 | D17: 34895 | E17: 10815 | F17: 5811 | G17: 0 | H17: 16626 | I17: 0 | J17: 0 | K17: 0 | L17: 0 | M17: 29030 | N17: 29030 | O17: 6801 | P17: 6801 | Q17: 87352 | R17: 423 | S17: 0 | T17: 423 | U17: 48052 | V17: 34847 | W17: 101 | X17: 83000 | Y17: 3840 | Z17: 0 | AA17: 9 | AB17: 3849 | AC17: 72 | AD17: 72 | AE17: 3 | AF17: 3 | AG17: 87347
A18: 2026 | B18: 29104 | C18: 1444 | D18: 30548 | E18: 12567 | F18: 5340 | G18: 0 | H18: 17907 | I18: 0 | J18: 0 | K18: 0 | L18: 0 | M18: 23426 | N18: 23426 | O18: 5115 | P18: 5115 | Q18: 76996 | R18: 216 | S18: 0 | T18: 216 | U18: 39911 | V18: 32992 | W18: 56 | X18: 72959 | Y18: 3674 | Z18: 0 | AA18: 8 | AB18: 3682 | AC18: 135 | AD18: 135 | AE18: 2 | AF18: 2 | AG18: 76994
A19: 2027 | B19: 29354 | C19: 2057 | D19: 31411 | E19: 14121 | F19: 5075 | G19: 0 | H19: 19196 | I19: 0 | J19: 0 | K19: 0 | L19: 0 | M19: 23116 | N19: 23116 | O19: 5048 | P19: 5048 | Q19: 78771 | R19: 210 | S19: 0 | T19: 210 | U19: 39598 | V19: 35160 | W19: 46 | X19: 74804 | Y19: 3601 | Z19: 0 | AA19: 8 | AB19: 3609 | AC19: 138 | AD19: 138 | AE19: 3 | AF19: 3 | AG19: 78764
A20: 2028 | B20: 28729 | C20: 2866 | D20: 31595 | E20: 15992 | F20: 4612 | G20: 0 | H20: 20604 | I20: 0 | J20: 0 | K20: 0 | L20: 0 | M20: 25922 | N20: 25922 | O20: 5438 | P20: 5438 | Q20: 83559 | R20: 211 | S20: 0 | T20: 211 | U20: 40532 | V20: 39681 | W20: 45 | X20: 80258 | Y20: 2982 | Z20: 0 | AA20: 10 | AB20: 2992 | AC20: 95 | AD20: 95 | AE20: 3 | AF20: 3 | AG20: 83559
A21: 2029 | B21: 27833 | C21: 3338 | D21: 31171 | E21: 16045 | F21: 4590 | G21: 0 | H21: 20635 | I21: 0 | J21: 0 | K21: 0 | L21: 0 | M21: 21755 | N21: 21755 | O21: 5576 | P21: 5576 | Q21: 79137 | R21: 223 | S21: 0 | T21: 223 | U21: 38118 | V21: 37921 | W21: 41 | X21: 76080 | Y21: 2660 | Z21: 0 | AA21: 10 | AB21: 2670 | AC21: 157 | AD21: 157 | AE21: 4 | AF21: 4 | AG21: 79134
A22: 2030 | B22: 27298 | C22: 3767 | D22: 31065 | E22: 16045 | F22: 4689 | G22: 0 | H22: 20734 | I22: 0 | J22: 0 | K22: 0 | L22: 0 | M22: 24114 | N22: 24114 | O22: 5885 | P22: 5885 | Q22: 81798 | R22: 251 | S22: 0 | T22: 251 | U22: 39205 | V22: 39314 | W22: 39 | X22: 78558 | Y22: 2845 | Z22: 0 | AA22: 12 | AB22: 2857 | AC22: 124 | AD22: 124 | AE22: 4 | AF22: 4 | AG22: 81794
A23: 2031 | B23: 26737 | C23: 3315 | D23: 30052 | E23: 15851 | F23: 4995 | G23: 0 | H23: 20846 | I23: 0 | J23: 0 | K23: 0 | L23: 0 | M23: 25600 | N23: 25600 | O23: 5882 | P23: 5882 | Q23: 82380 | R23: 285 | S23: 0 | T23: 285 | U23: 39170 | V23: 39370 | W23: 36 | X23: 78576 | Y23: 3401 | Z23: 0 | AA23: 12 | AB23: 3413 | AC23: 104 | AD23: 104 | AE23: 4 | AF23: 4 | AG23: 82382
A24: 2032 | B24: 25327 | C24: 3435 | D24: 28762 | E24: 15897 | F24: 4620 | G24: 0 | H24: 20517 | I24: 0 | J24: 0 | K24: 0 | L24: 0 | M24: 27059 | N24: 27059 | O24: 6321 | P24: 6321 | Q24: 82659 | R24: 291 | S24: 0 | T24: 291 | U24: 38860 | V24: 40464 | W24: 36 | X24: 79360 | Y24: 2918 | Z24: 0 | AA24: 10 | AB24: 2928 | AC24: 73 | AD24: 73 | AE24: 4 | AF24: 4 | AG24: 82656
... A42: 2050 | B42: 18115 | C42: 2087 | D42: 20202 | E42: 16770 | F42: 2646 | G42: 0 | H42: 19416 | I42: 0 | J42: 0 | K42: 0 | L42: 0 | M42: 21637 | N42: 21637 | O42: 4680 | P42: 4680 | Q42: 65935 | R42: 93 | S42: 0 | T42: 93 | U42: 25084 | V42: 39048 | W42: 13 | X42: 64145 | Y42: 1639 | Z42: 0 | AA42: 7 | AB42: 1646 | AC42: 46 | AD42: 46 | AE42: 4 | AF42: 4 | AG42: 65934

Sheet ShellTable
A1: Displays investment and subsidy, as well as annual new housing unit count, by shell type in this table -- note total expenditures on equipment or shell = consumer investment ("Sum of I_") + subsidy ("Sum of S_")
A2: i.e., total investment IECC2009 shells = S_IECC2009 + I_IECC2009; investments are in RTEKDOLLARYR dollars
A4: FUEL | B4: (All)
A5: BLDG | B5: (All)
A6: CDIV | B6: (All)
B8: Data
A9: YEAR | B9: Sum of S_BEST | C9: Sum of S_IECC+40% | D9: Sum of S_ESTAR | E9: Sum of S_IECC2009 | F9: Sum of S_NON_IECC09 | G9: Sum of I_BEST | H9: Sum of I_IECC+40% | I9: Sum of I_ESTAR | J9: Sum of I_IECC2009 | K9: Sum of I_NON_IECC09 | L9: Sum of BEST | M9: Sum of IECC+40% | N9: Sum of ESTAR | O9: Sum of IECC2009 | P9: Sum of NON_IECC09
A10: 2021 | B10: 100724957 | C10: 289362925 | D10: 0 | E10: 0 | F10: 0 | G10: 964417219 | H10: 2234537902 | I10: 2252871548 | J10: 4496338555 | K10: 0 | L10: 100051 | M10: 207570 | N10: 266832 | O10: 586264 | P10: 520474
A11: 2022 | B11: 253989944 | C11: 358224915 | D11: 0 | E11: 0 | F11: 0 | G11: 2408890247 | H11: 2744302503 | I11: 2533551420 | J11: 3764240671 | K11: 0 | L11: 238504 | M11: 249369 | N11: 300499 | O11: 506832 | P11: 368559
A12: 2023 | B12: 262931950 | C12: 608536442 | D12: 0 | E12: 0 | F12: 0 | G12: 1674164962 | H12: 3372084432 | I12: 2789593315 | J12: 2895361163 | K12: 0 | L12: 174086 | M12: 319293 | N12: 329889 | O12: 382356 | P12: 304062
A13: 2024 | B13: 253500950 | C13: 591853450 | D13: 0 | E13: 0 | F13: 0 | G13: 1599098584 | H13: 3248945210 | I13: 2914943622 | J13: 3097743396 | K13: 0 | L13: 152962 | M13: 293313 | N13: 328905 | O13: 385289 | P13: 312628
A14: 2025 | B14: 262298923 | C14: 601267914 | D14: 0 | E14: 0 | F14: 0 | G14: 1657329064 | H14: 3306690252 | I14: 2816195306 | J14: 2803470368 | K14: 0 | L14: 164049 | M14: 305893 | N14: 323762 | O14: 360175 | P14: 293407
A15: 2026 | B15: 152479431 | C15: 407612421 | D15: 0 | E15: 0 | F15: 0 | G15: 943997591 | H15: 2165269492 | I15: 1814026842 | J15: 4260662741 | K15: 0 | L15: 98743 | M15: 206311 | N15: 214608 | O15: 553480 | P15: 412247
A16: 2027 | B16: 0 | C16: 0 | D16: 0 | E16: 0 | F16: 0 | G16: 436481105 | H16: 894289738 | I16: 2251636717 | J16: 4904543769 | K16: 0 | L16: 60487 | M16: 105104 | N16: 265917 | O16: 641051 | P16: 447284
A17: 2028 | B17: 0 | C17: 0 | D17: 0 | E17: 0 | F17: 0 | G17: 429231307 | H17: 879047197 | I17: 2255637109 | J17: 4830313533 | K17: 0 | L17: 59177 | M17: 103084 | N17: 265411 | O17: 632810 | P17: 438155
A18: 2029 | B18: 0 | C18: 0 | D18: 0 | E18: 0 | F18: 0 | G18: 408345166 | H18: 934060732 | I18: 2485282872 | J18: 4617197637 | K18: 0 | L18: 57734 | M18: 109092 | N18: 289691 | O18: 609126 | P18: 434234
A19: 2030 | B19: 0 | C19: 0 | D19: 0 | E19: 0 | F19: 0 | G19: 416701726 | H19: 935121330 | I19: 2517587743 | J19: 4464625822 | K19: 0 | L19: 59427 | M19: 109571 | N19: 290897 | O19: 588777 | P19: 437148
A20: 2031 | B20: 0 | C20: 0 | D20: 0 | E20: 0 | F20: 0 | G20: 428777518 | H20: 944942364 | I20: 2534612464 | J20: 4373580998 | K20: 0 | L20: 62843 | M20: 113239 | N20: 295147 | O20: 585666 | P20: 438249
A21: 2032 | B21: 0 | C21: 0 | D21: 0 | E21: 0 | F21: 0 | G21: 432667731 | H21: 949502173 | I21: 2575557983 | J21: 4357033409 | K21: 0 | L21: 63056 | M21: 113560 | N21: 299181 | O21: 583921 | P21: 434255
... A39: 2050 | B39: 0 | C39: 0 | D39: 0 | E39: 0 | F39: 0 | G39: 311602761 | H39: 715456185 | I39: 2269423472 | J39: 2960854729 | K39: 0 | L39: 40786 | M39: 79912 | N39: 253998 | O39: 388499 | P39: 255267

Sheet ShellIndexTable
A1: Shell heating and cooling indices
A2: Index relative to RECS base year
A8: Sum of EQSTOCK | B8: ENDUSE
A9: YEAR | B9: CoolingIndexExisting | C9: CoolingIndexNew | D9: HeatingIndexExisting | E9: HeatingIndexNew
A10: 2020 | B10: 1 | C10: 1 | D10: 1 | E10: 1
A11: 2021 | B11: 0.99599755 | C11: 1.0091649 | D11: 0.98736274 | E11: 0.87648463
A12: 2022 | B12: 0.99208128 | C12: 0.99479604 | D12: 0.97692734 | E12: 0.81995225
A13: 2023 | B13: 0.98891568 | C13: 0.98634046 | D13: 0.96806389 | E13: 0.80307013
A14: 2024 | B14: 0.98679149 | C14: 0.9727568 | D14: 0.96188825 | E14: 0.78982347
A15: 2025 | B15: 0.98486483 | C15: 0.97893178 | D15: 0.95610034 | E15: 0.78972036
A16: 2026 | B16: 0.98308736 | C16: 1.0064977 | D16: 0.95072538 | E16: 0.86565924
A17: 2027 | B17: 0.98110241 | C17: 1.0235671 | D17: 0.94496751 | E17: 0.90141785
A18: 2028 | B18: 0.97895038 | C18: 1.0234783 | D18: 0.93891299 | E18: 0.90078545
A19: 2029 | B19: 0.97653568 | C19: 1.0224497 | D19: 0.93220139 | E19: 0.8984645
A20: 2030 | B20: 0.97393119 | C20: 1.0225478 | D20: 0.92494178 | E20: 0.90203619
A21: 2031 | B21: 0.97123021 | C21: 1.0262849 | D21: 0.91736883 | E21: 0.90737224
... A40: 2050 | B40: 0.92522109 | C40: 1.0139691 | D40: 0.78784168 | E40: 0.875063

Sheet EfficiencyTable
A1: See Units tab for efficiency metric by end use
A6: CDIV | B6: (All)
A7: ENDUSE | B7: Heating
A8: BLDG | B8: (All)
B10: Data | C10: EQPCLASS
B11: Average of EXEFF | L11: Average of NEWEFF
A12: YEAR | B12: DIST_FA | C12: DIST_RAD | D12: ELEC_HP | E12: ELEC_RAD | F12: GEO_HP | G12: LPG_FA | H12: NG_FA | I12: NG_HP | J12: NG_RAD | K12: WOOD_HT | L12: DIST_FA | M12: DIST_RAD | N12: ELEC_HP | O12: ELEC_RAD | P12: GEO_HP | Q12: LPG_FA | R12: NG_FA | S12: NG_HP | T12: NG_RAD | U12: WOOD_HT
A13: 2021 | B13: 0.8310037 | C13: 0.84204444 | D13: 8.0034889 | E13: 0.98110741 | F13: 3.1136852 | G13: 0.80365556 | H13: 0.80393704 | I13: 1.3 | J13: 0.8234037 | K13: 0.63354074 | L13: 0.59266667 | M13: 0.63865556 | N13: 8.9736074 | O13: 0.99715185 | P13: 2.5013852 | Q13: 0.8126037 | R13: 0.87658889 | S13: 0.96296296 | T13: 0.84302222 | U13: 0.58282222
A14: 2022 | B14: 0.83172593 | C14: 0.84278148 | D14: 8.1258407 | E14: 0.98223704 | F14: 3.1284 | G14: 0.80794074 | H14: 0.80845556 | I14: 1.3 | J14: 0.8272963 | K14: 0.63733704 | L14: 0.59014444 | M14: 0.63836296 | N14: 9.0035296 | O14: 0.99688519 | P14: 2.5100444 | Q14: 0.81754815 | R14: 0.88221852 | S14: 0.96296296 | T14: 0.84745556 | U14: 0.5828
A15: 2023 | B15: 0.83228519 | C15: 0.84331852 | D15: 8.2612148 | E15: 0.9833963 | F15: 3.1444926 | G15: 0.81227037 | H15: 0.81305926 | I15: 1.3 | J15: 0.83107407 | K15: 0.64108148 | L15: 0.59385185 | M15: 0.6393 | N15: 9.4626556 | O15: 0.99801481 | P15: 2.5187556 | Q15: 0.8199 | R15: 0.88624074 | S15: 0.96296296 | T15: 0.84747037 | U15: 0.58338889
A16: 2024 | B16: 0.83286296 | C16: 0.84386296 | D16: 8.3852074 | E16: 0.98448889 | F16: 3.1600815 | G16: 0.8166 | H16: 0.81767778 | I16: 1.3 | J16: 0.83484815 | K16: 0.6449 | L16: 0.59451111 | M16: 0.63951852 | N16: 9.4536185 | O16: 0.99751111 | P16: 2.5184593 | Q16: 0.82015185 | R16: 0.88636296 | S16: 0.96296296 | T16: 0.84747778 | U16: 0.58365185
A17: 2025 | B17: 0.8388 | C17: 0.85148889 | D17: 8.5539222 | E17: 0.98554444 | F17: 3.2874407 | G17: 0.82864815 | H17: 0.8223963 | I17: 1.3 | J17: 0.84341852 | K17: 0.67143704 | L17: 0.84515556 | M17: 0.86412963 | N17: 9.8613852 | O17: 0.99736667 | P17: 3.5470074 | Q17: 0.88758148 | R17: 0.88595556 | S17: 1.3 | T17: 0.91315185 | U17: 0.74514444
A18: 2026 | B18: 0.83836296 | C18: 0.85168148 | D18: 8.6721926 | E18: 0.98656667 | F18: 3.2762407 | G18: 0.8313963 | H18: 0.82668889 | I18: 1.3 | J18: 0.84644444 | K18: 0.67322593 | L18: 0.84304815 | M18: 0.86345556 | N18: 9.8012407 | O18: 0.99741481 | P18: 3.441737 | Q18: 0.87757407 | R18: 0.87803333 | S18: 1.3 | T18: 0.90947407 | U18: 0.73541481
A19: 2027 | B19: 0.83815926 | C19: 0.85198519 | D19: 8.7928185 | E19: 0.98762593 | F19: 3.2778519 | G19: 0.83468519 | H19: 0.83084815 | I19: 1.3 | J19: 0.84923333 | K19: 0.67597407 | L19: 0.84188519 | M19: 0.86306667 | N19: 9.7834556 | O19: 0.99804815 | P19: 3.4288296 | Q19: 0.87426667 | R19: 0.8753963 | S19: 1.3 | T19: 0.90747037 | U19: 0.73505185
A20: 2028 | B20: 0.83831111 | C20: 0.85243333 | D20: 8.9179889 | E20: 0.98866296 | F20: 3.2858074 | G20: 0.83829259 | H20: 0.83501481 | I20: 1.3 | J20: 0.85228148 | K20: 0.67898519 | L20: 0.84184815 | M20: 0.86306667 | N20: 9.7864667 | O20: 0.99807778 | P20: 3.4317519 | Q20: 0.87426296 | R20: 0.87568889 | S20: 1.3 | T20: 0.90762222 | U20: 0.7350963
A21: 2029 | B21: 0.83858148 | C21: 0.85293704 | D21: 9.034363 | E21: 0.98966296 | F21: 3.2962519 | G21: 0.8479037 | H21: 0.84354815 | I21: 1.3 | J21: 0.85544074 | K21: 0.6821037 | L21: 0.84182963 | M21: 0.86305926 | N21: 9.7842333 | O21: 0.99807407 | P21: 3.4349963 | Q21: 0.9463 | R21: 0.94436667 | S21: 1.3 | T21: 0.90781111 | U21: 0.73513333
A22: 2030 | B22: 0.83891111 | C22: 0.85347778 | D22: 9.1423667 | E22: 0.99063704 | F22: 3.3080593 | G22: 0.85742593 | H22: 0.85276667 | I22: 1.3 | J22: 0.85867037 | K22: 0.68524815 | L22: 0.84185556 | M22: 0.86306667 | N22: 9.7913481 | O22: 0.99806667 | P22: 3.439863 | Q22: 0.95994444 | R22: 0.9598 | S22: 1.3 | T22: 0.90816296 | U22: 0.73525556
A23: 2031 | B23: 0.83927037 | C23: 0.85404074 | D23: 9.241937 | E23: 0.99161481 | F23: 3.3207444 | G23: 0.86677037 | H23: 0.86209259 | I23: 1.3 | J23: 0.86188889 | K23: 0.68836667 | L23: 0.84195926 | M23: 0.86310741 | N23: 9.7937148 | O23: 0.99807037 | P23: 3.4437556 | Q23: 0.95994815 | R23: 0.95981111 | S23: 1.3 | T23: 0.90828889 | U23: 0.73525185
A24: 2032 | B24: 0.83963333 | C24: 0.85465185 | D24: 9.3328815 | E24: 0.99252222 | F24: 3.3333333 | G24: 0.87544444 | H24: 0.8709037 | I24: 1.3 | J24: 0.86508889 | K24: 0.6915 | L24: 0.84204074 | M24: 0.86312963 | N24: 9.7908 | O24: 0.9981 | P24: 3.4470889 | Q24: 0.95994815 | R24: 0.95984444 | S24: 1.3 | T24: 0.90845926 | U24: 0.73531111
... A42: 2050 | B42: 0.84314444 | C42: 0.86334444 | D42: 9.7852444 | E42: 0.99886296 | F42: 3.474763 | G42: 0.95089259 | H42: 0.95101111 | I42: 1.3 | J42: 0.90982222 | K42: 0.73825185 | L42: 0.8449037 | M42: 0.86362963 | N42: 9.806937 | O42: 1 | P42: 3.4900296 | Q42: 0.96047778 | R42: 0.96052222 | S42: 1.3 | T42: 0.91014815 | U42: 0.74064074

Sheet EStarEquipTable
A1: Number of units
A4: EQPTYPE | B4: (All)
A5: EQPCLASS | B5: (All)
A6: ENDUSE | B6: (All)
A7: FUEL | B7: (All)
A8: BLDG | B8: (All)
A9: CDIV | B9: (All)
A11: Sum of TotalPurchase
A12: YEAR | B12: Total
A13: 2021 | B13: 929979439
A14: 2022 | B14: 748158724
A15: 2023 | B15: 724788049
A16: 2024 | B16: 650295934
A17: 2025 | B17: 605719973
A18: 2026 | B18: 588194362
A19: 2027 | B19: 554173095
A20: 2028 | B20: 546681418
A21: 2029 | B21: 555736396
A22: 2030 | B22: 553488675
A23: 2031 | B23: 571345098
A24: 2032 | B24: 578138027
... A42: 2050 | B42: 685362810

Sheet InvestmentTable
A1: Displays Investment and Subsidy on the Shell and Investment Tables -- note total expenditures on equipment or shell = consumer investment ("Investment") + subsidy; subsidy includes both federal and non-federal subsidies
A2: i.e., total investment = totinvest + totsubsidy ; investments are in RTEKDOLLARYR dollars
A4: EQPTYPE | B4: (All)
A5: EQPCLASS | B5: (All)
A6: ENDUSE | B6: (All)
A7: FUEL | B7: (All)
A8: BLDG | B8: (All)
A9: CDIV | B9: (All)
B11: Data
A12: YEAR | B12: Sum of TOTSUBSIDY | C12: Sum of TOTPURCHASE | D12: Sum of TOTINVEST
A13: 2021 | B13: 4472798088 | C13: 967507598 | D13: 71938491422
A14: 2022 | B14: 7158870701 | C14: 784609007 | D14: 74538591190
A15: 2023 | B15: 7562323469 | C15: 763766246 | D15: 77121192434
A16: 2024 | B16: 7745695479 | C16: 689109647 | D16: 78979163967
A17: 2025 | B17: 7995993722 | C17: 646095527 | D17: 81029874976
A18: 2026 | B18: 1842680019 | C18: 632360828 | D18: 79738776927
A19: 2027 | B19: 1913579632 | C19: 605063954 | D19: 84897380618
A20: 2028 | B20: 1898814186 | C20: 604083862 | D20: 89055794763
A21: 2029 | B21: 1472502548 | C21: 618421409 | D21: 91456663659
A22: 2030 | B22: 1394884629 | C22: 621171029 | D22: 95291973926
A23: 2031 | B23: 1433275466 | C23: 640784281 | D23: 97553837391
A24: 2032 | B24: 1439643648 | C24: 649349667 | D24: 99197926933
... A42: 2050 | B42: 1442542694 | C42: 756081439 | D42: 99157867511

Sheet SEDSDataPivots
C2: SEDS consumption (billion Btu) | F2: SEDS expenditure (million dollars) | I2: <-- Refresh/expand source for pivot tables after using EIA & FRED Data add-on to refresh data in SEDS_CONS_API and SEDS_EXP_API tabs
C4: Division | D4: (All) | F4: Division | G4: (All) | I4: Note that SEDS Solar consumption includes distributed PV and solar thermal energy consumed by the residential, commercial, and industrial sectors, other than power generated at commercial and industrial facilities with capacity of 1 MW or greater
C5: Fuel | D5: Electricity | F5: Fuel | G5: Electricity
B7: Year | C7: Row Labels | F7: Row Labels | I7: =Deflators!B5&"$ per 1,000 MMBtu" -> 2022$ per 1,000 MMBtu | K7: Deflator
B8: =VALUE(MID(C8,8,4)) -> 1970 | C8: Sum of 1970-01-012 | F8: Sum of 1970-01-012 | I8: =IF(D8>0,G8/D8*1000/K8,#N/A) -> #N/A | K8: =HLOOKUP(B8,Deflators!$D$2:$BG$5,4,0) -> 0.17105568
B9: =VALUE(MID(C9,8,4)) -> #VALUE! | C9: 6997 | D9: 1798 | F9: 337.9 | G9: 15.5 | I9: =IF(D9>0,G9/D9*1000/K9,#N/A) -> #VALUE! | K9: =HLOOKUP(B9,Deflators!$D$2:$BG$5,4,0) -> #VALUE!
B10: =VALUE(MID(C10,8,4)) -> #VALUE! | C10: 7426 | D10: 4150 | F10: 390 | G10: 19.9 | I10: =IF(D10>0,G10/D10*1000/K10,#N/A) -> #VALUE! | K10: =HLOOKUP(B10,Deflators!$D$2:$BG$5,4,0) -> #VALUE!
B11: =VALUE(MID(C11,8,4)) -> #VALUE! | C11: 8092 | D11: 2832 | F11: 453.1 | G11: 27.7 | I11: =IF(D11>0,G11/D11*1000/K11,#N/A) -> #VALUE! | K11: =HLOOKUP(B11,Deflators!$D$2:$BG$5,4,0) -> #VALUE!
B12: =VALUE(MID(C12,8,4)) -> #VALUE! | C12: 9189 | D12: 4384 | F12: 557.9 | G12: 37.2 | I12: =IF(D12>0,G12/D12*1000/K12,#N/A) -> #VALUE! | K12: =HLOOKUP(B12,Deflators!$D$2:$BG$5,4,0) -> #VALUE!
B13: =VALUE(MID(C13,8,4)) -> #VALUE! | C13: 10058 | D13: 2059 | F13: 646.5 | G13: 42 | I13: =IF(D13>0,G13/D13*1000/K13,#N/A) -> #VALUE! | K13: =HLOOKUP(B13,Deflators!$D$2:$BG$5,4,0) -> #VALUE!
B14: =VALUE(MID(C14,8,4)) -> #VALUE! | C14: 10219 | D14: 4742 | F14: 721.7 | G14: 34.4 | I14: =IF(D14>0,G14/D14*1000/K14,#N/A) -> #VALUE! | K14: =HLOOKUP(B14,Deflators!$D$2:$BG$5,4,0) -> #VALUE!
B15: =VALUE(MID(C15,8,4)) -> #VALUE! | C15: 15883 | D15: 5037 | F15: 775.8 | G15: 30 | I15: =IF(D15>0,G15/D15*1000/K15,#N/A) -> #VALUE! | K15: =HLOOKUP(B15,Deflators!$D$2:$BG$5,4,0) -> #VALUE!
B16: =VALUE(MID(C16,8,4)) -> #VALUE! | C16: 16783 | D16: 5878 | F16: 809.2 | G16: 40 | I16: =IF(D16>0,G16/D16*1000/K16,#N/A) -> #VALUE! | K16: =HLOOKUP(B16,Deflators!$D$2:$BG$5,4,0) -> #VALUE!
B17: =VALUE(MID(C17,8,4)) -> #VALUE! | C17: 16827 | D17: 3988 | F17: 1015.8 | G17: 41 | I17: =IF(D17>0,G17/D17*1000/K17,#N/A) -> #VALUE! | K17: =HLOOKUP(B17,Deflators!$D$2:$BG$5,4,0) -> #VALUE!
B18: =VALUE(MID(C18,8,4)) -> #VALUE! | C18: 17289 | D18: 4775 | F18: 1082.5 | G18: 38.6 | I18: =IF(D18>0,G18/D18*1000/K18,#N/A) -> #VALUE! | K18: =HLOOKUP(B18,Deflators!$D$2:$BG$5,4,0) -> #VALUE!
B19: =VALUE(MID(C19,8,4)) -> #VALUE! | C19: 17899 | D19: 5411 | F19: 1141.7 | G19: 36 | I19: =IF(D19>0,G19/D19*1000/K19,#N/A) -> #VALUE! | K19: =HLOOKUP(B19,Deflators!$D$2:$BG$5,4,0) -> #VALUE!
B20: =VALUE(MID(C20,8,4)) -> #VALUE! | C20: 19638 | D20: 5234 | F20: 1195.2 | G20: 87 | I20: =IF(D20>0,G20/D20*1000/K20,#N/A) -> #VALUE! | K20: =HLOOKUP(B20,Deflators!$D$2:$BG$5,4,0) -> #VALUE!
... B58: =VALUE(MID(C58,8,4)) -> #VALUE! | C58: 463367 | D58: 83969 | F58: 10932.2 | G58: 413.2 | I58: =IF(D58>0,G58/D58*1000/K58,#N/A) -> #VALUE! | K58: =HLOOKUP(B58,Deflators!$D$2:$BG$5,4,0) -> #VALUE!
B59: =VALUE(MID(C59,8,4)) -> #VALUE! | C59: 575300 | D59: 111201 | F59: Sum of 1971-01-01 | I59: =IF(D59>0,G59/D59*1000/K59,#N/A) -> #VALUE! | K59: =HLOOKUP(B59,Deflators!$D$2:$BG$5,4,0) -> #VALUE!
B60: =VALUE(MID(C60,8,4)) -> 1971 | C60: Sum of 1971-01-01 | F60: 337.9 | G60: 16.8 | I60: =IF(D60>0,G60/D60*1000/K60,#N/A) -> #N/A | K60: =HLOOKUP(B60,Deflators!$D$2:$BG$5,4,0) -> 0.17973786
B61: =VALUE(MID(C61,8,4)) -> #VALUE! | C61: 6997 | D61: 2155 | F61: 390 | G61: 22.6 | I61: =IF(D61>0,G61/D61*1000/K61,#N/A) -> #VALUE! | K61: =HLOOKUP(B61,Deflators!$D$2:$BG$5,4,0) -> #VALUE!
C62: 7426 | D62: 4640 | F62: 453.1 | G62: 31.8
C63: 8092 | D63: 2925 | F63: 557.9 | G63: 39.3
C64: 9189 | D64: 4745 | F64: 646.5 | G64: 44.1
C65: 10058 | D65: 2231 | F65: 721.7 | G65: 36.6
C66: 10219 | D66: 5143 | F66: 775.8 | G66: 34.5
C67: 15883 | D67: 5686 | F67: 809.2 | G67: 44.2
C68: 16783 | D68: 6441 | F68: 1015.8 | G68: 45.4
C69: 16827 | D69: 4260 | F69: 1082.5 | G69: 43.7
C70: 17289 | D70: 5021 | F70: 1141.7 | G70: 41
C71: 17899 | D71: 5682 | F71: 1195.2 | G71: 95.9
C72: 19638 | D72: 5570 | F72: 1268.5 | G72: 44.2
C73: 25031 | D73: 5559 | F73: 1310.5 | G73: 46
... C109: 282585 | D109: 133301 | F109: 10932.2 | G109: 465.6
C110: 463367 | D110: 92893 | F110: Sum of 1972-01-01
C111: 575300 | D111: 122764 | F111: 337.9 | G111: 18.3
C112: Sum of 1972-01-01 | F112: 390 | G112: 23.7
C113: 6997 | D113: 2143 | F113: 453.1 | G113: 38.6
C114: 7426 | D114: 5105 | F114: 557.9 | G114: 43.7
C115: 8092 | D115: 2942 | F115: 646.5 | G115: 48.3
C116: 9189 | D116: 5155 | F116: 721.7 | G116: 39.9
C117: 10058 | D117: 2391 | F117: 775.8 | G117: 41.7
C118: 10219 | D118: 5475 | F118: 809.2 | G118: 52.7
C119: 15883 | D119: 6516 | F119: 1015.8 | G119: 50.9
C120: 16783 | D120: 7264 | F120: 1082.5 | G120: 47.9
C121: 16827 | D121: 4451 | F121: 1141.7 | G121: 45.2
C122: 17289 | D122: 5454 | F122: 1195.2 | G122: 96.3
C123: 17899 | D123: 6162 | F123: 1268.5 | G123: 47.8
C124: 19638 | D124: 5995 | F124: 1310.5 | G124: 53.7
... C160: 200412 | D160: 56564 | F160: 10932.2 | G160: 582.8
C161: 282585 | D161: 140949 | F161: Sum of 1973-01-01
C162: 463367 | D162: 103875 | F162: 337.9 | G162: 19.5
C163: 575300 | D163: 139886 | F163: 390 | G163: 27.7
C164: Sum of 1973-01-01 | F164: 453.1 | G164: 41.9
C165: 6997 | D165: 2342 | F165: 557.9 | G165: 44.6
C166: 7426 | D166: 5169 | F166: 646.5 | G166: 49.4
C167: 8092 | D167: 3254 | F167: 721.7 | G167: 42.6
C168: 9189 | D168: 5456 | F168: 775.8 | G168: 48.2
C169: 10058 | D169: 2677 | F169: 809.2 | G169: 59.7
C170: 10219 | D170: 5876 | F170: 1015.8 | G170: 57
C171: 15883 | D171: 7046 | F171: 1082.5 | G171: 51.9
C172: 16783 | D172: 7723 | F172: 1141.7 | G172: 52.3
C173: 16827 | D173: 4926 | F173: 1195.2 | G173: 99.9
C174: 17289 | D174: 5537 | F174: 1268.5 | G174: 54
C175: 17899 | D175: 6289 | F175: 1310.5 | G175: 61.6
C176: 19638 | D176: 6184 | F176: 1348.8 | G176: 66.8
... C211: 199303 | D211: 52486 | F211: 10932.2 | G211: 713.2
C212: 200412 | D212: 63055 | F212: Sum of 1974-01-01
C213: 282585 | D213: 148408 | F213: 337.9 | G213: 21.2
C214: 463367 | D214: 120232 | F214: 390 | G214: 34.7
C215: 575300 | D215: 145461 | F215: 453.1 | G215: 50.5
C216: Sum of 1974-01-01 | F216: 557.9 | G216: 50.3
C217: 6997 | D217: 2574 | F217: 646.5 | G217: 55.1
C218: 7426 | D218: 5106 | F218: 721.7 | G218: 45.8
C219: 8092 | D219: 3017 | F219: 775.8 | G219: 61.6
C220: 9189 | D220: 5646 | F220: 809.2 | G220: 83.2
C221: 10058 | D221: 2771 | F221: 1015.8 | G221: 65
C222: 10219 | D222: 5691 | F222: 1082.5 | G222: 57.4
C223: 15883 | D223: 7227 | F223: 1141.7 | G223: 62.6
C224: 16783 | D224: 8217 | F224: 1195.2 | G224: 111.2
C225: 16827 | D225: 4699 | F225: 1268.5 | G225: 63.5
C226: 17289 | D226: 5933 | F226: 1310.5 | G226: 84.9
C227: 17899 | D227: 6529 | F227: 1348.8 | G227: 82.7
C228: 19638 | D228: 6390 | F228: 1437.9 | G228: 138.9
... C262: 178542 | D262: 93296 | F262: 10932.2 | G262: 900.8
C263: 199303 | D263: 51515 | F263: Sum of 1975-01-01
C264: 200412 | D264: 63432 | F264: 337.9 | G264: 23
C265: 282585 | D265: 145123 | F265: 390 | G265: 39.2
C266: 463367 | D266: 117186 | F266: 453.1 | G266: 55.8
C267: 575300 | D267: 148514 | F267: 557.9 | G267: 59.5
C268: Sum of 1975-01-01 | F268: 646.5 | G268: 63.3
C269: 6997 | D269: 3063 | F269: 721.7 | G269: 51.3
C270: 7426 | D270: 4870 | F270: 775.8 | G270: 77.9
C271: 8092 | D271: 3102 | F271: 809.2 | G271: 88.7
C272: 9189 | D272: 5674 | F272: 1015.8 | G272: 69.9
C273: 10058 | D273: 3040 | F273: 1082.5 | G273: 69.5
C274: 10219 | D274: 5747 | F274: 1141.7 | G274: 82.8
C275: 15883 | D275: 7328 | F275: 1195.2 | G275: 130.3
C276: 16783 | D276: 8486 | F276: 1268.5 | G276: 75.2
C277: 16827 | D277: 5596 | F277: 1310.5 | G277: 104.5
...

Sheet SEDS_CONS_API
A1: 1date | B1: A | C1: 25569 | D1: 44197 | E1: Source | F1: date | G1: 45292 | H1: 44927 | I1: 44562 | J1: 44197 | K1: 43831 | L1: 43466 | M1: 43101 | N1: 42736 | O1: 42370 | P1: 42005 | Q1: 41640 | R1: 41275 | S1: 40909 | T1: 40544 | U1: 40179 | V1: 39814 | W1: 39448 | X1: 39083 | Y1: 38718 | Z1: 38353 | AA1: 37987 | AB1: 37622 | AC1: 37257 | AD1: 36892 | AE1: 36526 | AF1: 36161 | AG1: 35796 | AH1: 35431 | AI1: 35065 | AJ1: 34700 | AK1: 34335 | AL1: 33970 | AM1: 33604 | AN1: 33239 | AO1: 32874 | AP1: 32509 | AQ1: 32143 | AR1: 31778 | AS1: 31413 | AT1: 31048 | AU1: 30682 | AV1: 30317 | AW1: 29952 | AX1: 29587 | AY1: 29221 | AZ1: 28856 | BA1: 28491 | BB1: 28126 | BC1: 27760 | BD1: 27395 | BE1: 27030 | BF1: 26665 | BG1: 26299 | BH1: 25934 | BI1: 25569 | BJ1: Division | BK1: Fuel
A2: SEDS.ESRCB.AL.A | C2: Billion Btu | E2: EIA, U.S. Energy Information Administration | F2: value | G2: 112252 | H2: 107170 | I2: 112335 | J2: 107769 | K2: 106902 | L2: 110602 | M2: 112870 | N2: 102978 | O2: 109374 | P2: 108872 | Q2: 112356 | R2: 107064 | S2: 104517 | T2: 112606 | U2: 121226 | V2: 107442 | W2: 109814 | X2: 111857 | Y2: 110129 | Z2: 106847 | AA2: 102732 | AB2: 100369 | AC2: 102434 | AD2: 94861 | AE2: 98116 | AF2: 92287 | AG2: 93240 | AH2: 84935 | AI2: 87463 | AJ2: 82959 | AK2: 79017 | AL2: 77206 | AM2: 72118 | AN2: 72653 | AO2: 70692 | AP2: 67702 | AQ2: 67015 | AR2: 65833 | AS2: 62299 | AT2: 58626 | AU2: 58046 | AV2: 53958 | AW2: 53847 | AX2: 54291 | AY2: 56192 | AZ2: 51279 | BA2: 53701 | BB2: 52022 | BC2: 48066 | BD2: 45752 | BE2: 50113 | BF2: 50171 | BG2: 45542 | BH2: 41754 | BI2: 39331 | BJ2: =VLOOKUP(MID(A2,12,2),'State Codes'!$B$10:$D$60,3,0) -> 6 East South Central | BK2: =VLOOKUP(MID(A2,6,5),'Chart Controls'!$P$3:$Q$8,2,0) -> Electricity
A3: SEDS.ESRCB.AK.A | C3: Billion Btu | E3: EIA, U.S. Energy Information Administration | F3: value | G3: 7065 | H3: 6997 | I3: 6996 | J3: 7110 | K3: 7128 | L3: 6579 | M3: 6738 | N3: 7030 | O3: 6846 | P3: 6975 | Q3: 6973 | R3: 7179 | S3: 7371 | T3: 7283 | U3: 7142 | V3: 7225 | W3: 7267 | X3: 7215 | Y3: 7234 | Z3: 7034 | AA3: 7035 | AB3: 6780 | AC3: 6593 | AD3: 6454 | AE3: 6329 | AF3: 6366 | AG3: 6032 | AH3: 5889 | AI3: 6026 | AJ3: 5844 | AK3: 5760 | AL3: 5558 | AM3: 5596 | AN3: 5469 | AO3: 5668 | AP3: 5607 | AQ3: 5426 | AR3: 5283 | AS3: 5544 | AT3: 5711 | AU3: 5450 | AV3: 4959 | AW3: 4805 | AX3: 4190 | AY3: 3726 | AZ3: 3641 | BA3: 3787 | BB3: 3655 | BC3: 3355 | BD3: 3063 | BE3: 2574 | BF3: 2342 | BG3: 2143 | BH3: 2155 | BI3: 1798 | BJ3: =VLOOKUP(MID(A3,12,2),'State Codes'!$B$10:$D$60,3,0) -> 9 Pacific | BK3: =VLOOKUP(MID(A3,6,5),'Chart Controls'!$P$3:$Q$8,2,0) -> Electricity
A4: SEDS.ESRCB.AZ.A | C4: Billion Btu | E4: EIA, U.S. Energy Information Administration | F4: value | G4: 137964 | H4: 133042 | I4: 130910 | J4: 126689 | K4: 132070 | L4: 118465 | M4: 118261 | N4: 116865 | O4: 114953 | P4: 113167 | Q4: 110365 | R4: 112949 | S4: 112333 | T4: 112866 | U4: 110713 | V4: 112073 | W4: 113402 | X4: 117498 | Y4: 110438 | Z4: 104215 | AA4: 98677 | AB4: 94654 | AC4: 90120 | AD4: 89395 | AE4: 84768 | AF4: 76829 | AG4: 73736 | AH4: 70569 | AI4: 67375 | AJ4: 61537 | AK4: 62141 | AL4: 56998 | AM4: 55378 | AN4: 53369 | AO4: 52469 | AP4: 52024 | AQ4: 50262 | AR4: 47156 | AS4: 42785 | AT4: 41794 | AU4: 37908 | AV4: 35576 | AW4: 32426 | AX4: 32516 | AY4: 32881 | AZ4: 31745 | BA4: 28634 | BB4: 26800 | BC4: 24903 | BD4: 24353 | BE4: 24209 | BF4: 22918 | BG4: 19851 | BH4: 16825 | BI4: 14765 | BJ4: =VLOOKUP(MID(A4,12,2),'State Codes'!$B$10:$D$60,3,0) -> 8 Mountain | BK4: =VLOOKUP(MID(A4,6,5),'Chart Controls'!$P$3:$Q$8,2,0) -> Electricity
A5: SEDS.ESRCB.AR.A | C5: Billion Btu | E5: EIA, U.S. Energy Information Administration | F5: value | G5: 63397 | H5: 62692 | I5: 65683 | J5: 64548 | K5: 61348 | L5: 63915 | M5: 65712 | N5: 58095 | O5: 60680 | P5: 62349 | Q5: 62921 | R5: 62164 | S5: 61107 | T5: 64102 | U5: 65616 | V5: 57955 | W5: 59343 | X5: 59418 | Y5: 58226 | Z5: 58460 | AA5: 53293 | AB5: 53221 | AC5: 52979 | AD5: 51535 | AE5: 50739 | AF5: 47923 | AG5: 48926 | AH5: 44321 | AI5: 44131 | AJ5: 42367 | AK5: 39723 | AL5: 40131 | AM5: 35622 | AN5: 37534 | AO5: 36023 | AP5: 33974 | AQ5: 33935 | AR5: 33122 | AS5: 31574 | AT5: 30489 | AU5: 29901 | AV5: 30017 | AW5: 29401 | AX5: 28751 | AY5: 34895 | AZ5: 30237 | BA5: 31807 | BB5: 30081 | BC5: 26429 | BD5: 26447 | BE5: 20753 | BF5: 20955 | BG5: 18709 | BH5: 16164 | BI5: 14745 | BJ5: =VLOOKUP(MID(A5,12,2),'State Codes'!$B$10:$D$60,3,0) -> 7 West South Central | BK5: =VLOOKUP(MID(A5,6,5),'Chart Controls'!$P$3:$Q$8,2,0) -> Electricity
A6: SEDS.ESRCB.CA.A | C6: Billion Btu | E6: EIA, U.S. Energy Information Administration | F6: value | G6: 292922 | H6: 282585 | I6: 305518 | J6: 308049 | K6: 323917 | L6: 298632 | M6: 304009 | N6: 307501 | O6: 301317 | P6: 304986 | Q6: 304899 | R6: 304493 | S6: 307455 | T6: 301615 | U6: 297721 | V6: 306393 | W6: 311280 | X6: 304209 | Y6: 306520 | Z6: 292103 | AA6: 284429 | AB6: 282943 | AC6: 263414 | AD6: 261590 | AE6: 270369 | AF6: 256935 | AG6: 256601 | AH6: 249370 | AI6: 243604 | AJ6: 234687 | AK6: 234972 | AL6: 229828 | AM6: 232429 | AN6: 225249 | AO6: 227153 | AP6: 219553 | AQ6: 220548 | AR6: 205976 | AS6: 196334 | AT6: 196193 | AU6: 192886 | AV6: 183813 | AW6: 176989 | AX6: 180146 | AY6: 177462 | AZ6: 178860 | BA6: 168283 | BB6: 158847 | BC6: 156102 | BD6: 151005 | BE6: 145123 | BF6: 148408 | BG6: 140949 | BH6: 133301 | BI6: 122071 | BJ6: =VLOOKUP(MID(A6,12,2),'State Codes'!$B$10:$D$60,3,0) -> 9 Pacific | BK6: =VLOOKUP(MID(A6,6,5),'Chart Controls'!$P$3:$Q$8,2,0) -> Electricity
A7: SEDS.ESRCB.CO.A | C7: Billion Btu | E7: EIA, U.S. Energy Information Administration | F7: value | G7: 70607 | H7: 68238 | I7: 70267 | J7: 70373 | K7: 69886 | L7: 66209 | M7: 65807 | N7: 63514 | O7: 64261 | P7: 62729 | Q7: 61733 | R7: 63221 | S7: 62168 | T7: 62360 | U7: 61765 | V7: 59412 | W7: 60462 | X7: 60168 | Y7: 57839 | Z7: 56081 | AA7: 52996 | AB7: 53653 | AC7: 52630 | AD7: 49372 | AE7: 47867 | AF7: 44802 | AG7: 43167 | AH7: 41834 | AI7: 40502 | AJ7: 38578 | AK7: 37323 | AL7: 36357 | AM7: 34856 | AN7: 34459 | AO7: 33394 | AP7: 32740 | AQ7: 32586 | AR7: 31451 | AS7: 30240 | AT7: 30235 | AU7: 29578 | AV7: 32458 | AW7: 30925 | AX7: 28996 | AY7: 22837 | AZ7: 21888 | BA7: 20295 | BB7: 18858 | BC7: 18258 | BD7: 17544 | BE7: 18374 | BF7: 17748 | BG7: 15927 | BH7: 14360 | BI7: 13167 | BJ7: =VLOOKUP(MID(A7,12,2),'State Codes'!$B$10:$D$60,3,0) -> 8 Mountain | BK7: =VLOOKUP(MID(A7,6,5),'Chart Controls'!$P$3:$Q$8,2,0) -> Electricity
A8: SEDS.ESRCB.CT.A | C8: Billion Btu | E8: EIA, U.S. Energy Information Administration | F8: value | G8: 44158 | H8: 42832 | I8: 45007 | J8: 44670 | K8: 44294 | L8: 42628 | M8: 44565 | N8: 42239 | O8: 43254 | P8: 43990 | Q8: 43597 | R8: 44818 | S8: 43529 | T8: 44079 | U8: 44579 | V8: 42917 | W8: 43434 | X8: 45626 | Y8: 44231 | Z8: 47096 | AA8: 45077 | AB8: 44964 | AC8: 42557 | AD8: 40857 | AE8: 39734 | AF8: 39644 | AG8: 37310 | AH8: 37051 | AI8: 37337 | AJ8: 36713 | AK8: 37185 | AL8: 36156 | AM8: 35813 | AN8: 35623 | AO8: 35403 | AP8: 35776 | AQ8: 35145 | AR8: 32994 | AS8: 30982 | AT8: 29474 | AU8: 29290 | AV8: 29913 | AW8: 29020 | AX8: 29391 | AY8: 28040 | AZ8: 27893 | BA8: 27566 | BB8: 27158 | BC8: 26758 | BD8: 25417 | BE8: 25894 | BF8: 26070 | BG8: 24924 | BH8: 23319 | BI8: 21824 | BJ8: =VLOOKUP(MID(A8,12,2),'State Codes'!$B$10:$D$60,3,0) -> 1 New England | BK8: =VLOOKUP(MID(A8,6,5),'Chart Controls'!$P$3:$Q$8,2,0) -> Electricity
A9: SEDS.ESRCB.DE.A | C9: Billion Btu | E9: EIA, U.S. Energy Information Administration | F9: value | G9: 17655 | H9: 16827 | I9: 17777 | J9: 17641 | K9: 17030 | L9: 17074 | M9: 17299 | N9: 15909 | O9: 16252 | P9: 16545 | Q9: 15848 | R9: 15593 | S9: 15428 | T9: 15805 | U9: 16241 | V9: 14791 | W9: 15109 | X9: 15250 | Y9: 14530 | Z9: 15675 | AA9: 14687 | AB9: 14298 | AC9: 13717 | AD9: 12740 | AE9: 12197 | AF9: 12051 | AG9: 11392 | AH9: 11114 | AI9: 11161 | AJ9: 10810 | AK9: 10602 | AL9: 10386 | AM9: 9507 | AN9: 9637 | AO9: 9047 | AP9: 8948 | AQ9: 8643 | AR9: 7947 | AS9: 7237 | AT9: 6565 | AU9: 6495 | AV9: 5274 | AW9: 5003 | AX9: 4925 | AY9: 6367 | AZ9: 6196 | BA9: 6213 | BB9: 6108 | BC9: 5854 | BD9: 5596 | BE9: 4699 | BF9: 4926 | BG9: 4451 | BH9: 4260 | BI9: 3988 | BJ9: =VLOOKUP(MID(A9,12,2),'State Codes'!$B$10:$D$60,3,0) -> 5 South Atlantic | BK9: =VLOOKUP(MID(A9,6,5),'Chart Controls'!$P$3:$Q$8,2,0) -> Electricity
A10: SEDS.ESRCB.DC.A | C10: Billion Btu | E10: EIA, U.S. Energy Information Administration | F10: value | G10: 8345 | H10: 8092 | I10: 8595 | J10: 8626 | K10: 8368 | L10: 8690 | M10: 8845 | N10: 8171 | O10: 8536 | P10: 8522 | Q10: 7070 | R10: 6939 | S10: 6833 | T10: 7033 | U10: 7245 | V10: 6482 | W10: 6536 | X10: 6720 | Y10: 6217 | Z10: 6613 | AA10: 6259 | AB10: 5986 | AC10: 6108 | AD10: 5797 | AE10: 5541 | AF10: 5605 | AG10: 5444 | AH10: 5301 | AI10: 5508 | AJ10: 5488 | AK10: 5362 | AL10: 5578 | AM10: 5077 | AN10: 5391 | AO10: 5051 | AP10: 5002 | AQ10: 5000 | AR10: 4812 | AS10: 4543 | AT10: 4207 | AU10: 4188 | AV10: 4120 | AW10: 3800 | AX10: 3717 | AY10: 3702 | AZ10: 3364 | BA10: 3327 | BB10: 3258 | BC10: 3175 | BD10: 3102 | BE10: 3017 | BF10: 3254 | BG10: 2942 | BH10: 2925 | BI10: 2832 | BJ10: =VLOOKUP(MID(A10,12,2),'State Codes'!$B$10:$D$60,3,0) -> 5 South Atlantic | BK10: =VLOOKUP(MID(A10,6,5),'Chart Controls'!$P$3:$Q$8,2,0) -> Electricity
A11: SEDS.ESRCB.FL.A | C11: Billion Btu | E11: EIA, U.S. Energy Information Administration | F11: value | G11: 472121 | H11: 463367 | I11: 458047 | J11: 444967 | K11: 454816 | L11: 433943 | M11: 428302 | N11: 414430 | O11: 420770 | P11: 418855 | Q11: 397618 | R11: 386559 | S11: 382578 | T11: 396956 | U11: 417099 | V11: 393996 | W11: 388753 | X11: 401989 | Y11: 399385 | Z11: 395080 | AA11: 382837 | AB11: 384361 | AC11: 369055 | AD11: 345899 | AE11: 337807 | AF11: 320203 | AG11: 326761 | AH11: 299728 | AI11: 301330 | AJ11: 292646 | AK11: 274991 | AL11: 262135 | AM11: 249721 | AN11: 248441 | AO11: 242643 | AP11: 232642 | AQ11: 218272 | AR11: 206105 | AS11: 196778 | AT11: 184652 | AU11: 171674 | AV11: 161318 | AW11: 153971 | AX11: 157425 | AY11: 152673 | AZ11: 144048 | BA11: 142782 | BB11: 132914 | BC11: 122907 | BD11: 118588 | BE11: 117186 | BF11: 120232 | BG11: 103875 | BH11: 92893 | BI11: 83969 | BJ11: =VLOOKUP(MID(A11,12,2),'State Codes'!$B$10:$D$60,3,0) -> 5 South Atlantic | BK11: =VLOOKUP(MID(A11,6,5),'Chart Controls'!$P$3:$Q$8,2,0) -> Electricity
A12: SEDS.ESRCB.GA.A | C12: Billion Btu | E12: EIA, U.S. Energy Information Administration | F12: value | G12: 211759 | H12: 199303 | I12: 208611 | J12: 200233 | K12: 198648 | L12: 202439 | M12: 203659 | N12: 186880 | O12: 197519 | P12: 192511 | Q12: 195055 | R12: 182694 | S12: 183088 | T12: 197041 | U12: 210024 | V12: 188198 | W12: 189662 | X12: 191834 | Y12: 186024 | Z12: 180244 | AA12: 174433 | AB12: 164370 | AC12: 165822 | AD12: 151425 | AE12: 152039 | AF12: 142507 | AG12: 141664 | AH12: 125666 | AI12: 128847 | AJ12: 122192 | AK12: 111690 | AL12: 115554 | AM12: 104160 | AN12: 102997 | AO12: 102131 | AP12: 96728 | AQ12: 94203 | AR12: 92093 | AS12: 88056 | AT12: 80198 | AU12: 77010 | AV12: 70719 | AW12: 68742 | AX12: 68947 | AY12: 68353 | AZ12: 62668 | BA12: 65572 | BB12: 63497 | BC12: 57676 | BD12: 56151 | BE12: 51515 | BF12: 52486 | BG12: 47036 | BH12: 44694 | BI12: 42562 | BJ12: =VLOOKUP(MID(A12,12,2),'State Codes'!$B$10:$D$60,3,0) -> 5 South Atlantic | BK12: =VLOOKUP(MID(A12,6,5),'Chart Controls'!$P$3:$Q$8,2,0) -> Electricity
A13: SEDS.ESRCB.HI.A | C13: Billion Btu | E13: EIA, U.S. Energy Information Administration | F13: value | G13: 9047 | H13: 9189 | I13: 9378 | J13: 9639 | K13: 9721 | L13: 9416 | M13: 9249 | N13: 8972 | O13: 8911 | P13: 9012 | Q13: 8816 | R13: 8901 | S13: 9346 | T13: 9993 | U13: 10200 | V13: 10425 | W13: 10527 | X13: 10921 | Y13: 10858 | Z13: 10796 | AA13: 10789 | AB13: 10330 | AC13: 9889 | AD13: 9562 | AE13: 9433 | AF13: 9175 | AG13: 9010 | AH13: 9103 | AI13: 9130 | AJ13: 8893 | AK13: 8724 | AL13: 8423 | AM13: 8320 | AN13: 8174 | AO13: 7929 | AP13: 7650 | AQ13: 7341 | AR13: 7072 | AS13: 6695 | AT13: 6411 | AU13: 6270 | AV13: 6327 | AW13: 6284 | AX13: 6565 | AY13: 6281 | AZ13: 6299 | BA13: 6070 | BB13: 6005 | BC13: 5925 | BD13: 5674 | BE13: 5646 | BF13: 5456 | BG13: 5155 | BH13: 4745 | BI13: 4384 | BJ13: =VLOOKUP(MID(A13,12,2),'State Codes'!$B$10:$D$60,3,0) -> 9 Pacific | BK13: =VLOOKUP(MID(A13,6,5),'Chart Controls'!$P$3:$Q$8,2,0) -> Electricity
... A307: SEDS.WDRCB.WY.A | C307: Billion Btu | E307: EIA, U.S. Energy Information Administration | F307: value | G307: 0 | H307: 1409 | I307: 1657 | J307: 1315 | K307: 1272 | L307: 4279 | M307: 4227 | N307: 4198 | O307: 3605 | P307: 4176 | Q307: 1294 | R307: 1279 | S307: 980 | T307: 1173 | U307: 1209 | V307: 1127 | W307: 2136 | X307: 1909 | Y307: 1727 | Z307: 1947 | AA307: 622 | AB307: 607 | AC307: 577 | AD307: 568 | AE307: 1034 | AF307: 960 | AG307: 936 | AH307: 1053 | AI307: 1001 | AJ307: 964 | AK307: 964 | AL307: 1016 | AM307: 1108 | AN307: 1056 | AO307: 1008 | AP307: 1046 | AQ307: 1035 | AR307: 969 | AS307: 2091 | AT307: 2295 | AU307: 2228 | AV307: 2181 | AW307: 2039 | AX307: 1964 | AY307: 1455 | AZ307: 2219 | BA307: 1754 | BB307: 1342 | BC307: 1170 | BD307: 1101 | BE307: 894 | BF307: 894 | BG307: 912 | BH307: 946 | BI307: 980 | BJ307: =VLOOKUP(MID(A307,12,2),'State Codes'!$B$10:$D$60,3,0) -> 8 Mountain | BK307: =VLOOKUP(MID(A307,6,5),'Chart Controls'!$P$3:$Q$8,2,0) -> Wood

Sheet SEDS_EXP_API
A1: 1date | B1: A | C1: 25569 | D1: 44197 | E1: Source | F1: date | G1: 45292 | H1: 44927 | I1: 44562 | J1: 44197 | K1: 43831 | L1: 43466 | M1: 43101 | N1: 42736 | O1: 42370 | P1: 42005 | Q1: 41640 | R1: 41275 | S1: 40909 | T1: 40544 | U1: 40179 | V1: 39814 | W1: 39448 | X1: 39083 | Y1: 38718 | Z1: 38353 | AA1: 37987 | AB1: 37622 | AC1: 37257 | AD1: 36892 | AE1: 36526 | AF1: 36161 | AG1: 35796 | AH1: 35431 | AI1: 35065 | AJ1: 34700 | AK1: 34335 | AL1: 33970 | AM1: 33604 | AN1: 33239 | AO1: 32874 | AP1: 32509 | AQ1: 32143 | AR1: 31778 | AS1: 31413 | AT1: 31048 | AU1: 30682 | AV1: 30317 | AW1: 29952 | AX1: 29587 | AY1: 29221 | AZ1: 28856 | BA1: 28491 | BB1: 28126 | BC1: 27760 | BD1: 27395 | BE1: 27030 | BF1: 26665 | BG1: 26299 | BH1: 25934 | BI1: 25569 | BJ1: Division | BK1: Fuel
A2: SEDS.ESRCV.AL.A | C2: Million dollars | E2: EIA, U.S. Energy Information Administration | F2: value | G2: 4993.1 | H2: 4593.8 | I2: 4690.8 | J2: 4092.4 | K2: 3939.9 | L2: 4061.2 | M2: 4027.6 | N2: 3786.7 | O2: 3843.4 | P2: 3731.8 | Q2: 3781.9 | R2: 3532.6 | S2: 3491.4 | T2: 3661.5 | U2: 3790.7 | V2: 3356 | W2: 3347.6 | X2: 3056.8 | Y2: 2824.7 | Z2: 2504 | AA2: 2295.2 | AB2: 2175 | AC2: 2138.4 | AD2: 1950.1 | AE2: 2027.8 | AF2: 1901.4 | AG2: 1896.8 | AH2: 1678.8 | AI2: 1700.4 | AJ2: 1630.9 | AK2: 1549.9 | AL2: 1544.2 | AM2: 1413.4 | AN2: 1424.7 | AO2: 1366.1 | AP2: 1307 | AQ2: 1277 | AR2: 1245.2 | AS2: 1180.4 | AT2: 1098.4 | AU2: 1179.7 | AV2: 1046.7 | AW2: 1001.7 | AX2: 877.8 | AY2: 811.2 | AZ2: 632.5 | BA2: 578.3 | BB2: 542.3 | BC2: 418.6 | BD2: 368.5 | BE2: 336.1 | BF2: 287.3 | BG2: 234.3 | BH2: 204.2 | BI2: 181.7 | BJ2: =VLOOKUP(MID(A2,12,2),'State Codes'!$B$10:$D$60,3,0) -> 6 East South Central | BK2: =VLOOKUP(MID(A2,6,5),'Chart Controls'!$P$11:$Q$16,2,0) -> Electricity
A3: SEDS.ESRCV.AZ.A | C3: Million dollars | E3: EIA, U.S. Energy Information Administration | F3: value | G3: 12055 | H3: 10932.2 | I3: 9989.6 | J3: 9311.8 | K3: 9502 | L3: 8634.2 | M3: 8850.4 | N3: 8518.6 | O3: 8188.8 | P3: 8046.6 | Q3: 7698 | R3: 7756 | S3: 7436.8 | T3: 7332.4 | U3: 7116.4 | V3: 7048.2 | W3: 6824.6 | X3: 6655.2 | Y3: 6083.4 | Z3: 5414.8 | AA3: 4893.2 | AB3: 4631.4 | AC3: 4369.4 | AD3: 4348.8 | AE3: 4192.2 | AF3: 3843.6 | AG3: 3749.8 | AH3: 3648 | AI3: 3533.2 | AJ3: 3279 | AK3: 3387 | AL3: 3222.8 | AM3: 3110.2 | AN3: 2860.6 | AO3: 2780.2 | AP3: 2698 | AQ3: 2578 | AR3: 2366.2 | AS3: 2171 | AT3: 2021 | AU3: 1779.2 | AV3: 1624 | AW3: 1467.8 | AX3: 1314.4 | AY3: 1202.4 | AZ3: 1049.4 | BA3: 853.8 | BB3: 753 | BC3: 613.6 | BD3: 568.6 | BE3: 450.4 | BF3: 356.6 | BG3: 291.4 | BH3: 232.8 | BI3: 206.6 | BJ3: =VLOOKUP(MID(A3,12,2),'State Codes'!$B$10:$D$60,3,0) -> 8 Mountain | BK3: =VLOOKUP(MID(A3,6,5),'Chart Controls'!$P$11:$Q$16,2,0) -> Electricity
A4: SEDS.ESRCV.AZ.A | C4: Million dollars | E4: EIA, U.S. Energy Information Administration | F4: value | G4: 12055 | H4: 10932.2 | I4: 9989.6 | J4: 9311.8 | K4: 9502 | L4: 8634.2 | M4: 8850.4 | N4: 8518.6 | O4: 8188.8 | P4: 8046.6 | Q4: 7698 | R4: 7756 | S4: 7436.8 | T4: 7332.4 | U4: 7116.4 | V4: 7048.2 | W4: 6824.6 | X4: 6655.2 | Y4: 6083.4 | Z4: 5414.8 | AA4: 4893.2 | AB4: 4631.4 | AC4: 4369.4 | AD4: 4348.8 | AE4: 4192.2 | AF4: 3843.6 | AG4: 3749.8 | AH4: 3648 | AI4: 3533.2 | AJ4: 3279 | AK4: 3387 | AL4: 3222.8 | AM4: 3110.2 | AN4: 2860.6 | AO4: 2780.2 | AP4: 2698 | AQ4: 2578 | AR4: 2366.2 | AS4: 2171 | AT4: 2021 | AU4: 1779.2 | AV4: 1624 | AW4: 1467.8 | AX4: 1314.4 | AY4: 1202.4 | AZ4: 1049.4 | BA4: 853.8 | BB4: 753 | BC4: 613.6 | BD4: 568.6 | BE4: 450.4 | BF4: 356.6 | BG4: 291.4 | BH4: 232.8 | BI4: 206.6 | BJ4: =VLOOKUP(MID(A4,12,2),'State Codes'!$B$10:$D$60,3,0) -> 8 Mountain | BK4: =VLOOKUP(MID(A4,6,5),'Chart Controls'!$P$11:$Q$16,2,0) -> Electricity
A5: SEDS.ESRCV.AR.A | C5: Million dollars | E5: EIA, U.S. Energy Information Administration | F5: value | G5: 2288.7 | H5: 2251.2 | I5: 2320.5 | J5: 2131.7 | K5: 1871.4 | L5: 1834.9 | M5: 1888.7 | N5: 1749.7 | O5: 1764.9 | P5: 1794.3 | Q5: 1753.3 | R5: 1746.5 | S5: 1664.7 | T5: 1693.8 | U5: 1702.9 | V5: 1552.4 | W5: 1612.8 | X5: 1520.5 | Y5: 1510.7 | Z5: 1370.9 | AA5: 1149.9 | AB5: 1129.8 | AC5: 1126.3 | AD5: 1165.4 | AE5: 1108.5 | AF5: 1042.9 | AG5: 1076.4 | AH5: 1013.1 | AI5: 1005.3 | AJ5: 991.4 | AK5: 939.9 | AL5: 972.8 | AM5: 864.6 | AN5: 891.6 | AO5: 851.7 | AP5: 774 | AQ5: 757 | AR5: 743.8 | AS5: 716.2 | AT5: 667.9 | AU5: 631.6 | AV5: 636.5 | AW5: 563.1 | AX5: 475.9 | AY5: 543.7 | AZ5: 389.7 | BA5: 395.1 | BB5: 358.1 | BC5: 283.3 | BD5: 247.4 | BE5: 175.6 | BF5: 147.3 | BG5: 132.5 | BH5: 111.8 | BI5: 100.5 | BJ5: =VLOOKUP(MID(A5,12,2),'State Codes'!$B$10:$D$60,3,0) -> 7 West South Central | BK5: =VLOOKUP(MID(A5,6,5),'Chart Controls'!$P$11:$Q$16,2,0) -> Electricity
A6: SEDS.ESRCV.CA.A | C6: Million dollars | E6: EIA, U.S. Energy Information Administration | F6: value | G6: 27443.7 | H6: 24439.8 | I6: 23136.7 | J6: 20604.4 | K6: 19413.3 | L6: 16763.8 | M6: 16782.2 | N6: 16500.8 | O6: 15359.8 | P6: 15187.8 | Q6: 14517.4 | R6: 14481.1 | S6: 13821.6 | T6: 13060.9 | U6: 12873.6 | V6: 13238.6 | W6: 12594.7 | X6: 12859.8 | Y6: 12875.5 | Z6: 10707.6 | AA6: 10168.5 | AB6: 10141.6 | AC6: 9758.5 | AD6: 9269 | AE6: 8629 | AF6: 8044.9 | AG6: 7964.1 | AH6: 8405.4 | AI6: 8088 | AJ6: 7983.3 | AK6: 7868.9 | AL6: 7613.1 | AM6: 7543.7 | AN6: 7120.4 | AO6: 6646.5 | AP6: 6080 | AQ6: 5518 | AR6: 4850.8 | AS6: 4565.8 | AT6: 4472.8 | AU6: 3998.6 | AV6: 3838.9 | AW6: 3976.6 | AX6: 3438.3 | AY6: 3049.5 | AZ6: 2343 | BA6: 2208.9 | BB6: 1971.3 | BC6: 1746.2 | BD6: 1612.8 | BE6: 1435 | BF6: 1146.2 | BG6: 1017.2 | BH6: 903.8 | BI6: 797.6 | BJ6: =VLOOKUP(MID(A6,12,2),'State Codes'!$B$10:$D$60,3,0) -> 9 Pacific | BK6: =VLOOKUP(MID(A6,6,5),'Chart Controls'!$P$11:$Q$16,2,0) -> Electricity
A7: SEDS.ESRCV.CO.A | C7: Million dollars | E7: EIA, U.S. Energy Information Administration | F7: value | G7: 3086.8 | H7: 2859.3 | I7: 2922.5 | J7: 2696.1 | K7: 2531.3 | L7: 2362.6 | M7: 2342.8 | N7: 2264.6 | O7: 2274 | P7: 2228 | Q7: 2203.8 | R7: 2210.3 | S7: 2087.9 | T7: 2059.2 | U7: 1997.9 | V7: 1740.5 | W7: 1794.4 | X7: 1631.7 | Y7: 1529 | Z7: 1489.5 | AA7: 1307 | AB7: 1280.5 | AC7: 1137.2 | AD7: 1080.2 | AE7: 1024.8 | AF7: 968.9 | AG7: 942.4 | AH7: 909.6 | AI7: 889.2 | AJ7: 839 | AK7: 804.6 | AL7: 771.5 | AM7: 735.8 | AN7: 713.8 | AO7: 687.1 | AP7: 673 | AQ7: 662 | AR7: 629.5 | AS7: 623 | AT7: 613.3 | AU7: 584.4 | AV7: 640 | AW7: 606.6 | AX7: 498.7 | AY7: 342.5 | AZ7: 272.2 | BA7: 229.7 | BB7: 202.9 | BC7: 188.2 | BD7: 174.4 | BE7: 162.4 | BF7: 143.3 | BG7: 127.9 | BH7: 111.7 | BI7: 101.8 | BJ7: =VLOOKUP(MID(A7,12,2),'State Codes'!$B$10:$D$60,3,0) -> 8 Mountain | BK7: =VLOOKUP(MID(A7,6,5),'Chart Controls'!$P$11:$Q$16,2,0) -> Electricity
A8: SEDS.ESRCV.CT.A | C8: Million dollars | E8: EIA, U.S. Energy Information Administration | F8: value | G8: 3720.2 | H8: 3751.2 | I8: 3246.4 | J8: 2868.4 | K8: 2948.8 | L8: 2732.7 | M8: 2769.1 | N8: 2512 | O8: 2536.8 | P8: 2699.3 | Q8: 2523.3 | R8: 2305.8 | S8: 2212.6 | T8: 2339 | U8: 2514.5 | V8: 2557.4 | W8: 2487.9 | X8: 2555.6 | Y8: 2185.1 | Z8: 1882.8 | AA8: 1536.5 | AB8: 1491.1 | AC8: 1366.6 | AD8: 1305.8 | AE8: 1264.5 | AF8: 1331.6 | AG8: 1306.3 | AH8: 1317.5 | AI8: 1318.6 | AJ8: 1286.2 | AK8: 1250.3 | AL8: 1207.4 | AM8: 1162.3 | AN8: 1097.4 | AO8: 1038.5 | AP8: 1005 | AQ8: 950 | AR8: 884.9 | AS8: 842.6 | AT8: 861.9 | AU8: 859.8 | AV8: 844.3 | AW8: 810.6 | AX8: 745.4 | AY8: 568.4 | AZ8: 472 | BA8: 403.5 | BB8: 391.2 | BC8: 377.6 | BD8: 368.2 | BE8: 336.1 | BF8: 246 | BG8: 214.7 | BH8: 181.9 | BI8: 157.3 | BJ8: =VLOOKUP(MID(A8,12,2),'State Codes'!$B$10:$D$60,3,0) -> 1 New England | BK8: =VLOOKUP(MID(A8,6,5),'Chart Controls'!$P$11:$Q$16,2,0) -> Electricity
A9: SEDS.ESRCV.DE.A | C9: Million dollars | E9: EIA, U.S. Energy Information Administration | F9: value | G9: 857.3 | H9: 775.8 | I9: 714.3 | J9: 647.1 | K9: 627 | L9: 628 | M9: 635.4 | N9: 622.4 | O9: 639.1 | P9: 650.8 | Q9: 617.4 | R9: 592 | S9: 614 | T9: 634.6 | U9: 657.1 | V9: 610 | W9: 617 | X9: 588.4 | Y9: 504.6 | Z9: 414.1 | AA9: 377.7 | AB9: 360 | AC9: 349.8 | AD9: 321.4 | AE9: 305.3 | AF9: 323.8 | AG9: 304.8 | AH9: 300.4 | AI9: 293.4 | AJ9: 287.8 | AK9: 276.8 | AL9: 274.4 | AM9: 241.3 | AN9: 243.3 | AO9: 222.5 | AP9: 214 | AQ9: 213 | AR9: 192.4 | AS9: 180.1 | AT9: 179.1 | AU9: 176.6 | AV9: 149 | AW9: 142.9 | AX9: 123.2 | AY9: 138.6 | AZ9: 112 | BA9: 103.3 | BB9: 99.3 | BC9: 83.7 | BD9: 77.9 | BE9: 61.6 | BF9: 48.2 | BG9: 41.7 | BH9: 34.5 | BI9: 30 | BJ9: =VLOOKUP(MID(A9,12,2),'State Codes'!$B$10:$D$60,3,0) -> 5 South Atlantic | BK9: =VLOOKUP(MID(A9,6,5),'Chart Controls'!$P$11:$Q$16,2,0) -> Electricity
A10: SEDS.ESRCV.DC.A | C10: Million dollars | E10: EIA, U.S. Energy Information Administration | F10: value | G10: 433.1 | H10: 390 | I10: 357.3 | J10: 330.9 | K10: 309.8 | L10: 330.7 | M10: 332.9 | N10: 309.8 | O10: 307.5 | P10: 324.3 | Q10: 264 | R10: 255.6 | S10: 245.9 | T10: 276.2 | U10: 297.5 | V10: 260.8 | W10: 244.9 | X10: 220.2 | Y10: 180 | Z10: 176.4 | AA10: 146.8 | AB10: 137.6 | AC10: 142.8 | AD10: 132.3 | AE10: 130.4 | AF10: 131.4 | AG10: 127.7 | AH10: 122.3 | AI10: 125.4 | AJ10: 122.6 | AK10: 117.3 | AL10: 117.3 | AM10: 98.4 | AN10: 104 | AO10: 90.3 | AP10: 88 | AQ10: 92 | AR10: 92.1 | AS10: 90.7 | AT10: 85.4 | AU10: 78.9 | AV10: 80.3 | AW10: 71.2 | AX10: 71.9 | AY10: 64.1 | AZ10: 51.4 | BA10: 49.8 | BB10: 43.5 | BC10: 40.7 | BD10: 39.2 | BE10: 34.7 | BF10: 27.7 | BG10: 23.7 | BH10: 22.6 | BI10: 19.9 | BJ10: =VLOOKUP(MID(A10,12,2),'State Codes'!$B$10:$D$60,3,0) -> 5 South Atlantic | BK10: =VLOOKUP(MID(A10,6,5),'Chart Controls'!$P$11:$Q$16,2,0) -> Electricity
A11: SEDS.ESRCV.FL.A | C11: Million dollars | E11: EIA, U.S. Energy Information Administration | F11: value | G11: 19561.2 | H11: 20652 | I11: 18664.4 | J11: 15518.2 | K11: 15021.4 | L11: 14882.8 | M11: 14485.3 | N11: 14097.7 | O11: 13545.3 | P11: 14216.6 | Q11: 13854.5 | R11: 12770.1 | S11: 12806.8 | T11: 13389 | U11: 13982.2 | V11: 14302.6 | W11: 13278.7 | X11: 13222.6 | Y11: 13263.6 | Z11: 11140.7 | AA11: 10085.9 | AB11: 9636.1 | AC11: 8823 | AD11: 8712.9 | AE11: 7696.3 | AF11: 7253.3 | AG11: 7557.1 | AH11: 7097.3 | AI11: 7059.9 | AJ11: 6711.3 | AK11: 6270.5 | AL11: 6137 | AM11: 5671.2 | AN11: 5759.4 | AO11: 5527.2 | AP11: 5273 | AQ11: 5001 | AR11: 4683.9 | AS11: 4596.6 | AT11: 4566.8 | AU11: 4086.5 | AV11: 3677.8 | AW11: 3368.3 | AX11: 3332.2 | AY11: 2555 | AZ11: 2034.3 | BA11: 1816.2 | BB11: 1607.5 | BC11: 1422.6 | BD11: 1295.3 | BE11: 1069.4 | BF11: 835.6 | BG11: 678.9 | BH11: 581.5 | BI11: 512.1 | BJ11: =VLOOKUP(MID(A11,12,2),'State Codes'!$B$10:$D$60,3,0) -> 5 South Atlantic | BK11: =VLOOKUP(MID(A11,6,5),'Chart Controls'!$P$11:$Q$16,2,0) -> Electricity
A12: SEDS.ESRCV.GA.A | C12: Million dollars | E12: EIA, U.S. Energy Information Administration | F12: value | G12: 8740 | H12: 7996.7 | I12: 8437.9 | J12: 7339.6 | K12: 6995.9 | L12: 6979.1 | M12: 6847.3 | N12: 6516.8 | O12: 6659.2 | P12: 6511.2 | Q12: 6659.5 | R12: 6135.8 | S12: 5996.3 | T12: 6383.6 | U12: 6198.4 | V12: 5587.9 | W12: 5517.5 | X12: 5113.6 | Y12: 4857.7 | Z12: 4565.5 | AA12: 4016.4 | AB12: 3710.7 | AC12: 3705.9 | AD12: 3427.7 | AE12: 3386.3 | AF12: 3158.8 | AG12: 3185.2 | AH12: 2851.7 | AI12: 2891.7 | AJ12: 2811.1 | AK12: 2527 | AL12: 2639.6 | AM12: 2360.6 | AN12: 2264 | AO12: 2233.3 | AP12: 2049 | AQ12: 1939 | AR12: 1823.2 | AS12: 1732.3 | AT12: 1516.4 | AU12: 1434.2 | AV12: 1298.6 | AW12: 1227.7 | AX12: 1041.2 | AY12: 946.6 | AZ12: 790.2 | BA12: 777.2 | BB12: 684.1 | BC12: 534.2 | BD12: 505.9 | BE12: 380.8 | BF12: 324.4 | BG12: 277.2 | BH12: 244.4 | BI12: 220.7 | BJ12: =VLOOKUP(MID(A12,12,2),'State Codes'!$B$10:$D$60,3,0) -> 5 South Atlantic | BK12: =VLOOKUP(MID(A12,6,5),'Chart Controls'!$P$11:$Q$16,2,0) -> Electricity
A13: SEDS.ESRCV.HI.A | C13: Million dollars | E13: EIA, U.S. Energy Information Administration | F13: value | G13: 1136.6 | H13: 1141.7 | I13: 1182.6 | J13: 946.2 | K13: 862.8 | L13: 884.8 | M13: 880.2 | N13: 775.9 | O13: 717.4 | P13: 781.9 | Q13: 957.1 | R13: 964.9 | S13: 1022.9 | T13: 1015.7 | U13: 840.1 | V13: 739.4 | W13: 1002.6 | X13: 772.1 | Y13: 743 | Z13: 655 | AA13: 571.2 | AB13: 506.6 | AC13: 453.2 | AD13: 457.8 | AE13: 453.6 | AF13: 384.4 | AG13: 364.9 | AH13: 394.9 | AI13: 381.5 | AJ13: 347.3 | AK13: 318.4 | AL13: 303.2 | AM13: 265.8 | AN13: 252 | AO13: 238.4 | AP13: 208 | AQ13: 190 | AR13: 195.4 | AS13: 181.9 | AT13: 213.4 | AU13: 216.7 | AV13: 220.7 | AW13: 242.6 | AX13: 233.5 | AY13: 148.5 | AZ13: 124.6 | BA13: 111.2 | BB13: 98.5 | BC13: 89.2 | BD13: 82.8 | BE13: 62.6 | BF13: 52.3 | BG13: 45.2 | BH13: 41 | BI13: 36 | BJ13: =VLOOKUP(MID(A13,12,2),'State Codes'!$B$10:$D$60,3,0) -> 9 Pacific | BK13: =VLOOKUP(MID(A13,6,5),'Chart Controls'!$P$11:$Q$16,2,0) -> Electricity
... A307: SEDS.WDRCV.WY.A | C307: Million dollars | E307: EIA, U.S. Energy Information Administration | F307: value | G307: 0 | H307: 9.5 | I307: 12.3 | J307: 6.3 | K307: 5.1 | L307: 20.6 | M307: 21.2 | N307: 19 | O307: 14.6 | P307: 19.8 | Q307: 8.9 | R307: 9 | S307: 7.1 | T307: 7.6 | U307: 6.5 | V307: 5.1 | W307: 13 | X307: 9.4 | Y307: 7.7 | Z307: 7.5 | AA307: 1.8 | AB307: 1.6 | AC307: 1.2 | AD307: 1.3 | AE307: 2.6 | AF307: 1.6 | AG307: 1.5 | AH307: 2 | AI307: 1.9 | AJ307: 1.6 | AK307: 1.6 | AL307: 1.7 | AM307: 1.9 | AN307: 2 | AO307: 2 | AP307: 0.4 | AQ307: 0.4 | AR307: 0.4 | AS307: 0.8 | AT307: 1.1 | AU307: 1.1 | AV307: 1.1 | AW307: 1 | AX307: 1 | AY307: 0.6 | AZ307: 0.7 | BA307: 0.4 | BB307: 0.3 | BC307: 0.2 | BD307: 0.2 | BE307: 0.1 | BF307: 0.1 | BG307: 0.1 | BH307: 0.1 | BI307: 0.1 | BJ307: =VLOOKUP(MID(A307,12,2),'State Codes'!$B$10:$D$60,3,0) -> 8 Mountain | BK307: =VLOOKUP(MID(A307,6,5),'Chart Controls'!$P$11:$Q$16,2,0) -> Wood

Sheet Deflators
D2: 1970 | E2: 1971 | F2: 1972 | G2: 1973 | H2: 1974 | I2: 1975 | J2: 1976 | K2: 1977 | L2: 1978 | M2: 1979 | N2: 1980 | O2: 1981 | P2: 1982 | Q2: 1983 | R2: 1984 | S2: 1985 | T2: 1986 | U2: 1987 | V2: 1988 | W2: 1989 | X2: 1990 | Y2: 1991 | Z2: 1992 | AA2: 1993 | AB2: 1994 | AC2: 1995 | AD2: 1996 | AE2: 1997 | AF2: 1998 | AG2: 1999 | AH2: 2000 | AI2: 2001 | AJ2: 2002 | AK2: 2003 | AL2: 2004 | AM2: 2005 | AN2: 2006 | AO2: 2007 | AP2: 2008 | AQ2: 2009 | AR2: 2010 | AS2: 2011 | AT2: 2012 | AU2: 2013 | AV2: 2014 | AW2: 2015 | AX2: 2016 | AY2: 2017 | AZ2: 2018 | BA2: 2019 | BB2: 2020 | BC2: 2021 | BD2: 2022 | BE2: 2023 | BF2: 2024 | BG2: << Insert
B3: Chained Price Deflator | C3: 2012=1 | D3: =VLOOKUP(D2,$B$13:$E$66,4,0) -> 0.20188473 | E3: =VLOOKUP(E2,$B$13:$E$66,4,0) -> 0.2121317 | F3: =VLOOKUP(F2,$B$13:$E$66,4,0) -> 0.22129758 | G3: =VLOOKUP(G2,$B$13:$E$66,4,0) -> 0.23342722 | H3: =VLOOKUP(H2,$B$13:$E$66,4,0) -> 0.25442092 | I3: =VLOOKUP(I2,$B$13:$E$66,4,0) -> 0.27799502 | J3: =VLOOKUP(J2,$B$13:$E$66,4,0) -> 0.29329618 | K3: =VLOOKUP(K2,$B$13:$E$66,4,0) -> 0.31151613 | ... BE3: =VLOOKUP(BE2,$B$13:$E$66,4,0) -> 1.2238984 | BF3: =VLOOKUP(BF2,$B$13:$E$67,4,0) -> 1.2542811 | BG3: <<< Insert
B4: ='Year Selections'!C5 -> 1987 | C4: rebase | D4: =D3/HLOOKUP($B$4,$D$2:$BG$3,2,0) -> 0.37995595 | E4: =E3/HLOOKUP($B$4,$D$2:$BG$3,2,0) -> 0.39924119 | F4: =F3/HLOOKUP($B$4,$D$2:$BG$3,2,0) -> 0.41649178 | G4: =G3/HLOOKUP($B$4,$D$2:$BG$3,2,0) -> 0.4393203 | H4: =H3/HLOOKUP($B$4,$D$2:$BG$3,2,0) -> 0.47883136 | I4: =I3/HLOOKUP($B$4,$D$2:$BG$3,2,0) -> 0.52319885 | J4: =J3/HLOOKUP($B$4,$D$2:$BG$3,2,0) -> 0.55199631 | K4: =K3/HLOOKUP($B$4,$D$2:$BG$3,2,0) -> 0.58628706 | ... BF4: =BF3/HLOOKUP($B$4,$D$2:$BG$3,2,0) -> 2.3606122 | BG4: <<< Insert
B5: 2022 | C5: rebase | D5: =D3/HLOOKUP($B$5,$D$2:$BG$3,2,0) -> 0.17105568 | E5: =E3/HLOOKUP($B$5,$D$2:$BG$3,2,0) -> 0.17973786 | F5: =F3/HLOOKUP($B$5,$D$2:$BG$3,2,0) -> 0.18750406 | G5: =G3/HLOOKUP($B$5,$D$2:$BG$3,2,0) -> 0.19778143 | H5: =H3/HLOOKUP($B$5,$D$2:$BG$3,2,0) -> 0.21556926 | I5: =I3/HLOOKUP($B$5,$D$2:$BG$3,2,0) -> 0.23554344 | J5: =J3/HLOOKUP($B$5,$D$2:$BG$3,2,0) -> 0.24850802 | K5: =K3/HLOOKUP($B$5,$D$2:$BG$3,2,0) -> 0.26394567 | ... BF5: =BF3/HLOOKUP($B$5,$D$2:$BG$3,2,0) -> 1.0627446 | BG5: <<< Insert
B8: Current-Dollar and "Real" Gross Domestic Product
B9: (Seasonally adjusted annual rates)
B10: Data updated 2026-02-26
C12: GDP in billions of current dollars | D12: GDP in billions of chained 2012 dollars | E12: Calculated Index
B13: 1970 | C13: 1073.3 | D13: 5316.4 | E13: =C13/D13 -> 0.20188473 | G13: Direct link to spreadsheet data
B14: 1971 | C14: 1164.9 | D14: 5491.4 | E14: =C14/D14 -> 0.2121317 | G14: https://apps.bea.gov/national/xls/gdplev.xlsx
B15: 1972 | C15: 1279.1 | D15: 5780 | E15: =C15/D15 -> 0.22129758
B16: 1973 | C16: 1425.4 | D16: 6106.4 | E16: =C16/D16 -> 0.23342722 | G16: Interactive data table browser
B17: 1974 | C17: 1545.2 | D17: 6073.4 | E17: =C17/D17 -> 0.25442092 | G17: https://apps.bea.gov/iTable/iTable.cfm?reqid=19&step=2#reqid=19&step=2&isuri=1&1921=survey
B18: 1975 | C18: 1684.9 | D18: 6060.9 | E18: =C18/D18 -> 0.27799502 | G18: (Select annual data and adjust date range for 1970 through current full year)
B19: 1976 | C19: 1873.4 | D19: 6387.4 | E19: =C19/D19 -> 0.29329618
B20: 1977 | C20: 2081.8 | D20: 6682.8 | E20: =C20/D20 -> 0.31151613 | G20: General BEA Link
B21: 1978 | C21: 2351.6 | D21: 7052.7 | E21: =C21/D21 -> 0.33343259 | G21: https://www.bea.gov/data/gdp/gross-domestic-product#gdp
B22: 1979 | C22: 2627.3 | D22: 7276 | E22: =C22/D22 -> 0.36109126
B23: 1980 | C23: 2857.3 | D23: 7257.3 | E23: =C23/D23 -> 0.39371392
B24: 1981 | C24: 3207 | D24: 7441.5 | E24: =C24/D24 -> 0.4309615
B25: 1982 | C25: 3343.8 | D25: 7307.3 | E25: =C25/D25 -> 0.4575972
B26: 1983 | C26: 3634 | D26: 7642.3 | E26: =C26/D26 -> 0.4755113
B27: 1984 | C27: 4037.6 | D27: 8195.3 | E27: =C27/D27 -> 0.49267263
B28: 1985 | C28: 4339 | D28: 8537 | E28: =C28/D28 -> 0.50825817
B29: 1986 | C29: 4579.6 | D29: 8832.6 | E29: =C29/D29 -> 0.51848833
B30: 1987 | C30: 4855.2 | D30: 9137.7 | E30: =C30/D30 -> 0.53133721
B31: 1988 | C31: 5236.4 | D31: 9519.4 | E31: =C31/D31 -> 0.55007669
B32: 1989 | C32: 5641.6 | D32: 9869 | E32: =C32/D32 -> 0.5716486
B33: 1990 | C33: 5963.1 | D33: 10055.1 | E33: =C33/D33 -> 0.59304234
... B67: 2024 | C67: 29298 | D67: 23358.4 | E67: =C67/D67 -> 1.2542811
B68: ^ Insert line above ^

Sheet RECS Data
B2: RECS Housing Stocks (millions of housing units)
B3: Census division | C3: Type | D3: 1990 | E3: 1991 | F3: 1992 | G3: 1993 | H3: 1994 | I3: 1995 | J3: 1996 | K3: 1997 | L3: 1998 | M3: 1999 | N3: 2000 | O3: 2001 | P3: 2002 | Q3: 2003 | R3: 2004 | S3: 2005 | T3: 2006 | U3: 2007 | V3: 2008 | W3: 2009 | X3: 2010 | Y3: 2011 | Z3: 2012 | AA3: 2013 | AB3: 2014 | AC3: 2015 | AD3: 2016 | AE3: 2017 | AF3: 2018 | AG3: 2019 | AH3: 2020
B4: 1 New England | C4: Single-family | D4: 2.532478 | G4: 3.094829 | K4: 3.759905 | O4: 3.491245 | S4: 3.3929437 | W4: 3.3745972 | AC4: 3.496102 | AH4: 3.637502
B5: 1 New England | C5: Multifamily | D5: 1.859536 | G5: 1.747055 | K5: 1.43496 | O5: 1.750832 | S5: 1.8999805 | W5: 2.052063 | AC5: 2.004141 | AH5: 2.098565
B6: 1 New England | C6: Mobile | D6: 0.151708 | G6: 0.225381 | K6: 0.114801 | O6: 0.16492 | S6: 0.17307178 | W6: 0.084436812 | AC6: 0.128601 | AH6: 0.140099
B7: 2 Middle Atlantic | C7: Single-family | D7: 9.334444 | G7: 8.813412 | K7: 9.990266 | O7: 8.517861 | S7: 10.077231 | W7: 9.2872669 | AC7: 9.174731 | AH7: 9.541561
B8: 2 Middle Atlantic | C8: Multifamily | D8: 4.968451 | G8: 5.279802 | K8: 4.063826 | O8: 5.841068 | S8: 4.7846857 | W8: 5.536739 | AC8: 5.841457 | AH8: 6.144683
B9: 2 Middle Atlantic | C9: Mobile | D9: 0.376404 | G9: 0.317255 | K9: 0.370168 | O9: 0.487669 | S9: 0.25461008 | W9: 0.43534414 | AC9: 0.361506 | AH9: 0.357259
B10: 3 East North Central | C10: Single-family | D10: 11.250133 | G10: 11.396562 | K10: 12.541488 | O10: 12.434352 | S10: 14.091216 | W10: 13.077414 | AC10: 13.175099 | AH10: 13.498851
B11: 3 East North Central | C11: Multifamily | D11: 4.137222 | G11: 4.009539 | K11: 3.616338 | O11: 3.823487 | S11: 3.2339288 | W11: 4.2171988 | AC11: 4.289665 | AH11: 4.422986
B12: 3 East North Central | C12: Mobile | D12: 1.224017 | G12: 0.945403 | K12: 0.748928 | O12: 0.833176 | S12: 0.42427086 | W12: 0.5588015 | AC12: 0.629627 | AH12: 0.625075
B13: 4 West North Central | C13: Single-family | D13: 4.765415 | G13: 5.175494 | K13: 5.905676 | O13: 5.847681 | S13: 6.107582 | W13: 6.1533861 | AC13: 6.263921 | AH13: 6.417005
B14: 4 West North Central | C14: Multifamily | D14: 1.307091 | G14: 1.304775 | K14: 0.893549 | O14: 1.165884 | S14: 1.4062141 | W14: 1.4069031 | AC14: 1.662715 | AH14: 1.730073
B15: 4 West North Central | C15: Mobile | D15: 0.385088 | G15: 0.468787 | K15: 0.353749 | O15: 0.386829 | S15: 0.34075891 | W15: 0.50381682 | AC15: 0.350708 | AH15: 0.348737
... B30: 9 Pacific | C30: Mobile | D30: 0.705987 | G30: 0.355646 | K30: 1.080339 | O30: 0.921178 | S30: 1.030541 | W30: 0.77837723 | AC30: 0.783483 | AH30: 0.802791
D31: =SUM(D4:D30) -> 93.990964 | G31: =SUM(G4:G30) -> 96.631492 | K31: =SUM(K4:K30) -> 101.48117 | O31: =SUM(O4:O30) -> 106.98927 | S31: =SUM(S4:S30) -> 111.09062 | W31: =SUM(W4:W30) -> 113.61623 | AC31: =SUM(AC4:AC30) -> 118.20825 | AH31: =SUM(AH4:AH30) -> 123.52903
B33: RECS Average Heated Floorspace (square feet)
B34: Census division | C34: Type | D34: 1990 | E34: 1991 | F34: 1992 | G34: 1993 | H34: 1994 | I34: 1995 | J34: 1996 | K34: 1997 | L34: 1998 | M34: 1999 | N34: 2000 | O34: 2001 | P34: 2002 | Q34: 2003 | R34: 2004 | S34: 2005 | T34: 2006 | U34: 2007 | V34: 2008 | W34: 2009 | X34: 2010 | Y34: 2011 | Z34: 2012 | AA34: 2013 | AB34: 2014 | AC34: 2015 | AD34: 2016 | AE34: 2017 | AF34: 2018 | AG34: 2019 | AH34: 2020
B35: 1 New England | C35: Single-family | D35: 2209.9879 | G35: 2171.3951 | K35: 2094.1545 | O35: 2441.2267 | S35: 2138.1395 | W35: 2151.1571 | AC35: 2392 | AH35: 2061.3676
B36: 1 New England | C36: Multifamily | D36: 998.27404 | G36: 1080.0035 | K36: 908.12966 | O36: 1179.1551 | S36: 929.30882 | W36: 936.9078 | AC36: 968 | AH36: 958.57094
B37: 1 New England | C37: Mobile | D37: 968.09094 | G37: 824.60075 | K37: 988.80727 | O37: 976.94177 | S37: 940.41324 | W37: 906.05529 | AC37: 1321 | AH37: 1150.1412
B38: 2 Middle Atlantic | C38: Single-family | D38: 2281.3003 | G38: 2251.8973 | K38: 2136.0976 | O38: 2358.7806 | S38: 2058.8974 | W38: 2149.6578 | AC38: 2322 | AH38: 2048.9941
B39: 2 Middle Atlantic | C39: Multifamily | D39: 1072.1588 | G39: 980.84618 | K39: 885.61287 | O39: 1084.2658 | S39: 860.60094 | W39: 882.83719 | AC39: 934 | AH39: 896.87782
B40: 2 Middle Atlantic | C40: Mobile | D40: 890.47845 | G40: 971.72374 | K40: 958.49685 | O40: 1046.5068 | S40: 755.03388 | W40: 979.82906 | AC40: 1067 | AH40: 1020.0458
B41: 3 East North Central | C41: Single-family | D41: 2140.8307 | G41: 2302.9527 | K41: 2231.1451 | O41: 2344.1379 | S41: 2175.0332 | W41: 2230.4446 | AC41: 2459 | AH41: 2178.6513
B42: 3 East North Central | C42: Multifamily | D42: 1023.6739 | G42: 955.29433 | K42: 889.05379 | O42: 1035.5657 | S42: 985.22573 | W42: 868.73303 | AC42: 933 | AH42: 958.22436
B43: 3 East North Central | C43: Mobile | D43: 921.36663 | G43: 967.61718 | K43: 849.30134 | O43: 932.89868 | S43: 838.88032 | W43: 955.151 | AC43: 1120 | AH43: 1097.8957
B44: 4 West North Central | C44: Single-family | D44: 2030.9779 | G44: 2160.7903 | K44: 2227.6 | O44: 2282.7025 | S44: 2245.9933 | W44: 2287.4745 | AC44: 2377 | AH44: 2194.4452
B45: 4 West North Central | C45: Multifamily | D45: 960.04673 | G45: 955.12863 | K45: 866.38677 | O45: 1058.167 | S45: 756.32322 | W45: 820.96272 | AC45: 884 | AH45: 895.01704
B46: 4 West North Central | C46: Mobile | D46: 988.65464 | G46: 925.69594 | K46: 958.37609 | O46: 1017.0415 | S46: 1113.2387 | W46: 1195.748 | AC46: 1130 | AH46: 1247.9348
... B62: U.S. Total | C62: All | D62: 1569.1964 | G62: 1630.2711 | K62: 1663.4508 | O62: 1691.9242 | S62: 1618.4589 | W62: 1644.0347 | AC62: 1754.3197 | AH62: 1613.8643
B64: RECS Total Floorspace (millions of square feet)
B65: Census division | C65: Type | D65: 1990 | E65: 1991 | F65: 1992 | G65: 1993 | H65: 1994 | I65: 1995 | J65: 1996 | K65: 1997 | L65: 1998 | M65: 1999 | N65: 2000 | O65: 2001 | P65: 2002 | Q65: 2003 | R65: 2004 | S65: 2005 | T65: 2006 | U65: 2007 | V65: 2008 | W65: 2009 | X65: 2010 | Y65: 2011 | Z65: 2012 | AA65: 2013 | AB65: 2014 | AC65: 2015 | AD65: 2016 | AE65: 2017 | AF65: 2018 | AG65: 2019 | AH65: 2020
B66: 1 New England | C66: Single-family | D66: =IF((D35*D4)=0,#N/A,D35*D4) -> 5596.7457 | G66: =IF((G35*G4)=0,#N/A,G35*G4) -> 6720.0967 | K66: =IF((K35*K4)=0,#N/A,K35*K4) -> 7873.822 | O66: =IF((O35*O4)=0,#N/A,O35*O4) -> 8522.9206 | S66: =IF((S35*S4)=0,#N/A,S35*S4) -> 7254.587 | W66: =IF((W35*W4)=0,#N/A,W35*W4) -> 7259.2886 | AC66: =IF((AC35*AC4)=0,#N/A,AC35*AC4) -> 8362.676 | AH66: =IF((AH35*AH4)=0,#N/A,AH35*AH4) -> 7498.2288
B67: 1 New England | C67: Multifamily | D67: =IF((D36*D5)=0,#N/A,D36*D5) -> 1856.3265 | G67: =IF((G36*G5)=0,#N/A,G36*G5) -> 1886.8256 | K67: =IF((K36*K5)=0,#N/A,K36*K5) -> 1303.1297 | O67: =IF((O36*O5)=0,#N/A,O36*O5) -> 2064.5025 | S67: =IF((S36*S5)=0,#N/A,S36*S5) -> 1765.6686 | W67: =IF((W36*W5)=0,#N/A,W36*W5) -> 1922.5938 | AC67: =IF((AC36*AC5)=0,#N/A,AC36*AC5) -> 1940.0085 | AH67: =IF((AH36*AH5)=0,#N/A,AH36*AH5) -> 2011.6234
B68: 1 New England | C68: Mobile | D68: =IF((D37*D6)=0,#N/A,D37*D6) -> 146.86714 | G68: =IF((G37*G6)=0,#N/A,G37*G6) -> 185.84934 | K68: =IF((K37*K6)=0,#N/A,K37*K6) -> 113.51606 | O68: =IF((O37*O6)=0,#N/A,O37*O6) -> 161.11724 | S68: =IF((S37*S6)=0,#N/A,S37*S6) -> 162.75899 | W68: =IF((W37*W6)=0,#N/A,W37*W6) -> 76.50442 | AC68: =IF((AC37*AC6)=0,#N/A,AC37*AC6) -> 169.88192 | AH68: =IF((AH37*AH6)=0,#N/A,AH37*AH6) -> 161.13363
B69: 2 Middle Atlantic | C69: Single-family | D69: =IF((D38*D7)=0,#N/A,D38*D7) -> 21294.67 | G69: =IF((G38*G7)=0,#N/A,G38*G7) -> 19846.899 | K69: =IF((K38*K7)=0,#N/A,K38*K7) -> 21340.183 | O69: =IF((O38*O7)=0,#N/A,O38*O7) -> 20091.765 | S69: =IF((S38*S7)=0,#N/A,S38*S7) -> 20747.985 | W69: =IF((W38*W7)=0,#N/A,W38*W7) -> 19964.445 | AC69: =IF((AC38*AC7)=0,#N/A,AC38*AC7) -> 21303.725 | AH69: =IF((AH38*AH7)=0,#N/A,AH38*AH7) -> 19550.603
B70: 2 Middle Atlantic | C70: Multifamily | D70: =IF((D39*D8)=0,#N/A,D39*D8) -> 5326.9685 | G70: =IF((G39*G8)=0,#N/A,G39*G8) -> 5178.6736 | K70: =IF((K39*K8)=0,#N/A,K39*K8) -> 3598.9766 | O70: =IF((O39*O8)=0,#N/A,O39*O8) -> 6333.2701 | S70: =IF((S39*S8)=0,#N/A,S39*S8) -> 4117.705 | W70: =IF((W39*W8)=0,#N/A,W39*W8) -> 4888.0391 | AC70: =IF((AC39*AC8)=0,#N/A,AC39*AC8) -> 5455.9208 | AH70: =IF((AH39*AH8)=0,#N/A,AH39*AH8) -> 5511.0299
B71: 2 Middle Atlantic | C71: Mobile | D71: =IF((D40*D9)=0,#N/A,D40*D9) -> 335.17965 | G71: =IF((G40*G9)=0,#N/A,G40*G9) -> 308.28422 | K71: =IF((K40*K9)=0,#N/A,K40*K9) -> 354.80486 | O71: =IF((O40*O9)=0,#N/A,O40*O9) -> 510.34894 | S71: =IF((S40*S9)=0,#N/A,S40*S9) -> 192.23924 | W71: =IF((W40*W9)=0,#N/A,W40*W9) -> 426.56284 | AC71: =IF((AC40*AC9)=0,#N/A,AC40*AC9) -> 385.7269 | AH71: =IF((AH40*AH9)=0,#N/A,AH40*AH9) -> 364.42056
B72: 3 East North Central | C72: Single-family | D72: =IF((D41*D10)=0,#N/A,D41*D10) -> 24084.63 | G72: =IF((G41*G10)=0,#N/A,G41*G10) -> 26245.744 | K72: =IF((K41*K10)=0,#N/A,K41*K10) -> 27981.879 | O72: =IF((O41*O10)=0,#N/A,O41*O10) -> 29147.836 | S72: =IF((S41*S10)=0,#N/A,S41*S10) -> 30648.864 | W72: =IF((W41*W10)=0,#N/A,W41*W10) -> 29168.447 | AC72: =IF((AC41*AC10)=0,#N/A,AC41*AC10) -> 32397.568 | AH72: =IF((AH41*AH10)=0,#N/A,AH41*AH10) -> 29409.289
B73: 3 East North Central | C73: Multifamily | D73: =IF((D42*D11)=0,#N/A,D42*D11) -> 4235.1663 | G73: =IF((G42*G11)=0,#N/A,G42*G11) -> 3830.2899 | K73: =IF((K42*K11)=0,#N/A,K42*K11) -> 3215.119 | O73: =IF((O42*O11)=0,#N/A,O42*O11) -> 3959.4721 | S73: =IF((S42*S11)=0,#N/A,S42*S11) -> 3186.1499 | W73: =IF((W42*W11)=0,#N/A,W42*W11) -> 3663.6199 | AC73: =IF((AC42*AC11)=0,#N/A,AC42*AC11) -> 4002.2574 | AH73: =IF((AH42*AH11)=0,#N/A,AH42*AH11) -> 4238.2129
B74: 3 East North Central | C74: Mobile | D74: =IF((D43*D12)=0,#N/A,D43*D12) -> 1127.7684 | G74: =IF((G43*G12)=0,#N/A,G43*G12) -> 914.78818 | K74: =IF((K43*K12)=0,#N/A,K43*K12) -> 636.06556 | O74: =IF((O43*O12)=0,#N/A,O43*O12) -> 777.26879 | S74: =IF((S43*S12)=0,#N/A,S43*S12) -> 355.91248 | W74: =IF((W43*W12)=0,#N/A,W43*W12) -> 533.73981 | AC74: =IF((AC43*AC12)=0,#N/A,AC43*AC12) -> 705.18224 | AH74: =IF((AH43*AH12)=0,#N/A,AH43*AH12) -> 686.26716
B75: 4 West North Central | C75: Single-family | D75: =IF((D44*D13)=0,#N/A,D44*D13) -> 9678.4525 | G75: =IF((G44*G13)=0,#N/A,G44*G13) -> 11183.157 | K75: =IF((K44*K13)=0,#N/A,K44*K13) -> 13155.484 | O75: =IF((O44*O13)=0,#N/A,O44*O13) -> 13348.516 | S75: =IF((S44*S13)=0,#N/A,S44*S13) -> 13717.589 | W75: =IF((W44*W13)=0,#N/A,W44*W13) -> 14075.714 | AC75: =IF((AC44*AC13)=0,#N/A,AC44*AC13) -> 14889.34 | AH75: =IF((AH44*AH13)=0,#N/A,AH44*AH13) -> 14081.766
B76: 4 West North Central | C76: Multifamily | D76: =IF((D45*D14)=0,#N/A,D45*D14) -> 1254.8684 | G76: =IF((G45*G14)=0,#N/A,G45*G14) -> 1246.228 | K76: =IF((K45*K14)=0,#N/A,K45*K14) -> 774.15903 | O76: =IF((O45*O14)=0,#N/A,O45*O14) -> 1233.7 | S76: =IF((S45*S14)=0,#N/A,S45*S14) -> 1063.5524 | W76: =IF((W45*W14)=0,#N/A,W45*W14) -> 1155.015 | AC76: =IF((AC45*AC14)=0,#N/A,AC45*AC14) -> 1469.8401 | AH76: =IF((AH45*AH14)=0,#N/A,AH45*AH14) -> 1548.4448
B77: 4 West North Central | C77: Mobile | D77: =IF((D46*D15)=0,#N/A,D46*D15) -> 380.71904 | G77: =IF((G46*G15)=0,#N/A,G46*G15) -> 433.95422 | K77: =IF((K46*K15)=0,#N/A,K46*K15) -> 339.02458 | O77: =IF((O46*O15)=0,#N/A,O46*O15) -> 393.42115 | S77: =IF((S46*S15)=0,#N/A,S46*S15) -> 379.346 | W77: =IF((W46*W15)=0,#N/A,W46*W15) -> 602.43798 | AC77: =IF((AC46*AC15)=0,#N/A,AC46*AC15) -> 396.30004 | AH77: =IF((AH46*AH15)=0,#N/A,AH46*AH15) -> 435.20105
... B92: 9 Pacific | C92: Mobile | D92: =IF((D61*D30)=0,#N/A,D61*D30) -> 690.73064 | G92: =IF((G61*G30)=0,#N/A,G61*G30) -> 325.08255 | K92: =IF((K61*K30)=0,#N/A,K61*K30) -> 1034.8319 | O92: =IF((O61*O30)=0,#N/A,O61*O30) -> 985.5184 | S92: =IF((S61*S30)=0,#N/A,S61*S30) -> 912.49251 | W92: =IF((W61*W30)=0,#N/A,W61*W30) -> 653.54262 | AC92: =IF((AC61*AC30)=0,#N/A,AC61*AC30) -> 795.23525 | AH92: =IF((AH61*AH30)=0,#N/A,AH61*AH30) -> 874.80208
B95: Millions of housing units
B96: Census division | C96: (All)
B97: Type | C97: (All)
B99: Values | C99: Total
B100: Sum of 1990 | C100: 93.990964
B101: Sum of 1991
B102: Sum of 1992
B103: Sum of 1993 | C103: 96.631492
B104: Sum of 1994
B105: Sum of 1995
B106: Sum of 1996
B107: Sum of 1997 | C107: 101.48117
B108: Sum of 1998
B109: Sum of 1999
B110: Sum of 2000
B111: Sum of 2001 | C111: 106.98927
B112: Sum of 2002
B113: Sum of 2003
B114: Sum of 2004
B115: Sum of 2005 | C115: 111.09062
B116: Sum of 2006
B117: Sum of 2007
B118: Sum of 2008
B119: Sum of 2009 | C119: 113.61623
B120: Sum of 2010
B121: Sum of 2011
B122: Sum of 2012
B123: Sum of 2013
B124: Sum of 2014
B125: Sum of 2015 | C125: 118.20825
B126: Sum of 2016
B127: Sum of 2017
B128: Sum of 2018
B129: Sum of 2019
B130: Sum of 2020 | C130: 123.52903
B135: Average SquareFootage
B136: Census division | C136: (All)
B137: Type | C137: (All)
B139: Data
B140: Sum of 1990 | C140: 33278.735
B141: Sum of 1991
B142: Sum of 1992
B143: Sum of 1993 | C143: 34195.976
B144: Sum of 1994
B145: Sum of 1995
B146: Sum of 1996
B147: Sum of 1997 | C147: 34285.059
B148: Sum of 1998
B149: Sum of 1999
B150: Sum of 2000
B151: Sum of 2001 | C151: 35896.726
B152: Sum of 2002
B153: Sum of 2003
B154: Sum of 2004
...

Sheet Chart Controls
B2: DivisionList | C2: FuelList | D2: BuildingList | E2: EndUseList | G2: Electricity | H2: Natural Gas | I2: Distillate | J2: LPG | K2: Kerosene | L2: Wood | M2: Solar | N2: (All) | P2: API cons fuel lookup
B3: 1 New England | C3: Electricity | D3: Single-family | E3: =HLOOKUP(SelectedFuel,$G$2:$N$22,F3,0) -> Cooking | F3: 2 | G3: Cooking | H3: Cooking | I3: Heating | J3: Heating | K3: Heating | L3: Heating | M3: Heating | N3: Cooking | P3: NGRCB | Q3: Natural Gas
B4: 2 Middle Atlantic | C4: Natural Gas | D4: Multifamily | E4: =HLOOKUP(SelectedFuel,$G$2:$N$22,F4,0) -> Cooling | F4: 3 | G4: Cooling | H4: Cooling | I4: HotWater | J4: HotWater | K4: HotWater | L4: SecHeating | M4: HotWater | N4: Cooling | P4: ESRCB | Q4: Electricity
B5: 3 East North Central | C5: Distillate | D5: Mobile | E5: =HLOOKUP(SelectedFuel,$G$2:$N$22,F5,0) -> ClothesWash | F5: 4 | G5: ClothesWash | H5: Dryer | I5: OtherAppl | J5: OtherAppl | K5: OtherAppl | L5: (All) | M5: SecHeating | N5: ClothesWash | P5: DFRCB | Q5: Distillate
B6: 4 West North Central | C6: LPG | D6: (All) | E6: =HLOOKUP(SelectedFuel,$G$2:$N$22,F6,0) -> Dryer | F6: 5 | G6: Dryer | H6: Heating | I6: SecHeating | J6: SecHeating | K6: SecHeating | M6: (All) | N6: Dryer | P6: PQRCB | Q6: LPG
B7: 5 South Atlantic | C7: Kerosene | E7: =HLOOKUP(SelectedFuel,$G$2:$N$22,F7,0) -> DishWash | F7: 6 | G7: DishWash | H7: HotWater | I7: (All) | J7: (All) | K7: (All) | N7: DishWash | P7: KSRCB | Q7: Kerosene
B8: 6 East South Central | C8: Wood | E8: =HLOOKUP(SelectedFuel,$G$2:$N$22,F8,0) -> ElecMotors | F8: 7 | G8: ElecMotors | H8: OtherAppl | N8: ElecMotors | P8: WDRCB | Q8: Wood
B9: 7 West South Central | C9: Solar | E9: =HLOOKUP(SelectedFuel,$G$2:$N$22,F9,0) -> ElecHtgElements | F9: 8 | G9: ElecHtgElements | H9: SecHeating | N9: ElecHtgElements
B10: 8 Mountain | C10: (All) | E10: =HLOOKUP(SelectedFuel,$G$2:$N$22,F10,0) -> Electronics | F10: 9 | G10: Electronics | H10: (All) | N10: Electronics | P10: API exp fuel lookup
B11: 9 Pacific | E11: =HLOOKUP(SelectedFuel,$G$2:$N$22,F11,0) -> FurnaceFans | F11: 10 | G11: FurnaceFans | N11: FurnaceFans | P11: NGRCV | Q11: Natural Gas
B12: (All) | E12: =HLOOKUP(SelectedFuel,$G$2:$N$22,F12,0) -> Freezer | F12: 11 | G12: Freezer | N12: Freezer | P12: ESRCV | Q12: Electricity
E13: =HLOOKUP(SelectedFuel,$G$2:$N$22,F13,0) -> Heating | F13: 12 | G13: Heating | N13: Heating | P13: DFRCV | Q13: Distillate
E14: =HLOOKUP(SelectedFuel,$G$2:$N$22,F14,0) -> HotWater | F14: 13 | G14: HotWater | N14: HotWater | P14: PQRCV | Q14: LPG
E15: =HLOOKUP(SelectedFuel,$G$2:$N$22,F15,0) -> Refrigerator | F15: 14 | G15: Refrigerator | N15: Refrigerator | P15: KSRCV | Q15: Kerosene
E16: =HLOOKUP(SelectedFuel,$G$2:$N$22,F16,0) -> Lighting | F16: 15 | G16: Lighting | N16: Lighting | P16: WDRCV | Q16: Wood
E17: =HLOOKUP(SelectedFuel,$G$2:$N$22,F17,0) -> OtherAppl | F17: 16 | G17: OtherAppl | N17: OtherAppl
E18: =HLOOKUP(SelectedFuel,$G$2:$N$22,F18,0) -> PC | F18: 17 | G18: PC | N18: PC
E19: =HLOOKUP(SelectedFuel,$G$2:$N$22,F19,0) -> SecHeating | F19: 18 | G19: SecHeating | N19: SecHeating
E20: =HLOOKUP(SelectedFuel,$G$2:$N$22,F20,0) -> DV | F20: 19 | G20: DV
E21: =HLOOKUP(SelectedFuel,$G$2:$N$22,F21,0) -> TV | F21: 20 | G21: TV | N21: TV
E22: =HLOOKUP(SelectedFuel,$G$2:$N$22,F22,0) -> (All) | F22: 21 | G22: (All) | N22: (All)
B24: SelectedDivision | C24: SelectedFuel | D24: SelectedBuilding | E24: SelectedEndUse
B25: (All) | C25: Electricity | D25: (All) | E25: (All)
B26: =MATCH(SelectedDivision,DivisionList,0) -> 10 | C26: =MATCH(SelectedFuel,FuelList,0) -> 1 | D26: =MATCH(SelectedBuilding,BuildingList,0) -> 4 | E26: =MATCH(SelectedEndUse,EndUseList,0) -> 20

Sheet Year Selections
B2: Please Set Parameters for Deflating and Display
B4: NEMS price base year for internal calculations
C5: 1987 | D5: =IF(ISERROR(HLOOKUP(NEMS_Internal_PriceYr,Deflators!$D$2:$BG$5,3,)),"It appears that no deflator is available for this base year.","")
B7: Price index base year for display
C8: 2023 | D8: =IF(ISERROR(HLOOKUP(Price_Base_yr,Deflators!$D$2:$BG$5,4,)),"It appears that no deflator is available for this base year.","")
B10: Last Year of SEDS Historical Data from EIA Web
C11: 2022
B13: RECS Year
C14: 2020
B16: First Year of NEMS Projections to Plot
C17: 2023
B19: Last Year of Historical Household Data
C20: 2020

Sheet State Codes
B2: State Energy Data System
B3: State Codes and Descriptions
B5: The State Codes are 2-character codes, following the U.S. Postal Service State abbreviations. Geographic
B6: areas used throughout SEDS includes the 50 States and the District of Columbia, and the United States.
B7: For production of crude oil and natural gas, Federal offshore regions are identified by X3 and X5.
B9: State Code | C9: State Name | D9: Census Division
B10: AK | C10: Alaska | D10: 9 Pacific
B11: AL | C11: Alabama | D11: 6 East South Central
B12: AR | C12: Arkansas | D12: 7 West South Central
B13: AZ | C13: Arizona | D13: 8 Mountain
B14: CA | C14: California | D14: 9 Pacific
B15: CO | C15: Colorado | D15: 8 Mountain
B16: CT | C16: Connecticut | D16: 1 New England
B17: DC | C17: District of Columbia | D17: 5 South Atlantic
B18: DE | C18: Delaware | D18: 5 South Atlantic
B19: FL | C19: Florida | D19: 5 South Atlantic
B20: GA | C20: Georgia | D20: 5 South Atlantic
... B60: WY | C60: Wyoming | D60: 8 Mountain
B61: X3 | C61: Federal Offshore, Gulf of Mexico
B62: X5 | C62: Federa Offshore, Pacific
B63: US | C63: United States
